Workbook

Sheet Amazon Model Unit Economics - V
K1: $7 per CFT | L1: 0.07
C2: Box 1 Dimensions (in) | J2: 84 | K2: 7 | L2: 0.18 | Q2: Product Size Tier | Z2: 0.06
A3: SKU | B3: Comments | C3: L (in) | D3: B (in) | E3: H (in) | F3: Gross wt (lbs) | G3: Ex-factory Price (INR) | H3: ## of boxes | I3: Box CFT | J3: Ex-factory cost | K3: Amazon SEND Shipping | L3: Import Duty (USD) | M3: Landed COGS | N3: Gross weight (lb) | O3: Dimensional weight (lb) | P3: Shipping weight (lb) | Q3: Shipping weight Class | R3: Longest side Class | S3: Median side Class | T3: Shortest side Class | U3: Final Product Size Tier | V3: Base Fare | W3: Incremental Fare per lb | X3: Cutoff Lb | Y3: FBA Fulfilment fees | Z3: FBA Storage fees | AA3: Landed COGS + FBA Fulfilment + FBA Warehousing | AB3: Return as % of Gross Sales | AC3: AZ Selling Fees as % of Gross Sales (15% of net + 3% return admin on returned items) | AD3: Ads as % of Gross Sales | AE3: Net Margin as % of Gross Sales | AF3: [Returns + Platform fees + Ads + Margin] as % of Gross Sales | AG3: [Landed COGS + FBA Fulfilment + FBA Warehousing] as % of Gross Sales | AH3: Theoratical Listing Price | AI3: ASP (Target selling Price) | AJ3: Current Ads as % of Gross Sales | AK3: Current Return % of Gross Sales | AL3: COGS% basis target price | AM3: Operating Margin% basis Target Selling Price | AN3: Net Margin% basis Target Selling Price | AO3: Profit + Ads % | AP3: Fullfillment fee% of Gross Sales | AQ3: ROE
A4: ET008 | B4: Universe | C4: 23 | D4: 15 | E4: 9 | F4: 33.3 | G4: 2200 | H4: 1 | I4: =C4*D4*E4/12^3 -> 1.796875 | J4: =G4/$J$2 -> 26.190476 | K4: =$K$2*I4 -> 12.578125 | L4: =J4*(1+$L$1)*$L$2 -> 5.0442857 | M4: =L4+K4+J4 -> 43.812887 | N4: =F4 -> 33.3 | O4: =roundup(C4*D4*E4/139,0) -> 23 | P4: =MAX(N4,O4) -> 33.3 | Q4: =if(P4<1,Cockpit!$H$7,if(P4<20,Cockpit!$H$8,if(P4<50,Cockpit!$H$9,if(P4<70,Cockpit!$H$10,if(P4<150,Cockpit!$H$11,Cockpit!$H$12))))) -> 3 | R4: =if(MAX(C4:E4)<15,Cockpit!$L$7,if(MAX(C4:E4)<18,Cockpit!$L$8,if(MAX(C4:E4)<59,Cockpit!$L$9,Cockpit!$L$10))) -> 3 | S4: =if(MEDIAN(C4:E4)<0.12,Cockpit!$L$7,if(MEDIAN(C4:E4)<14,Cockpit!$L$8,if(MEDIAN(C4:E4)<33,Cockpit!$L$9,Cockpit!$L$10))) -> 3 | T4: =if(MIN(C4:E4)<0.75,Cockpit!$L$7,if(MIN(C4:E4)<8,Cockpit!$L$8,if(MIN(C4:E4)<33,Cockpit!$L$9,Cockpit!$L$10))) -> 3 | U4: =MAX(Q4:T4) -> 3 | V4: =VLOOKUP($U4,Cockpit!$H$16:$M$22,3, FALSE) -> 10.65 | W4: =VLOOKUP($U4,Cockpit!$H$16:$M$22,4, FALSE) -> 0.38 | X4: =VLOOKUP($U4,Cockpit!$H$16:$M$22,5, FALSE) -> 1 | Y4: =V4+W4*(P4-X4) -> 22.924 | Z4: =$Z$2*AI4 -> 11.9994 | AA4: =M4+Y4+Z4 -> 78.736287 | AB4: 0.15 | AC4: =(1-AB4)*15% + 3%*AB4 -> 0.132 | AD4: 0.25 | AE4: 0.15 | AF4: =AB4+AC4+AD4+AE4 -> 0.682 | AG4: =1-AF4 -> 0.318 | AH4: =AA4/AG4 -> 247.59839 | AI4: 199.99 | AJ4: 0.25 | AK4: 0.15 | AL4: =M4/AI4 -> 0.21907539 | AM4: =1-AJ4-AK4-AC4-(Y4+Z4)/AI4 -> 0.29337427 | AN4: =1-AJ4-AK4-AC4-AA4/AI4 -> 0.07429888 | AO4: =AN4+AJ4 -> 0.32429888 | AP4: =Y4/AI4 -> 0.11462573 | AQ4: =AI4*AN4/M4 -> 0.33914755
A5: ET042MB(D) | B5: Universe | C5: 23 | D5: 6 | E5: 18 | F5: 14.1 | G5: 1650 | H5: 1 | I5: =C5*D5*E5/12^3 -> 1.4375 | J5: =G5/$J$2 -> 19.642857 | K5: =$K$2*I5 -> 10.0625 | L5: =J5*(1+$L$1)*$L$2 -> 3.7832143 | M5: =L5+K5+J5 -> 33.488571 | N5: =F5 -> 14.1 | O5: =roundup(C5*D5*E5/139,0) -> 18 | P5: =MAX(N5,O5) -> 18 | Q5: =if(P5<1,Cockpit!$H$7,if(P5<20,Cockpit!$H$8,if(P5<50,Cockpit!$H$9,if(P5<70,Cockpit!$H$10,if(P5<150,Cockpit!$H$11,Cockpit!$H$12))))) -> 2 | R5: =if(MAX(C5:E5)<15,Cockpit!$L$7,if(MAX(C5:E5)<18,Cockpit!$L$8,if(MAX(C5:E5)<59,Cockpit!$L$9,Cockpit!$L$10))) -> 3 | S5: =if(MEDIAN(C5:E5)<0.12,Cockpit!$L$7,if(MEDIAN(C5:E5)<14,Cockpit!$L$8,if(MEDIAN(C5:E5)<33,Cockpit!$L$9,Cockpit!$L$10))) -> 3 | T5: =if(MIN(C5:E5)<0.75,Cockpit!$L$7,if(MIN(C5:E5)<8,Cockpit!$L$8,if(MIN(C5:E5)<33,Cockpit!$L$9,Cockpit!$L$10))) -> 2 | U5: =MAX(Q5:T5) -> 3 | V5: =VLOOKUP($U5,Cockpit!$H$16:$M$22,3, FALSE) -> 10.65 | W5: =VLOOKUP($U5,Cockpit!$H$16:$M$22,4, FALSE) -> 0.38 | X5: =VLOOKUP($U5,Cockpit!$H$16:$M$22,5, FALSE) -> 1 | Y5: =V5+W5*(P5-X5) -> 17.11 | Z5: =$Z$2*AI5 -> 8.9994 | AA5: =M5+Y5+Z5 -> 59.597971 | AB5: 0.15 | AC5: =(1-AB5)*15% + 3%*AB5 -> 0.132 | AD5: 0.25 | AE5: 0.15 | AF5: =AB5+AC5+AD5+AE5 -> 0.682 | AG5: =1-AF5 -> 0.318 | AH5: =AA5/AG5 -> 187.415 | AI5: 149.99 | AJ5: 0.25 | AK5: 0.15 | AL5: =M5/AI5 -> 0.22327203 | AM5: =1-AJ5-AK5-AC5-(Y5+Z5)/AI5 -> 0.29392573 | AN5: =1-AJ5-AK5-AC5-AA5/AI5 -> 0.070653701 | AO5: =AN5+AJ5 -> 0.3206537 | AP5: =Y5/AI5 -> 0.11407427 | AQ5: =AI5*AN5/M5 -> 0.31644672
A6: ET042MW | B6: Universe | C6: 23 | D6: 6 | E6: 18 | F6: 14.1 | G6: 1650 | H6: 1 | I6: =C6*D6*E6/12^3 -> 1.4375 | J6: =G6/$J$2 -> 19.642857 | K6: =$K$2*I6 -> 10.0625 | L6: =J6*(1+$L$1)*$L$2 -> 3.7832143 | M6: =L6+K6+J6 -> 33.488571 | N6: =F6 -> 14.1 | O6: =roundup(C6*D6*E6/139,0) -> 18 | P6: =MAX(N6,O6) -> 18 | Q6: =if(P6<1,Cockpit!$H$7,if(P6<20,Cockpit!$H$8,if(P6<50,Cockpit!$H$9,if(P6<70,Cockpit!$H$10,if(P6<150,Cockpit!$H$11,Cockpit!$H$12))))) -> 2 | R6: =if(MAX(C6:E6)<15,Cockpit!$L$7,if(MAX(C6:E6)<18,Cockpit!$L$8,if(MAX(C6:E6)<59,Cockpit!$L$9,Cockpit!$L$10))) -> 3 | S6: =if(MEDIAN(C6:E6)<0.12,Cockpit!$L$7,if(MEDIAN(C6:E6)<14,Cockpit!$L$8,if(MEDIAN(C6:E6)<33,Cockpit!$L$9,Cockpit!$L$10))) -> 3 | T6: =if(MIN(C6:E6)<0.75,Cockpit!$L$7,if(MIN(C6:E6)<8,Cockpit!$L$8,if(MIN(C6:E6)<33,Cockpit!$L$9,Cockpit!$L$10))) -> 2 | U6: =MAX(Q6:T6) -> 3 | V6: =VLOOKUP($U6,Cockpit!$H$16:$M$22,3, FALSE) -> 10.65 | W6: =VLOOKUP($U6,Cockpit!$H$16:$M$22,4, FALSE) -> 0.38 | X6: =VLOOKUP($U6,Cockpit!$H$16:$M$22,5, FALSE) -> 1 | Y6: =V6+W6*(P6-X6) -> 17.11 | Z6: =$Z$2*AI6 -> 8.9994 | AA6: =M6+Y6+Z6 -> 59.597971 | AB6: 0.15 | AC6: =(1-AB6)*15% + 3%*AB6 -> 0.132 | AD6: 0.25 | AE6: 0.15 | AF6: =AB6+AC6+AD6+AE6 -> 0.682 | AG6: =1-AF6 -> 0.318 | AH6: =AA6/AG6 -> 187.415 | AI6: 149.99 | AJ6: 0.25 | AK6: 0.15 | AL6: =M6/AI6 -> 0.22327203 | AM6: =1-AJ6-AK6-AC6-(Y6+Z6)/AI6 -> 0.29392573 | AN6: =1-AJ6-AK6-AC6-AA6/AI6 -> 0.070653701 | AO6: =AN6+AJ6 -> 0.3206537 | AP6: =Y6/AI6 -> 0.11407427 | AQ6: =AI6*AN6/M6 -> 0.31644672
A7: ET003-N | B7: Universe | C7: 18 | D7: 18.5 | E7: 8 | F7: 21.6 | G7: 2700 | H7: 1 | I7: =C7*D7*E7/12^3 -> 1.5416667 | J7: =G7/$J$2 -> 32.142857 | K7: =$K$2*I7 -> 10.791667 | L7: =J7*(1+$L$1)*$L$2 -> 6.1907143 | M7: =L7+K7+J7 -> 49.125238 | N7: =F7 -> 21.6 | O7: =roundup(C7*D7*E7/139,0) -> 20 | P7: =MAX(N7,O7) -> 21.6 | Q7: =if(P7<1,Cockpit!$H$7,if(P7<20,Cockpit!$H$8,if(P7<50,Cockpit!$H$9,if(P7<70,Cockpit!$H$10,if(P7<150,Cockpit!$H$11,Cockpit!$H$12))))) -> 3 | R7: =if(MAX(C7:E7)<15,Cockpit!$L$7,if(MAX(C7:E7)<18,Cockpit!$L$8,if(MAX(C7:E7)<59,Cockpit!$L$9,Cockpit!$L$10))) -> 3 | S7: =if(MEDIAN(C7:E7)<0.12,Cockpit!$L$7,if(MEDIAN(C7:E7)<14,Cockpit!$L$8,if(MEDIAN(C7:E7)<33,Cockpit!$L$9,Cockpit!$L$10))) -> 3 | T7: =if(MIN(C7:E7)<0.75,Cockpit!$L$7,if(MIN(C7:E7)<8,Cockpit!$L$8,if(MIN(C7:E7)<33,Cockpit!$L$9,Cockpit!$L$10))) -> 3 | U7: =MAX(Q7:T7) -> 3 | V7: =VLOOKUP($U7,Cockpit!$H$16:$M$22,3, FALSE) -> 10.65 | W7: =VLOOKUP($U7,Cockpit!$H$16:$M$22,4, FALSE) -> 0.38 | X7: =VLOOKUP($U7,Cockpit!$H$16:$M$22,5, FALSE) -> 1 | Y7: =V7+W7*(P7-X7) -> 18.478 | Z7: =$Z$2*AI7 -> 11.94 | AA7: =M7+Y7+Z7 -> 79.543238 | AB7: 0.15 | AC7: =(1-AB7)*15% + 3%*AB7 -> 0.132 | AD7: 0.25 | AE7: 0.15 | AF7: =AB7+AC7+AD7+AE7 -> 0.682 | AG7: =1-AF7 -> 0.318 | AH7: =AA7/AG7 -> 250.13597 | AI7: 199 | AJ7: 0.25 | AK7: 0.15 | AL7: =M7/AI7 -> 0.24686049 | AM7: =1-AJ7-AK7-AC7-(Y7+Z7)/AI7 -> 0.31514573 | AN7: =1-AJ7-AK7-AC7-AA7/AI7 -> 0.068285236 | AO7: =AN7+AJ7 -> 0.31828524 | AP7: =Y7/AI7 -> 0.092854271 | AQ7: =AI7*AN7/M7 -> 0.27661468
A8: ET003-W | B8: Universe | C8: 18 | D8: 18.5 | E8: 8 | F8: 21.6 | G8: 2700 | H8: 1 | I8: =C8*D8*E8/12^3 -> 1.5416667 | J8: =G8/$J$2 -> 32.142857 | K8: =$K$2*I8 -> 10.791667 | L8: =J8*(1+$L$1)*$L$2 -> 6.1907143 | M8: =L8+K8+J8 -> 49.125238 | N8: =F8 -> 21.6 | O8: =roundup(C8*D8*E8/139,0) -> 20 | P8: =MAX(N8,O8) -> 21.6 | Q8: =if(P8<1,Cockpit!$H$7,if(P8<20,Cockpit!$H$8,if(P8<50,Cockpit!$H$9,if(P8<70,Cockpit!$H$10,if(P8<150,Cockpit!$H$11,Cockpit!$H$12))))) -> 3 | R8: =if(MAX(C8:E8)<15,Cockpit!$L$7,if(MAX(C8:E8)<18,Cockpit!$L$8,if(MAX(C8:E8)<59,Cockpit!$L$9,Cockpit!$L$10))) -> 3 | S8: =if(MEDIAN(C8:E8)<0.12,Cockpit!$L$7,if(MEDIAN(C8:E8)<14,Cockpit!$L$8,if(MEDIAN(C8:E8)<33,Cockpit!$L$9,Cockpit!$L$10))) -> 3 | T8: =if(MIN(C8:E8)<0.75,Cockpit!$L$7,if(MIN(C8:E8)<8,Cockpit!$L$8,if(MIN(C8:E8)<33,Cockpit!$L$9,Cockpit!$L$10))) -> 3 | U8: =MAX(Q8:T8) -> 3 | V8: =VLOOKUP($U8,Cockpit!$H$16:$M$22,3, FALSE) -> 10.65 | W8: =VLOOKUP($U8,Cockpit!$H$16:$M$22,4, FALSE) -> 0.38 | X8: =VLOOKUP($U8,Cockpit!$H$16:$M$22,5, FALSE) -> 1 | Y8: =V8+W8*(P8-X8) -> 18.478 | Z8: =$Z$2*AI8 -> 11.94 | AA8: =M8+Y8+Z8 -> 79.543238 | AB8: 0.15 | AC8: =(1-AB8)*15% + 3%*AB8 -> 0.132 | AD8: 0.25 | AE8: 0.15 | AF8: =AB8+AC8+AD8+AE8 -> 0.682 | AG8: =1-AF8 -> 0.318 | AH8: =AA8/AG8 -> 250.13597 | AI8: 199 | AJ8: 0.25 | AK8: 0.15 | AL8: =M8/AI8 -> 0.24686049 | AM8: =1-AJ8-AK8-AC8-(Y8+Z8)/AI8 -> 0.31514573 | AN8: =1-AJ8-AK8-AC8-AA8/AI8 -> 0.068285236 | AO8: =AN8+AJ8 -> 0.31828524 | AP8: =Y8/AI8 -> 0.092854271 | AQ8: =AI8*AN8/M8 -> 0.27661468
A9: ET009 | B9: Universe | C9: 15.5 | D9: 13 | E9: 10 | F9: 21.2 | G9: 1800 | H9: 1 | I9: =C9*D9*E9/12^3 -> 1.166088 | J9: =G9/$J$2 -> 21.428571 | K9: =$K$2*I9 -> 8.1626157 | L9: =J9*(1+$L$1)*$L$2 -> 4.1271429 | M9: =L9+K9+J9 -> 33.71833 | N9: =F9 -> 21.2 | O9: =roundup(C9*D9*E9/139,0) -> 15 | P9: =MAX(N9,O9) -> 21.2 | Q9: =if(P9<1,Cockpit!$H$7,if(P9<20,Cockpit!$H$8,if(P9<50,Cockpit!$H$9,if(P9<70,Cockpit!$H$10,if(P9<150,Cockpit!$H$11,Cockpit!$H$12))))) -> 3 | R9: =if(MAX(C9:E9)<15,Cockpit!$L$7,if(MAX(C9:E9)<18,Cockpit!$L$8,if(MAX(C9:E9)<59,Cockpit!$L$9,Cockpit!$L$10))) -> 2 | S9: =if(MEDIAN(C9:E9)<0.12,Cockpit!$L$7,if(MEDIAN(C9:E9)<14,Cockpit!$L$8,if(MEDIAN(C9:E9)<33,Cockpit!$L$9,Cockpit!$L$10))) -> 2 | T9: =if(MIN(C9:E9)<0.75,Cockpit!$L$7,if(MIN(C9:E9)<8,Cockpit!$L$8,if(MIN(C9:E9)<33,Cockpit!$L$9,Cockpit!$L$10))) -> 3 | U9: =MAX(Q9:T9) -> 3 | V9: =VLOOKUP($U9,Cockpit!$H$16:$M$22,3, FALSE) -> 10.65 | W9: =VLOOKUP($U9,Cockpit!$H$16:$M$22,4, FALSE) -> 0.38 | X9: =VLOOKUP($U9,Cockpit!$H$16:$M$22,5, FALSE) -> 1 | Y9: =V9+W9*(P9-X9) -> 18.326 | Z9: =$Z$2*AI9 -> 8.9994 | AA9: =M9+Y9+Z9 -> 61.04373 | AB9: 0.15 | AC9: =(1-AB9)*15% + 3%*AB9 -> 0.132 | AD9: 0.25 | AE9: 0.15 | AF9: =AB9+AC9+AD9+AE9 -> 0.682 | AG9: =1-AF9 -> 0.318 | AH9: =AA9/AG9 -> 191.96142 | AI9: 149.99 | AJ9: 0.25 | AK9: 0.15 | AL9: =M9/AI9 -> 0.22480385 | AM9: =1-AJ9-AK9-AC9-(Y9+Z9)/AI9 -> 0.28581852 | AN9: =1-AJ9-AK9-AC9-AA9/AI9 -> 0.061014667 | AO9: =AN9+AJ9 -> 0.31101467 | AP9: =Y9/AI9 -> 0.12218148 | AQ9: =AI9*AN9/M9 -> 0.27141291
A10: ET012 | B10: Universe | C10: 24.5 | D10: 20 | E10: 6.5 | F10: 21.2 | G10: 1980 | H10: 1 | I10: =C10*D10*E10/12^3 -> 1.8431713 | J10: =G10/$J$2 -> 23.571429 | K10: =$K$2*I10 -> 12.902199 | L10: =J10*(1+$L$1)*$L$2 -> 4.5398571 | M10: =L10+K10+J10 -> 41.013485 | N10: =F10 -> 21.2 | O10: =roundup(C10*D10*E10/139,0) -> 23 | P10: =MAX(N10,O10) -> 23 | Q10: =if(P10<1,Cockpit!$H$7,if(P10<20,Cockpit!$H$8,if(P10<50,Cockpit!$H$9,if(P10<70,Cockpit!$H$10,if(P10<150,Cockpit!$H$11,Cockpit!$H$12))))) -> 3 | R10: =if(MAX(C10:E10)<15,Cockpit!$L$7,if(MAX(C10:E10)<18,Cockpit!$L$8,if(MAX(C10:E10)<59,Cockpit!$L$9,Cockpit!$L$10))) -> 3 | S10: =if(MEDIAN(C10:E10)<0.12,Cockpit!$L$7,if(MEDIAN(C10:E10)<14,Cockpit!$L$8,if(MEDIAN(C10:E10)<33,Cockpit!$L$9,Cockpit!$L$10))) -> 3 | T10: =if(MIN(C10:E10)<0.75,Cockpit!$L$7,if(MIN(C10:E10)<8,Cockpit!$L$8,if(MIN(C10:E10)<33,Cockpit!$L$9,Cockpit!$L$10))) -> 2 | U10: =MAX(Q10:T10) -> 3 | V10: =VLOOKUP($U10,Cockpit!$H$16:$M$22,3, FALSE) -> 10.65 | W10: =VLOOKUP($U10,Cockpit!$H$16:$M$22,4, FALSE) -> 0.38 | X10: =VLOOKUP($U10,Cockpit!$H$16:$M$22,5, FALSE) -> 1 | Y10: =V10+W10*(P10-X10) -> 19.01 | Z10: =$Z$2*AI10 -> 9 | AA10: =M10+Y10+Z10 -> 69.023485 | AB10: 0.15 | AC10: =(1-AB10)*15% + 3%*AB10 -> 0.132 | AD10: 0.25 | AE10: 0.15 | AF10: =AB10+AC10+AD10+AE10 -> 0.682 | AG10: =1-AF10 -> 0.318 | AH10: =AA10/AG10 -> 217.05498 | AI10: 150 | AJ10: 0.25 | AK10: 0.1 | AL10: =M10/AI10 -> 0.27342323 | AM10: =1-AJ10-AK10-AC10-(Y10+Z10)/AI10 -> 0.33126667 | AN10: =1-AJ10-AK10-AC10-AA10/AI10 -> 0.057843435 | AO10: =AN10+AJ10 -> 0.30784343 | AP10: =Y10/AI10 -> 0.12673333 | AQ10: =AI10*AN10/M10 -> 0.21155274
A11: DR005MW | B11: Universe | C11: 14.5 | D11: 15 | E11: 6.5 | F11: 8.8 | G11: 1200 | H11: 1 | I11: =C11*D11*E11/12^3 -> 0.81814236 | J11: =G11/$J$2 -> 14.285714 | K11: =$K$2*I11 -> 5.7269965 | L11: =J11*(1+$L$1)*$L$2 -> 2.7514286 | M11: =L11+K11+J11 -> 22.764139 | N11: =F11 -> 8.8 | O11: =roundup(C11*D11*E11/139,0) -> 11 | P11: =MAX(N11,O11) -> 11 | Q11: =if(P11<1,Cockpit!$H$7,if(P11<20,Cockpit!$H$8,if(P11<50,Cockpit!$H$9,if(P11<70,Cockpit!$H$10,if(P11<150,Cockpit!$H$11,Cockpit!$H$12))))) -> 2 | R11: =if(MAX(C11:E11)<15,Cockpit!$L$7,if(MAX(C11:E11)<18,Cockpit!$L$8,if(MAX(C11:E11)<59,Cockpit!$L$9,Cockpit!$L$10))) -> 2 | S11: =if(MEDIAN(C11:E11)<0.12,Cockpit!$L$7,if(MEDIAN(C11:E11)<14,Cockpit!$L$8,if(MEDIAN(C11:E11)<33,Cockpit!$L$9,Cockpit!$L$10))) -> 3 | T11: =if(MIN(C11:E11)<0.75,Cockpit!$L$7,if(MIN(C11:E11)<8,Cockpit!$L$8,if(MIN(C11:E11)<33,Cockpit!$L$9,Cockpit!$L$10))) -> 2 | U11: =MAX(Q11:T11) -> 3 | V11: =VLOOKUP($U11,Cockpit!$H$16:$M$22,3, FALSE) -> 10.65 | W11: =VLOOKUP($U11,Cockpit!$H$16:$M$22,4, FALSE) -> 0.38 | X11: =VLOOKUP($U11,Cockpit!$H$16:$M$22,5, FALSE) -> 1 | Y11: =V11+W11*(P11-X11) -> 14.45 | Z11: =$Z$2*AI11 -> 5.9994 | AA11: =M11+Y11+Z11 -> 43.213539 | AB11: 0.15 | AC11: =(1-AB11)*15% + 3%*AB11 -> 0.132 | AD11: 0.25 | AE11: 0.15 | AF11: =AB11+AC11+AD11+AE11 -> 0.682 | AG11: =1-AF11 -> 0.318 | AH11: =AA11/AG11 -> 135.89163 | AI11: 99.99 | AJ11: 0.25 | AK11: 0.15 | AL11: =M11/AI11 -> 0.22766416 | AM11: =1-AJ11-AK11-AC11-(Y11+Z11)/AI11 -> 0.26348555 | AN11: =1-AJ11-AK11-AC11-AA11/AI11 -> 0.035821388 | AO11: =AN11+AJ11 -> 0.28582139 | AP11: =Y11/AI11 -> 0.14451445 | AQ11: =AI11*AN11/M11 -> 0.15734312
A12: DR002MTMW | B12: Universe | C12: 14.5 | D12: 14.5 | E12: 26.5 | F12: 19 | G12: 1449.84 | H12: 1 | I12: =C12*D12*E12/12^3 -> 3.22432 | J12: =G12/$J$2 -> 17.26 | K12: =$K$2*I12 -> 22.57024 | L12: =J12*(1+$L$1)*$L$2 -> 3.324276 | M12: =L12+K12+J12 -> 43.154516 | N12: =F12 -> 19 | O12: =roundup(C12*D12*E12/139,0) -> 41 | P12: =MAX(N12,O12) -> 41 | Q12: =if(P12<1,Cockpit!$H$7,if(P12<20,Cockpit!$H$8,if(P12<50,Cockpit!$H$9,if(P12<70,Cockpit!$H$10,if(P12<150,Cockpit!$H$11,Cockpit!$H$12))))) -> 3 | R12: =if(MAX(C12:E12)<15,Cockpit!$L$7,if(MAX(C12:E12)<18,Cockpit!$L$8,if(MAX(C12:E12)<59,Cockpit!$L$9,Cockpit!$L$10))) -> 3 | S12: =if(MEDIAN(C12:E12)<0.12,Cockpit!$L$7,if(MEDIAN(C12:E12)<14,Cockpit!$L$8,if(MEDIAN(C12:E12)<33,Cockpit!$L$9,Cockpit!$L$10))) -> 3 | T12: =if(MIN(C12:E12)<0.75,Cockpit!$L$7,if(MIN(C12:E12)<8,Cockpit!$L$8,if(MIN(C12:E12)<33,Cockpit!$L$9,Cockpit!$L$10))) -> 3 | U12: =MAX(Q12:T12) -> 3 | V12: =VLOOKUP($U12,Cockpit!$H$16:$M$22,3, FALSE) -> 10.65 | W12: =VLOOKUP($U12,Cockpit!$H$16:$M$22,4, FALSE) -> 0.38 | X12: =VLOOKUP($U12,Cockpit!$H$16:$M$22,5, FALSE) -> 1 | Y12: =V12+W12*(P12-X12) -> 25.85 | Z12: =$Z$2*AI12 -> 8.9994 | AA12: =M12+Y12+Z12 -> 78.003916 | AB12: 0.15 | AC12: =(1-AB12)*15% + 3%*AB12 -> 0.132 | AD12: 0.25 | AE12: 0.15 | AF12: =AB12+AC12+AD12+AE12 -> 0.682 | AG12: =1-AF12 -> 0.318 | AH12: =AA12/AG12 -> 245.29533 | AI12: 149.99 | AJ12: 0.15 | AK12: 0.15 | AL12: =M12/AI12 -> 0.28771596 | AM12: =1-AJ12-AK12-AC12-(Y12+Z12)/AI12 -> 0.33565518 | AN12: =1-AJ12-AK12-AC12-AA12/AI12 -> 0.047939222 | AO12: =AN12+AJ12 -> 0.19793922 | AP12: =Y12/AI12 -> 0.17234482 | AQ12: =AI12*AN12/M12 -> 0.16661996
A13: DR001MW | B13: Universe | C13: 14 | D13: 14 | E13: 26 | F13: 11.9 | G13: 1249.92 | H13: 1 | I13: =C13*D13*E13/12^3 -> 2.9490741 | J13: =G13/$J$2 -> 14.88 | K13: =$K$2*I13 -> 20.643519 | L13: =J13*(1+$L$1)*$L$2 -> 2.865888 | M13: =L13+K13+J13 -> 38.389407 | N13: =F13 -> 11.9 | O13: =roundup(C13*D13*E13/139,0) -> 37 | P13: =MAX(N13,O13) -> 37 | Q13: =if(P13<1,Cockpit!$H$7,if(P13<20,Cockpit!$H$8,if(P13<50,Cockpit!$H$9,if(P13<70,Cockpit!$H$10,if(P13<150,Cockpit!$H$11,Cockpit!$H$12))))) -> 3 | R13: =if(MAX(C13:E13)<15,Cockpit!$L$7,if(MAX(C13:E13)<18,Cockpit!$L$8,if(MAX(C13:E13)<59,Cockpit!$L$9,Cockpit!$L$10))) -> 3 | S13: =if(MEDIAN(C13:E13)<0.12,Cockpit!$L$7,if(MEDIAN(C13:E13)<14,Cockpit!$L$8,if(MEDIAN(C13:E13)<33,Cockpit!$L$9,Cockpit!$L$10))) -> 3 | T13: =if(MIN(C13:E13)<0.75,Cockpit!$L$7,if(MIN(C13:E13)<8,Cockpit!$L$8,if(MIN(C13:E13)<33,Cockpit!$L$9,Cockpit!$L$10))) -> 3 | U13: =MAX(Q13:T13) -> 3 | V13: =VLOOKUP($U13,Cockpit!$H$16:$M$22,3, FALSE) -> 10.65 | W13: =VLOOKUP($U13,Cockpit!$H$16:$M$22,4, FALSE) -> 0.38 | X13: =VLOOKUP($U13,Cockpit!$H$16:$M$22,5, FALSE) -> 1 | Y13: =V13+W13*(P13-X13) -> 24.33 | Z13: =$Z$2*AI13 -> 8.3994 | AA13: =M13+Y13+Z13 -> 71.118807 | AB13: 0.15 | AC13: =(1-AB13)*15% + 3%*AB13 -> 0.132 | AD13: 0.25 | AE13: 0.15 | AF13: =AB13+AC13+AD13+AE13 -> 0.682 | AG13: =1-AF13 -> 0.318 | AH13: =AA13/AG13 -> 223.64405 | AI13: 139.99 | AJ13: 0.15 | AK13: 0.15 | AL13: =M13/AI13 -> 0.27422963 | AM13: =1-AJ13-AK13-AC13-(Y13+Z13)/AI13 -> 0.33420187 | AN13: =1-AJ13-AK13-AC13-AA13/AI13 -> 0.059972237 | AO13: =AN13+AJ13 -> 0.20997224 | AP13: =Y13/AI13 -> 0.17379813 | AQ13: =AI13*AN13/M13 -> 0.21869349
A14: DR004MB | B14: Kill | C14: 14.5 | D14: 14.5 | E14: 7.5 | F14: 10.4 | G14: 1250 | H14: 1 | I14: =C14*D14*E14/12^3 -> 0.9125434 | J14: =G14/$J$2 -> 14.880952 | K14: =$K$2*I14 -> 6.3878038 | L14: =J14*(1+$L$1)*$L$2 -> 2.8660714 | M14: =L14+K14+J14 -> 24.134828 | N14: =F14 -> 10.4 | O14: =roundup(C14*D14*E14/139,0) -> 12 | P14: =MAX(N14,O14) -> 12 | Q14: =if(P14<1,Cockpit!$H$7,if(P14<20,Cockpit!$H$8,if(P14<50,Cockpit!$H$9,if(P14<70,Cockpit!$H$10,if(P14<150,Cockpit!$H$11,Cockpit!$H$12))))) -> 2 | R14: =if(MAX(C14:E14)<15,Cockpit!$L$7,if(MAX(C14:E14)<18,Cockpit!$L$8,if(MAX(C14:E14)<59,Cockpit!$L$9,Cockpit!$L$10))) -> 1 | S14: =if(MEDIAN(C14:E14)<0.12,Cockpit!$L$7,if(MEDIAN(C14:E14)<14,Cockpit!$L$8,if(MEDIAN(C14:E14)<33,Cockpit!$L$9,Cockpit!$L$10))) -> 3 | T14: =if(MIN(C14:E14)<0.75,Cockpit!$L$7,if(MIN(C14:E14)<8,Cockpit!$L$8,if(MIN(C14:E14)<33,Cockpit!$L$9,Cockpit!$L$10))) -> 2 | U14: =MAX(Q14:T14) -> 3 | V14: =VLOOKUP($U14,Cockpit!$H$16:$M$22,3, FALSE) -> 10.65 | W14: =VLOOKUP($U14,Cockpit!$H$16:$M$22,4, FALSE) -> 0.38 | X14: =VLOOKUP($U14,Cockpit!$H$16:$M$22,5, FALSE) -> 1 | Y14: =V14+W14*(P14-X14) -> 14.83 | Z14: =$Z$2*AI14 -> 4.1994 | AA14: =M14+Y14+Z14 -> 43.164228 | AB14: 0.15 | AC14: =(1-AB14)*15% + 3%*AB14 -> 0.132 | AD14: 0.25 | AE14: 0.15 | AF14: =AB14+AC14+AD14+AE14 -> 0.682 | AG14: =1-AF14 -> 0.318 | AH14: =AA14/AG14 -> 135.73656 | AI14: 69.99 | AJ14: 0.25 | AK14: 0.1 | AL14: =M14/AI14 -> 0.34483251 | AM14: =1-AJ14-AK14-AC14-(Y14+Z14)/AI14 -> 0.24611259 | AN14: =1-AJ14-AK14-AC14-AA14/AI14 -> -0.098719926 | AO14: =AN14+AJ14 -> 0.15128007 | AP14: =Y14/AI14 -> 0.21188741 | AQ14: =AI14*AN14/M14 -> -0.28628369
A15: ET067MB | C15: 24 | D15: 20.5 | E15: 6.5 | F15: 18.0779 | G15: =2500*0.65 -> 1625 | H15: 1 | I15: =C15*D15*E15/12^3 -> 1.8506944 | J15: =G15/$J$2 -> 19.345238 | K15: =$K$2*I15 -> 12.954861 | L15: =J15*(1+$L$1)*$L$2 -> 3.7258929 | M15: =L15+K15+J15 -> 36.025992 | N15: =F15 -> 18.0779 | O15: =roundup(C15*D15*E15/139,0) -> 24 | P15: =MAX(N15,O15) -> 24 | Q15: =if(P15<1,Cockpit!$H$7,if(P15<20,Cockpit!$H$8,if(P15<50,Cockpit!$H$9,if(P15<70,Cockpit!$H$10,if(P15<150,Cockpit!$H$11,Cockpit!$H$12))))) -> 3 | R15: =if(MAX(C15:E15)<15,Cockpit!$L$7,if(MAX(C15:E15)<18,Cockpit!$L$8,if(MAX(C15:E15)<59,Cockpit!$L$9,Cockpit!$L$10))) -> 3 | S15: =if(MEDIAN(C15:E15)<0.12,Cockpit!$L$7,if(MEDIAN(C15:E15)<14,Cockpit!$L$8,if(MEDIAN(C15:E15)<33,Cockpit!$L$9,Cockpit!$L$10))) -> 3 | T15: =if(MIN(C15:E15)<0.75,Cockpit!$L$7,if(MIN(C15:E15)<8,Cockpit!$L$8,if(MIN(C15:E15)<33,Cockpit!$L$9,Cockpit!$L$10))) -> 2 | U15: =MAX(Q15:T15) -> 3 | V15: =VLOOKUP($U15,Cockpit!$H$16:$M$22,3, FALSE) -> 10.65 | W15: =VLOOKUP($U15,Cockpit!$H$16:$M$22,4, FALSE) -> 0.38 | X15: =VLOOKUP($U15,Cockpit!$H$16:$M$22,5, FALSE) -> 1 | Y15: =V15+W15*(P15-X15) -> 19.39 | Z15: =$Z$2*AI15 -> 8.9994 | AA15: =M15+Y15+Z15 -> 64.415392 | AB15: 0.15 | AC15: =(1-AB15)*15% + 3%*AB15 -> 0.132 | AD15: 0.25 | AE15: 0.15 | AF15: =AB15+AC15+AD15+AE15 -> 0.682 | AG15: =1-AF15 -> 0.318 | AH15: =AA15/AG15 -> 202.56413 | AI15: 149.99 | AJ15: 0.25 | AK15: 0.15 | AL15: =M15/AI15 -> 0.24018929 | AM15: =1-AJ15-AK15-AC15-(Y15+Z15)/AI15 -> 0.27872472 | AN15: =1-AJ15-AK15-AC15-AA15/AI15 -> 0.038535422 | AO15: =AN15+AJ15 -> 0.28853542 | AP15: =Y15/AI15 -> 0.12927528 | AQ15: =AI15*AN15/M15 -> 0.16043772
A16: DR003MW | B16: Kill | C16: 14.5 | D16: 15 | E16: 5.5 | F16: 7.7 | G16: 1150 | H16: 1 | I16: =C16*D16*E16/12^3 -> 0.69227431 | J16: =G16/$J$2 -> 13.690476 | K16: =$K$2*I16 -> 4.8459201 | L16: =J16*(1+$L$1)*$L$2 -> 2.6367857 | M16: =L16+K16+J16 -> 21.173182 | N16: =F16 -> 7.7 | O16: =roundup(C16*D16*E16/139,0) -> 9 | P16: =MAX(N16,O16) -> 9 | Q16: =if(P16<1,Cockpit!$H$7,if(P16<20,Cockpit!$H$8,if(P16<50,Cockpit!$H$9,if(P16<70,Cockpit!$H$10,if(P16<150,Cockpit!$H$11,Cockpit!$H$12))))) -> 2 | R16: =if(MAX(C16:E16)<15,Cockpit!$L$7,if(MAX(C16:E16)<18,Cockpit!$L$8,if(MAX(C16:E16)<59,Cockpit!$L$9,Cockpit!$L$10))) -> 2 | S16: =if(MEDIAN(C16:E16)<0.12,Cockpit!$L$7,if(MEDIAN(C16:E16)<14,Cockpit!$L$8,if(MEDIAN(C16:E16)<33,Cockpit!$L$9,Cockpit!$L$10))) -> 3 | T16: =if(MIN(C16:E16)<0.75,Cockpit!$L$7,if(MIN(C16:E16)<8,Cockpit!$L$8,if(MIN(C16:E16)<33,Cockpit!$L$9,Cockpit!$L$10))) -> 2 | U16: =MAX(Q16:T16) -> 3 | V16: =VLOOKUP($U16,Cockpit!$H$16:$M$22,3, FALSE) -> 10.65 | W16: =VLOOKUP($U16,Cockpit!$H$16:$M$22,4, FALSE) -> 0.38 | X16: =VLOOKUP($U16,Cockpit!$H$16:$M$22,5, FALSE) -> 1 | Y16: =V16+W16*(P16-X16) -> 13.69 | Z16: =$Z$2*AI16 -> 3.5994 | AA16: =M16+Y16+Z16 -> 38.462582 | AB16: 0.15 | AC16: =(1-AB16)*15% + 3%*AB16 -> 0.132 | AD16: 0.25 | AE16: 0.15 | AF16: =AB16+AC16+AD16+AE16 -> 0.682 | AG16: =1-AF16 -> 0.318 | AH16: =AA16/AG16 -> 120.95152 | AI16: 59.99 | AJ16: 0.25 | AK16: 0.1 | AL16: =M16/AI16 -> 0.35294519 | AM16: =1-AJ16-AK16-AC16-(Y16+Z16)/AI16 -> 0.2297953 | AN16: =1-AJ16-AK16-AC16-AA16/AI16 -> -0.12314989 | AO16: =AN16+AJ16 -> 0.12685011 | AP16: =Y16/AI16 -> 0.2282047 | AQ16: =AI16*AN16/M16 -> -0.34892073
A17: DR003MWW(D) | B17: Kill | C17: 14.5 | D17: 15 | E17: 5.5 | F17: 7.7 | G17: 1150 | H17: 1 | I17: =C17*D17*E17/12^3 -> 0.69227431 | J17: =G17/$J$2 -> 13.690476 | K17: =$K$2*I17 -> 4.8459201 | L17: =J17*(1+$L$1)*$L$2 -> 2.6367857 | M17: =L17+K17+J17 -> 21.173182 | N17: =F17 -> 7.7 | O17: =roundup(C17*D17*E17/139,0) -> 9 | P17: =MAX(N17,O17) -> 9 | Q17: =if(P17<1,Cockpit!$H$7,if(P17<20,Cockpit!$H$8,if(P17<50,Cockpit!$H$9,if(P17<70,Cockpit!$H$10,if(P17<150,Cockpit!$H$11,Cockpit!$H$12))))) -> 2 | R17: =if(MAX(C17:E17)<15,Cockpit!$L$7,if(MAX(C17:E17)<18,Cockpit!$L$8,if(MAX(C17:E17)<59,Cockpit!$L$9,Cockpit!$L$10))) -> 2 | S17: =if(MEDIAN(C17:E17)<0.12,Cockpit!$L$7,if(MEDIAN(C17:E17)<14,Cockpit!$L$8,if(MEDIAN(C17:E17)<33,Cockpit!$L$9,Cockpit!$L$10))) -> 3 | T17: =if(MIN(C17:E17)<0.75,Cockpit!$L$7,if(MIN(C17:E17)<8,Cockpit!$L$8,if(MIN(C17:E17)<33,Cockpit!$L$9,Cockpit!$L$10))) -> 2 | U17: =MAX(Q17:T17) -> 3 | V17: =VLOOKUP($U17,Cockpit!$H$16:$M$22,3, FALSE) -> 10.65 | W17: =VLOOKUP($U17,Cockpit!$H$16:$M$22,4, FALSE) -> 0.38 | X17: =VLOOKUP($U17,Cockpit!$H$16:$M$22,5, FALSE) -> 1 | Y17: =V17+W17*(P17-X17) -> 13.69 | Z17: =$Z$2*AI17 -> 3.5994 | AA17: =M17+Y17+Z17 -> 38.462582 | AB17: 0.15 | AC17: =(1-AB17)*15% + 3%*AB17 -> 0.132 | AD17: 0.25 | AE17: 0.15 | AF17: =AB17+AC17+AD17+AE17 -> 0.682 | AG17: =1-AF17 -> 0.318 | AH17: =AA17/AG17 -> 120.95152 | AI17: 59.99 | AJ17: 0.25 | AK17: 0.1 | AL17: =M17/AI17 -> 0.35294519 | AM17: =1-AJ17-AK17-AC17-(Y17+Z17)/AI17 -> 0.2297953 | AN17: =1-AJ17-AK17-AC17-AA17/AI17 -> -0.12314989 | AO17: =AN17+AJ17 -> 0.12685011 | AP17: =Y17/AI17 -> 0.2282047 | AQ17: =AI17*AN17/M17 -> -0.34892073
A18: ET043MTMS | B18: Kill | C18: 26 | D18: 18 | E18: 5.5 | F18: 20.3 | G18: 1200 | H18: 1 | I18: =C18*D18*E18/12^3 -> 1.4895833 | J18: =G18/$J$2 -> 14.285714 | K18: =$K$2*I18 -> 10.427083 | L18: =J18*(1+$L$1)*$L$2 -> 2.7514286 | M18: =L18+K18+J18 -> 27.464226 | N18: =F18 -> 20.3 | O18: =roundup(C18*D18*E18/139,0) -> 19 | P18: =MAX(N18,O18) -> 20.3 | Q18: =if(P18<1,Cockpit!$H$7,if(P18<20,Cockpit!$H$8,if(P18<50,Cockpit!$H$9,if(P18<70,Cockpit!$H$10,if(P18<150,Cockpit!$H$11,Cockpit!$H$12))))) -> 3 | R18: =if(MAX(C18:E18)<15,Cockpit!$L$7,if(MAX(C18:E18)<18,Cockpit!$L$8,if(MAX(C18:E18)<59,Cockpit!$L$9,Cockpit!$L$10))) -> 3 | S18: =if(MEDIAN(C18:E18)<0.12,Cockpit!$L$7,if(MEDIAN(C18:E18)<14,Cockpit!$L$8,if(MEDIAN(C18:E18)<33,Cockpit!$L$9,Cockpit!$L$10))) -> 3 | T18: =if(MIN(C18:E18)<0.75,Cockpit!$L$7,if(MIN(C18:E18)<8,Cockpit!$L$8,if(MIN(C18:E18)<33,Cockpit!$L$9,Cockpit!$L$10))) -> 2 | U18: =MAX(Q18:T18) -> 3 | V18: =VLOOKUP($U18,Cockpit!$H$16:$M$22,3, FALSE) -> 10.65 | W18: =VLOOKUP($U18,Cockpit!$H$16:$M$22,4, FALSE) -> 0.38 | X18: =VLOOKUP($U18,Cockpit!$H$16:$M$22,5, FALSE) -> 1 | Y18: =V18+W18*(P18-X18) -> 17.984 | Z18: =$Z$2*AI18 -> 4.4994 | AA18: =M18+Y18+Z18 -> 49.947626 | AB18: 0.15 | AC18: =(1-AB18)*15% + 3%*AB18 -> 0.132 | AD18: 0.25 | AE18: 0.15 | AF18: =AB18+AC18+AD18+AE18 -> 0.682 | AG18: =1-AF18 -> 0.318 | AH18: =AA18/AG18 -> 157.06801 | AI18: 74.99 | AJ18: 0.25 | AK18: 0.1 | AL18: =M18/AI18 -> 0.36623851 | AM18: =1-AJ18-AK18-AC18-(Y18+Z18)/AI18 -> 0.21818136 | AN18: =1-AJ18-AK18-AC18-AA18/AI18 -> -0.14805716 | AO18: =AN18+AJ18 -> 0.10194284 | AP18: =Y18/AI18 -> 0.23981864 | AQ18: =AI18*AN18/M18 -> -0.4042643
A19: ET005MR | B19: Kill | C19: 20.5 | D19: 20 | E19: 23 | F19: 34.6 | G19: 4200 | H19: 1 | I19: =C19*D19*E19/12^3 -> 5.4571759 | J19: =G19/$J$2 -> 50 | K19: =$K$2*I19 -> 38.200231 | L19: =J19*(1+$L$1)*$L$2 -> 9.63 | M19: =L19+K19+J19 -> 97.830231 | N19: =F19 -> 34.6 | O19: =roundup(C19*D19*E19/139,0) -> 68 | P19: =MAX(N19,O19) -> 68 | Q19: =if(P19<1,Cockpit!$H$7,if(P19<20,Cockpit!$H$8,if(P19<50,Cockpit!$H$9,if(P19<70,Cockpit!$H$10,if(P19<150,Cockpit!$H$11,Cockpit!$H$12))))) -> 5 | R19: =if(MAX(C19:E19)<15,Cockpit!$L$7,if(MAX(C19:E19)<18,Cockpit!$L$8,if(MAX(C19:E19)<59,Cockpit!$L$9,Cockpit!$L$10))) -> 3 | S19: =if(MEDIAN(C19:E19)<0.12,Cockpit!$L$7,if(MEDIAN(C19:E19)<14,Cockpit!$L$8,if(MEDIAN(C19:E19)<33,Cockpit!$L$9,Cockpit!$L$10))) -> 3 | T19: =if(MIN(C19:E19)<0.75,Cockpit!$L$7,if(MIN(C19:E19)<8,Cockpit!$L$8,if(MIN(C19:E19)<33,Cockpit!$L$9,Cockpit!$L$10))) -> 3 | U19: =MAX(Q19:T19) -> 5 | V19: =VLOOKUP($U19,Cockpit!$H$16:$M$22,3, FALSE) -> 40.12 | W19: =VLOOKUP($U19,Cockpit!$H$16:$M$22,4, FALSE) -> 0.75 | X19: =VLOOKUP($U19,Cockpit!$H$16:$M$22,5, FALSE) -> 51 | Y19: =V19+W19*(P19-X19) -> 52.87 | Z19: =$Z$2*AI19 -> 14.9994 | AA19: =M19+Y19+Z19 -> 165.69963 | AB19: 0.15 | AC19: =(1-AB19)*15% + 3%*AB19 -> 0.132 | AD19: 0.25 | AE19: 0.15 | AF19: =AB19+AC19+AD19+AE19 -> 0.682 | AG19: =1-AF19 -> 0.318 | AH19: =AA19/AG19 -> 521.06802 | AI19: 249.99 | AJ19: 0.25 | AK19: 0.15 | AL19: =M19/AI19 -> 0.39133658 | AM19: =1-AJ19-AK19-AC19-(Y19+Z19)/AI19 -> 0.19651154 | AN19: =1-AJ19-AK19-AC19-AA19/AI19 -> -0.19482504 | AO19: =AN19+AJ19 -> 0.055174961 | AP19: =Y19/AI19 -> 0.21148846 | AQ19: =AI19*AN19/M19 -> -0.4978452
A20: ET004 | B20: Kill | C20: 19 | D20: 19 | E20: 23 | G20: 2700 | H20: 1 | I20: =C20*D20*E20/12^3 -> 4.8049769 | J20: =G20/$J$2 -> 32.142857 | K20: =$K$2*I20 -> 33.634838 | L20: =J20*(1+$L$1)*$L$2 -> 6.1907143 | M20: =L20+K20+J20 -> 71.968409 | N20: =F20 | O20: =roundup(C20*D20*E20/139,0) -> 60 | P20: =MAX(N20,O20) -> 60 | Q20: =if(P20<1,Cockpit!$H$7,if(P20<20,Cockpit!$H$8,if(P20<50,Cockpit!$H$9,if(P20<70,Cockpit!$H$10,if(P20<150,Cockpit!$H$11,Cockpit!$H$12))))) -> 5 | R20: =if(MAX(C20:E20)<15,Cockpit!$L$7,if(MAX(C20:E20)<18,Cockpit!$L$8,if(MAX(C20:E20)<59,Cockpit!$L$9,Cockpit!$L$10))) -> 3 | S20: =if(MEDIAN(C20:E20)<0.12,Cockpit!$L$7,if(MEDIAN(C20:E20)<14,Cockpit!$L$8,if(MEDIAN(C20:E20)<33,Cockpit!$L$9,Cockpit!$L$10))) -> 3 | T20: =if(MIN(C20:E20)<0.75,Cockpit!$L$7,if(MIN(C20:E20)<8,Cockpit!$L$8,if(MIN(C20:E20)<33,Cockpit!$L$9,Cockpit!$L$10))) -> 3 | U20: =MAX(Q20:T20) -> 5 | V20: =VLOOKUP($U20,Cockpit!$H$16:$M$22,3, FALSE) -> 40.12 | W20: =VLOOKUP($U20,Cockpit!$H$16:$M$22,4, FALSE) -> 0.75 | X20: =VLOOKUP($U20,Cockpit!$H$16:$M$22,5, FALSE) -> 51 | Y20: =V20+W20*(P20-X20) -> 46.87 | Z20: =$Z$2*AI20 -> 14.9994 | AA20: =M20+Y20+Z20 -> 133.83781 | AB20: 0.15 | AC20: =(1-AB20)*15% + 3%*AB20 -> 0.132 | AD20: 0.25 | AE20: 0.15 | AF20: =AB20+AC20+AD20+AE20 -> 0.682 | AG20: =1-AF20 -> 0.318 | AH20: =AA20/AG20 -> 420.87361 | AI20: =249.99 -> 249.99 | AJ20: 0.25 | AK20: 0.15 | AL20: =M20/AI20 -> 0.28788515 | AM20: =1-AJ20-AK20-AC20-(Y20+Z20)/AI20 -> 0.2205125 | AN20: =1-AJ20-AK20-AC20-AA20/AI20 -> -0.067372652 | AO20: =AN20+AJ20 -> 0.18262735 | AP20: =Y20/AI20 -> 0.1874875 | AQ20: =AI20*AN20/M20 -> -0.23402614
A21: ET006 | B21: Kill | C21: 17 | D21: 17 | E21: 23 | F21: 38.8 | G21: 5100 | H21: 1 | I21: =C21*D21*E21/12^3 -> 3.8466435 | J21: =G21/$J$2 -> 60.714286 | K21: =$K$2*I21 -> 26.926505 | L21: =J21*(1+$L$1)*$L$2 -> 11.693571 | M21: =L21+K21+J21 -> 99.334362 | N21: =F21 -> 38.8 | O21: =roundup(C21*D21*E21/139,0) -> 48 | P21: =MAX(N21,O21) -> 48 | Q21: =if(P21<1,Cockpit!$H$7,if(P21<20,Cockpit!$H$8,if(P21<50,Cockpit!$H$9,if(P21<70,Cockpit!$H$10,if(P21<150,Cockpit!$H$11,Cockpit!$H$12))))) -> 3 | R21: =if(MAX(C21:E21)<15,Cockpit!$L$7,if(MAX(C21:E21)<18,Cockpit!$L$8,if(MAX(C21:E21)<59,Cockpit!$L$9,Cockpit!$L$10))) -> 3 | S21: =if(MEDIAN(C21:E21)<0.12,Cockpit!$L$7,if(MEDIAN(C21:E21)<14,Cockpit!$L$8,if(MEDIAN(C21:E21)<33,Cockpit!$L$9,Cockpit!$L$10))) -> 3 | T21: =if(MIN(C21:E21)<0.75,Cockpit!$L$7,if(MIN(C21:E21)<8,Cockpit!$L$8,if(MIN(C21:E21)<33,Cockpit!$L$9,Cockpit!$L$10))) -> 3 | U21: =MAX(Q21:T21) -> 3 | V21: =VLOOKUP($U21,Cockpit!$H$16:$M$22,3, FALSE) -> 10.65 | W21: =VLOOKUP($U21,Cockpit!$H$16:$M$22,4, FALSE) -> 0.38 | X21: =VLOOKUP($U21,Cockpit!$H$16:$M$22,5, FALSE) -> 1 | Y21: =V21+W21*(P21-X21) -> 28.51 | Z21: =$Z$2*AI21 -> 13.7994 | AA21: =M21+Y21+Z21 -> 141.64376 | AB21: 0.15 | AC21: =(1-AB21)*15% + 3%*AB21 -> 0.132 | AD21: 0.25 | AE21: 0.15 | AF21: =AB21+AC21+AD21+AE21 -> 0.682 | AG21: =1-AF21 -> 0.318 | AH21: =AA21/AG21 -> 445.42063 | AI21: 229.99 | AJ21: 0.25 | AK21: 0.15 | AL21: =M21/AI21 -> 0.43190731 | AM21: =1-AJ21-AK21-AC21-(Y21+Z21)/AI21 -> 0.28403809 | AN21: =1-AJ21-AK21-AC21-AA21/AI21 -> -0.14786922 | AO21: =AN21+AJ21 -> 0.10213078 | AP21: =Y21/AI21 -> 0.12396191 | AQ21: =AI21*AN21/M21 -> -0.34236332
A22: ET013 | B22: Kill | C22: 21 | D22: 21 | E22: 25 | F22: 64.3 | G22: 4000 | H22: 1 | I22: =C22*D22*E22/12^3 -> 6.3802083 | J22: =G22/$J$2 -> 47.619048 | K22: =$K$2*I22 -> 44.661458 | L22: =J22*(1+$L$1)*$L$2 -> 9.1714286 | M22: =L22+K22+J22 -> 101.45193 | N22: =F22 -> 64.3 | O22: =roundup(C22*D22*E22/139,0) -> 80 | P22: =MAX(N22,O22) -> 80 | Q22: =if(P22<1,Cockpit!$H$7,if(P22<20,Cockpit!$H$8,if(P22<50,Cockpit!$H$9,if(P22<70,Cockpit!$H$10,if(P22<150,Cockpit!$H$11,Cockpit!$H$12))))) -> 6 | R22: =if(MAX(C22:E22)<15,Cockpit!$L$7,if(MAX(C22:E22)<18,Cockpit!$L$8,if(MAX(C22:E22)<59,Cockpit!$L$9,Cockpit!$L$10))) -> 3 | S22: =if(MEDIAN(C22:E22)<0.12,Cockpit!$L$7,if(MEDIAN(C22:E22)<14,Cockpit!$L$8,if(MEDIAN(C22:E22)<33,Cockpit!$L$9,Cockpit!$L$10))) -> 3 | T22: =if(MIN(C22:E22)<0.75,Cockpit!$L$7,if(MIN(C22:E22)<8,Cockpit!$L$8,if(MIN(C22:E22)<33,Cockpit!$L$9,Cockpit!$L$10))) -> 3 | U22: =MAX(Q22:T22) -> 6 | V22: =VLOOKUP($U22,Cockpit!$H$16:$M$22,3, FALSE) -> 54.81 | W22: =VLOOKUP($U22,Cockpit!$H$16:$M$22,4, FALSE) -> 0.75 | X22: =VLOOKUP($U22,Cockpit!$H$16:$M$22,5, FALSE) -> 71 | Y22: =V22+W22*(P22-X22) -> 61.56 | Z22: =$Z$2*AI22 -> 11.9994 | AA22: =M22+Y22+Z22 -> 175.01133 | AB22: 0.15 | AC22: =(1-AB22)*15% + 3%*AB22 -> 0.132 | AD22: 0.25 | AE22: 0.15 | AF22: =AB22+AC22+AD22+AE22 -> 0.682 | AG22: =1-AF22 -> 0.318 | AH22: =AA22/AG22 -> 550.35011 | AI22: 199.99 | AJ22: 0.25 | AK22: 0.15 | AL22: =M22/AI22 -> 0.50728504 | AM22: =1-AJ22-AK22-AC22-(Y22+Z22)/AI22 -> 0.10018461 | AN22: =1-AJ22-AK22-AC22-AA22/AI22 -> -0.40710043 | AO22: =AN22+AJ22 -> -0.15710043 | AP22: =Y22/AI22 -> 0.30781539 | AQ22: =AI22*AN22/M22 -> -0.80250825

Sheet invoice values
A1: ='Amazon Model Unit Economics - V'!A3 -> SKU | B1: ='Amazon Model Unit Economics - V'!J3 -> Ex-factory cost | C1: Invoice value
A2: ='Amazon Model Unit Economics - V'!A4 -> ET008 | B2: ='Amazon Model Unit Economics - V'!J4 -> 26.190476 | C2: =B2*1.07 -> 28.02381
A3: ='Amazon Model Unit Economics - V'!A5 -> ET042MB(D) | B3: ='Amazon Model Unit Economics - V'!J5 -> 19.642857 | C3: =B3*1.07 -> 21.017857
A4: ='Amazon Model Unit Economics - V'!A6 -> ET042MW | B4: ='Amazon Model Unit Economics - V'!J6 -> 19.642857 | C4: =B4*1.07 -> 21.017857
A5: ='Amazon Model Unit Economics - V'!A7 -> ET003-N | B5: ='Amazon Model Unit Economics - V'!J7 -> 32.142857 | C5: =B5*1.07 -> 34.392857
A6: ='Amazon Model Unit Economics - V'!A8 -> ET003-W | B6: ='Amazon Model Unit Economics - V'!J8 -> 32.142857 | C6: =B6*1.07 -> 34.392857
A7: ='Amazon Model Unit Economics - V'!A9 -> ET009 | B7: ='Amazon Model Unit Economics - V'!J9 -> 21.428571 | C7: =B7*1.07 -> 22.928571
A8: ='Amazon Model Unit Economics - V'!A10 -> ET012 | B8: ='Amazon Model Unit Economics - V'!J10 -> 23.571429 | C8: =B8*1.07 -> 25.221429
A9: ='Amazon Model Unit Economics - V'!A11 -> DR005MW | B9: ='Amazon Model Unit Economics - V'!J11 -> 14.285714 | C9: =B9*1.07 -> 15.285714
A10: ='Amazon Model Unit Economics - V'!A12 -> DR002MTMW | B10: ='Amazon Model Unit Economics - V'!J12 -> 17.26 | C10: =B10*1.07 -> 18.4682
A11: ='Amazon Model Unit Economics - V'!A13 -> DR001MW | B11: ='Amazon Model Unit Economics - V'!J13 -> 14.88 | C11: =B11*1.07 -> 15.9216
A12: ='Amazon Model Unit Economics - V'!A14 -> DR004MB | B12: ='Amazon Model Unit Economics - V'!J14 -> 14.880952 | C12: =B12*1.07 -> 15.922619
A13: ='Amazon Model Unit Economics - V'!A15 -> ET067MB | B13: ='Amazon Model Unit Economics - V'!J15 -> 19.345238 | C13: =B13*1.07 -> 20.699405
... A20: ='Amazon Model Unit Economics - V'!A22 -> ET013 | B20: ='Amazon Model Unit Economics - V'!J22 -> 47.619048 | C20: =B20*1.07 -> 50.952381
A21: ='Amazon Model Unit Economics - V'!A23
A22: ='Amazon Model Unit Economics - V'!A24
A23: ='Amazon Model Unit Economics - V'!A25
A24: ='Amazon Model Unit Economics - V'!A26
A25: ='Amazon Model Unit Economics - V'!A27
A26: ='Amazon Model Unit Economics - V'!A28

Sheet Sheet13
B3: SKU | C3: ASP (Target selling Price) | D3: Net Margin% basis Target Selling Price | E3: Current Units
B4: ET008 | C4: 199.99 | D4: 0.078502662 | E4: 20
B5: ET042MB(D) | C5: 149.99 | D5: 0.074857552 | E5: 35
B6: ET042MW | C6: 149.99 | D6: 0.074857552 | E6: 35
B7: ET003-W | C7: 199 | D7: 0.073470089 | E7: 25
B8: ET003-N | C8: 199 | D8: 0.073470089 | E8: 25
B9: ET009 | C9: 149.99 | D9: 0.065600687 | E9: 30
B10: ET012 | C10: 150 | D10: 0.06288772 | E10: 22
B11: DR005MW | C11: 99.99 | D11: 0.040407561 | E11: 25
B12: DR001MW | C12: 139.99 | D12: 0.04 | E12: 25
B13: DR002MTMW | C13: 149.99 | D13: 0.04 | E13: 25

Sheet Cockpit
B2: USD to INR Conversion | C2: 84
B3: Number of months for storage | C3: 2
B4: PA WH Storage cost per month per CFT (USD) | C4: 0.45
C6: INR | D6: USD | G6: Max Shipping Weight (lb) | H6: Class | I6: Shipping tier | K6: Longest side (in)
B7: Ind WH to Ind Port | C7: 100000 | D7: =C7/$C$2 -> 1190.4762 | G7: 16 | H7: 1 | I7: Small standard size | K7: 15 | L7: 1 | M7: Small standard size
G8: 20 | H8: 2 | I8: Large standard size | K8: 18 | L8: 2 | M8: Large standard size
G9: 50 | H9: 3 | I9: Large bulky | K9: 59 | L9: 3 | M9: Large bulky
D10: =8000-D7 -> 6809.5238 | G10: 70 | H10: 5 | I10: Extra large bulky | L10: 4 | M10: Extra large bulky
B11: India WH to PA-WH logistics cost | D11: =SUM(D7:D10) -> 8000 | G11: 150 | H11: 6 | I11: Extra large bulky (70 to 150lbs)
I15: Shipping tier | J15: Base Charges | K15: Incremental charges
H16: 1 | I16: Small standard size
H17: 2 | I17: Large standard size | J17: 7.46 | K17: =0.08*4 -> 0.32 | L17: 3
H18: 3 | I18: Large bulky | J18: 10.65 | K18: 0.38 | L18: 1
H19: 4 | I19: Extra large bulky (0 to 50lbs) | J19: 26.33 | K19: 0.38 | L19: 1
H20: 5 | I20: Extra large bulky (50 to 70lbs) | J20: 40.12 | K20: 0.75 | L20: 51
H21: 6 | I21: Extra large bulky (70 to 150lbs) | J21: 54.81 | K21: 0.75 | L21: 71
H22: 7 | I22: Extra large bulky (150lbs+) | J22: 194.95 | K22: 0.19 | L22: 151
I41: FBA Non-peak Fulfillment Fees (excluding apparel)
B42: 2025 Peak Fulfillment fees (excluding apparel) (October 15, 2025 – January 14, 2026) | K42: January 15, 2025 – October 14, 2025 | N42: Starting January 15, 2026
B43: Size tier | C43: Shipping weight | D43: <$10 | E43: $10-$50 | F43: >$50 | I43: Size tier | J43: Shipping weight | K43: <$10 | L43: $10-$50 | M43: >$50 | N43: <$10 | O43: $10-$50 | P43: >$50
B44: Large standard | C44: 4 oz or less | D44: 3.15 | E44: 3.92 | F44: 3.92 | I44: Large standard | J44: 4 oz or less | K44: 2.91 | L44: 3.68 | M44: 3.68 | N44: 2.91 | O44: 3.73 | P44: 3.99
C45: 4+ to 8 oz | D45: 3.39 | E45: 4.16 | F45: 4.16 | J45: 4+ to 8 oz | K45: 3.13 | L45: 3.9 | M45: 3.9 | N45: 3.13 | O45: 3.95 | P45: 4.21
C46: 8+ to 12 oz | D46: 3.66 | E46: 4.43 | F46: 4.43 | J46: 8+ to 12 oz | K46: 3.38 | L46: 4.15 | M46: 4.15 | N46: 3.38 | O46: 4.2 | P46: 4.46
C47: 12+ to 16 oz | D47: 4.07 | E47: 4.84 | F47: 4.84 | J47: 12+ to 16 oz | K47: 3.78 | L47: 4.55 | M47: 4.55 | N47: 3.78 | O47: 4.6 | P47: 4.86
C48: 1+ to 1.25 lb | D48: 4.52 | E48: 5.29 | F48: 5.29 | J48: 1+ to 1.25 lb | K48: 4.22 | L48: 4.99 | M48: 4.99 | N48: 4.22 | O48: 5.04 | P48: 5.3
C49: 1.25+ to 1.5 lb | D49: 4.91 | E49: 5.68 | F49: 5.68 | J49: 1.25+ to 1.5 lb | K49: 4.6 | L49: 5.37 | M49: 5.37 | N49: 4.6 | O49: 5.42 | P49: 5.68
C50: 1.5+ to 1.75 lb | D50: 5.07 | E50: 5.84 | F50: 5.84 | J50: 1.5+ to 1.75 lb | K50: 4.75 | L50: 5.52 | M50: 5.52 | N50: 4.75 | O50: 5.57 | P50: 5.83
C51: 1.75+ to 2 lb | D51: 5.33 | E51: 6.1 | F51: 6.1 | J51: 1.75+ to 2 lb | K51: 5 | L51: 5.77 | M51: 5.77 | N51: 5 | O51: 5.82 | P51: 6.08
C52: 2+ to 2.25 lb | D52: 5.47 | E52: 6.24 | F52: 6.24 | J52: 2+ to 2.25 lb | K52: 5.1 | L52: 5.87 | M52: 5.87 | N52: 5.1 | O52: 5.92 | P52: 6.18
C53: 2.25+ to 2.5 lb | D53: 5.67 | E53: 6.44 | F53: 6.44 | J53: 2.25+ to 2.5 lb | K53: 5.28 | L53: 6.05 | M53: 6.05 | N53: 5.28 | O53: 6.1 | P53: 6.36
C54: 2.5+ to 2.75 lb | D54: 5.84 | E54: 6.61 | F54: 6.61 | J54: 2.5+ to 2.75 lb | K54: 5.44 | L54: 6.21 | M54: 6.21 | N54: 5.44 | O54: 6.26 | P54: 6.52
C55: 2.75+ to 3 lb | D55: 6.26 | E55: 7.03 | F55: 7.03 | J55: 2.75+ to 3 lb | K55: 5.85 | L55: 6.62 | M55: 6.62 | N55: 5.85 | O55: 6.67 | P55: 6.93
C56: 3+ lb to 20 lb | D56: $6.69 + $0.08 per 4 oz interval above first 3 lb | E56: $7.46 + $0.08 per 4 oz interval above first 3 lb | F56: $7.46 + $0.08 per 4 oz interval above first 3 lb | J56: 3+ lb to 20 lb | K56: $6.15 + $0.08 per 4 oz interval above first 3 lb | L56: $6.92 + $0.08 per 4 oz interval above first 3 lb | M56: $6.92 + $0.08 per 4 oz interval above first 3 lb | N56: $6.15 + $0.08 per 4 oz interval above first 3 lb | O56: $6.97 + $0.08 per 4 oz interval above first 3 lb | P56: $7.23 + $0.08 per 4 oz interval above first 3 lb
B57: Small Bulky | C57: 0 to 50 lb | D57: $9.88 + $0.38/lb interval above first lb | E57: $10.65 + $0.38/lb interval above first lb | F57: $10.65 + $0.38/lb interval above first lb | I57: Small Bulky | J57: 0 to 50 lb | K57: $8.84 + $0.38/lb interval above first lb | L57: $9.61 + $0.38/lb interval above first lb | M57: $9.61 + $0.38/lb interval above first lb | N57: $6.78 + $0.38/lb interval above first lb | O57: $7.55 + $0.38/lb interval above first lb | P57: $7.55 + $0.38/lb interval above first lb
I58: Large Bulky | J58: 0 to 50 lb | K58: $8.84 + $0.38/lb interval above first lb | L58: $9.61 + $0.38/lb interval above first lb | M58: $9.61 + $0.38/lb interval above first lb | N58: $8.58 + $0.38/lb interval above first lb | O58: $9.35 + $0.38/lb interval above first lb | P58: $9.35 + $0.38/lb interval above first lb
I59: Extra-large 0 to 50 lb | J59: 0 to 50 lb | K59: $25.56 + $0.38/lb interval above first lb | L59: $26.33 + $0.38/lb interval above first lb | M59: $26.33 + $0.38/lb interval above first lb | N59: $25.56 + $0.38/lb interval above first lb | O59: $26.33 + $0.38/lb interval above first lb | P59: $26.33 + $0.38/lb interval above first lb
I60: Extra-large 50+ to 70 lb | J60: 50+ to 70 lb | K60: $39.35 + $0.75/lb interval above 51 lb | L60: $40.12 + $0.75/lb interval above 51 lb | M60: $40.12 + $0.75/lb interval above 51 lb | N60: $36.55 + $0.75/lb interval above 51 lb | O60: $37.32 + $0.75/lb interval above 51 lb | P60: $37.32 + $0.75/lb interval above 51 lb
I61: Extra-large 70+ to 150 lb | J61: 70+ to 150 lb | K61: $54.04 + $0.75/lb interval above 71 lb | L61: $54.81 + $0.75/lb interval above 71 lb | M61: $54.81 + $0.75/lb interval above 71 lb | N61: $50.55 + $0.75/lb interval above 71 lb | O61: $51.32 + $0.75/lb interval above 71 lb | P61: $51.32 + $0.75/lb interval above 71 lb
I62: Extra-large 150+ lb1 | J62: 150+ lb | K62: $194.18 + $0.19/lb interval above 151 lb | L62: $194.95 + $0.19/lb interval above 151 lb | M62: $194.95 + $0.19/lb interval above 151 lb | N62: $194.18 + $0.19/lb interval above 151 lb | O62: $194.95 + $0.19/lb interval above 151 lb | P62: $194.95 + $0.19/lb interval above 151 lb
B68: 2024 Product size tier definitions (ending on January 14, 2026) | I68: 2026 product size tier definitions (starting on January 15, 2026)
B69: Product size tier | C69: Shipping weight1 | D69: Longest side | E69: Median side | F69: Shortest side | G69: Length plus girth | I69: Product size tier | J69: Shipping weight1 | K69: Longest side | L69: Median side | M69: Shortest side | N69: Length plus girth
B70: Small standard-size | C70: Up to 16 oz | D70: Up to 15 inches | E70: Up to 12 inches | F70: Up to 0.75 inch | G70: N/A | I70: Small standard-size | J70: Up to 16 oz | K70: Up to 15 inches | L70: Up to 12 inches | M70: Up to 0.75 inch | N70: N/A
B71: Large standard-size | C71: Up to 20 lb | D71: Up to 18 inches | E71: Up to 14 inches | F71: Up to 8 inches | G71: N/A | I71: Large standard-size | J71: Up to 20 lb | K71: Up to 18 inches | L71: Up to 14 inches | M71: Up to 8 inches | N71: N/A
B72: Large Bulky | C72: Up to 50 lb | D72: Up to 59 inches | E72: Up to 33 inches | F72: Up to 33 inches | G72: Up to 130 inches | I72: Small Bulky | J72: Up to 50 lb | K72: Up to 37 inches | L72: Up to 28 inches | M72: Up to 20 inches | N72: Up to 130 inches
B73: Extra-Large 0 to 50 lb | C73: Up to 50 lb | D73: Extra-Large exceeds 59 inches for the longest side or 33 inches for the median side or 33 inches for the shortest side or 130 inches for length plus girth, or if the product’s larger of unit weight or dimensional weight exceeds 50 lb. | I73: Large Bulky | J73: Up to 50 lb | K73: Up to 59 inches | L73: Up to 33 inches | M73: Up to 33 inches | N73: Up to 130 inches
B74: Extra-Large 50+ to 70 lb | C74: 50+ to 70 lb | I74: Extra-Large 0 to 50 lb | J74: Up to 50 lb | K74: Extra-Large exceeds 59 inches for the longest side or 33 inches for the median side or 33 inches for the shortest side or 130 inches for length plus girth, or if the product’s larger of unit weight or dimensional weight exceeds 50 lb. Extra-Large (up to 150 lb) exceeding 96 inches for longest side or 130 inches for length plus girth will be considered Overmax.
B75: Extra-Large 70+ to 150 lb | C75: 70+ to 150 lb | I75: Extra-Large 50+ to 70 lb | J75: 50+ to 70 lb
B76: Extra-Large 150+ lb | C76: Over 150 lb | I76: Extra-large 70+ to 150 lb | J76: 70+ to 150 lb
I77: Extra-large 150+ lb | J77: Over 150 lb

Sheet Amazon Unit Economics Model - V
F2: $7 per CFT | M2: 15% of net + 3% return admin on returned items | Q2: 25% of Gross sales | R2: 5% of Gross sales | W2: Net COGS in dollars calculated on gross sale units as returns will not be resold
F3: 7 | J3: 0.15 | M3: 0.15 | Q3: 0.25 | R3: 0.055
B4: SKU | C4: KD/Non-KD | D4: Factory price | E4: CFT | F4: SEND Shipping | G4: ASP | H4: Gross Units | I4: Gross Sales | J4: Return % | K4: Net Units | L4: Net Sales | M4: AZ Selling Fees | N4: FBA Fulfilment Fees | O4: AZ Fulfillment fees | P4: OM1 | Q4: Ads | R4: Other costs | S4: Profit Before COGS | T4: Unit COGS 0% Tariff | U4: Unit COGS 25% Tariff | V4: Unit COGS 50% Tariff | W4: Gross COGS 0% Tariff | X4: Gross COGS 25% Tariff | Y4: Gross COGS 50% Tariff | Z4: Net Margin 0% Tariff | AA4: Net Margin 25% Tariff | AB4: Net Margin 50% Tariff | AC4: % Net Margin 0% Tariff | AD4: % Net margin 25% Tariff | AE4: % Net margin 50% Tariff | AF4: % returns | AG4: Gross sales (4 months) | AH4: Gross COGS % 0% Tariff | AI4: Gross COGS% 25% Tariff | AJ4: Gross COGS% 50% Tariff | AS4: Returns (4 months)
B5: RH-ET042MB(D)-FBA | C5: KD | D5: 19.64 | E5: =23*6*18/12/12/12 -> 1.4375 | F5: =E5*$F$3 -> 10.0625 | G5: 149.99 | H5: 26 | I5: =G5*H5 -> 3899.74 | J5: =$J$3 -> 0.15 | K5: =rounddown(H5*(1-J5),0) -> 22 | L5: =K5*G5 -> 3299.78 | M5: =L5*$M$3+3%*(H5-K5)*G5 -> 512.9658 | N5: 16.45 | O5: =N5*(H5) -> 427.7 | P5: =L5-M5-O5 -> 2359.1142 | Q5: =I5*$Q$3 -> 974.935 | R5: =I5*$R$3 -> 214.4857 | S5: =P5-Q5-R5 -> 1169.6935 | T5: =F5+D5 -> 29.7025 | U5: =D5*(1.02)*(0.25)+D5+F5 -> 34.7107 | V5: =D5*(1.02)*(0.5)+D5+F5 -> 39.7189 | W5: =$H5*T5 -> 772.265 | X5: =$H5*U5 -> 902.4782 | Y5: =$H5*V5 -> 1032.6914 | Z5: =$S5-W5 -> 397.4285 | AA5: =$S5-X5 -> 267.2153 | AB5: =$S5-Y5 -> 137.0021 | AC5: =Z5/$L5 -> 0.12044091 | AD5: =AA5/$L5 -> 0.080979732 | AE5: =AB5/$L5 -> 0.041518556 | AF5: =AS5/AG5 -> 0.057142857 | AG5: 35 | AH5: =W5/$L5 -> 0.2340353 | AI5: =X5/$L5 -> 0.27349648 | AJ5: =Y5/$L5 -> 0.31295765 | AS5: 2
B6: RH-ET042MW-FBA | C6: KD | D6: 19.64 | E6: =23*6*18/12/12/12 -> 1.4375 | F6: =E6*$F$3 -> 10.0625 | G6: 149.99 | H6: 26 | I6: =G6*H6 -> 3899.74 | J6: =$J$3 -> 0.15 | K6: =rounddown(H6*(1-J6),0) -> 22 | L6: =K6*G6 -> 3299.78 | M6: =L6*$M$3+3%*(H6-K6)*G6 -> 512.9658 | N6: 16.45 | O6: =N6*(H6) -> 427.7 | P6: =L6-M6-O6 -> 2359.1142 | Q6: =I6*$Q$3 -> 974.935 | R6: =I6*$R$3 -> 214.4857 | S6: =P6-Q6-R6 -> 1169.6935 | T6: =F6+D6 -> 29.7025 | U6: =D6*(1.02)*(0.25)+D6+F6 -> 34.7107 | V6: =D6*(1.02)*(0.5)+D6+F6 -> 39.7189 | W6: =$H6*T6 -> 772.265 | X6: =$H6*U6 -> 902.4782 | Y6: =$H6*V6 -> 1032.6914 | Z6: =$S6-W6 -> 397.4285 | AA6: =$S6-X6 -> 267.2153 | AB6: =$S6-Y6 -> 137.0021 | AC6: =Z6/$L6 -> 0.12044091 | AD6: =AA6/$L6 -> 0.080979732 | AE6: =AB6/$L6 -> 0.041518556 | AF6: =AS6/AG6 -> 0.081081081 | AG6: 37 | AH6: =W6/L6 -> 0.2340353 | AI6: =X6/$L6 -> 0.27349648 | AJ6: =Y6/$L6 -> 0.31295765 | AS6: 3
B7: RH-DR002MTMW-FBA | C7: Non-KD | D7: 17.26 | E7: =14.5*14.5*26.5/12/12/12 -> 3.22432 | F7: =E7*$F$3 -> 22.57024 | G7: 149.99 | H7: 21 | I7: =G7*H7 -> 3149.79 | J7: =$J$3 -> 0.15 | K7: =rounddown(H7*(1-J7),0) -> 17 | L7: =K7*G7 -> 2549.83 | M7: =L7*$M$3+3%*(H7-K7)*G7 -> 400.4733 | N7: 25.95 | O7: =N7*(H7) -> 544.95 | P7: =L7-M7-O7 -> 1604.4067 | Q7: =I7*$Q$3 -> 787.4475 | R7: =I7*$R$3 -> 173.23845 | S7: =P7-Q7-R7 -> 643.72075 | T7: =F7+D7 -> 39.83024 | U7: =D7*(1.02)*(0.25)+D7+F7 -> 44.23154 | V7: =D7*(1.02)*(0.5)+D7+F7 -> 48.63284 | W7: =$H7*T7 -> 836.43504 | X7: =$H7*U7 -> 928.86234 | Y7: =$H7*V7 -> 1021.2896 | Z7: =$S7-W7 -> -192.71429 | AA7: =$S7-X7 -> -285.14159 | AB7: =$S7-Y7 -> -377.56889 | AC7: =Z7/$L7 -> -0.075579271 | AD7: =AA7/$L7 -> -0.11182769 | AE7: =AB7/$L7 -> -0.1480761 | AF7: =AS7/AG7 -> 0.1369863 | AG7: 73 | AH7: =W7/L7 -> 0.32803561 | AI7: =X7/$L7 -> 0.36428403 | AJ7: =Y7/$L7 -> 0.40053244 | AS7: 10
B8: RH-DR001MW-FBA | C8: Non-KD | D8: 14.88 | E8: =14*14*26/12/12/12 -> 2.9490741 | F8: =E8*$F$3 -> 20.643519 | G8: 139.99 | H8: 16 | I8: =G8*H8 -> 2239.84 | J8: =$J$3 -> 0.15 | K8: =rounddown(H8*(1-J8),0) -> 13 | L8: =K8*G8 -> 1819.87 | M8: =L8*$M$3+3%*(H8-K8)*G8 -> 285.5796 | N8: 24.43 | O8: =N8*(H8) -> 390.88 | P8: =L8-M8-O8 -> 1143.4104 | Q8: =I8*$Q$3 -> 559.96 | R8: =I8*$R$3 -> 123.1912 | S8: =P8-Q8-R8 -> 460.2592 | T8: =F8+D8 -> 35.523519 | U8: =D8*(1.02)*(0.25)+D8+F8 -> 39.317919 | V8: =D8*(1.02)*(0.5)+D8+F8 -> 43.112319 | W8: =$H8*T8 -> 568.3763 | X8: =$H8*U8 -> 629.0867 | Y8: =$H8*V8 -> 689.7971 | Z8: =$S8-W8 -> -108.1171 | AA8: =$S8-X8 -> -168.8275 | AB8: =$S8-Y8 -> -229.5379 | AC8: =Z8/$L8 -> -0.059409241 | AD8: =AA8/$L8 -> -0.092768987 | AE8: =AB8/$L8 -> -0.12612873 | AF8: =AS8/AG8 -> 0.20512821 | AG8: 39 | AH8: =W8/L8 -> 0.31231698 | AI8: =X8/$L8 -> 0.34567672 | AJ8: =Y8/$L8 -> 0.37903647 | AS8: 8
B9: RH-ET003-N-FBA | C9: KD | D9: 51.79 | E9: =17.5*19.5*14.5/12/12/12 -> 2.8634983 | F9: =E9*$F$3 -> 20.044488 | G9: 199 | H9: 10 | I9: =G9*H9 -> 1990 | J9: =$J$3 -> 0.15 | K9: =rounddown(H9*(1-J9),0) -> 8 | L9: =K9*G9 -> 1592 | M9: =L9*$M$3+3%*(H9-K9)*G9 -> 250.74 | N9: 21.39 | O9: =N9*(H9) -> 213.9 | P9: =L9-M9-O9 -> 1127.36 | Q9: =I9*$Q$3 -> 497.5 | R9: =I9*$R$3 -> 109.45 | S9: =P9-Q9-R9 -> 520.41 | T9: =F9+D9 -> 71.834488 | U9: =D9*(1.02)*(0.25)+D9+F9 -> 85.040938 | V9: =D9*(1.02)*(0.5)+D9+F9 -> 98.247388 | W9: =$H9*T9 -> 718.34488 | X9: =$H9*U9 -> 850.40938 | Y9: =$H9*V9 -> 982.47388 | Z9: =$S9-W9 -> -197.93488 | AA9: =$S9-X9 -> -329.99938 | AB9: =$S9-Y9 -> -462.06388 | AC9: =Z9/$L9 -> -0.12433095 | AD9: =AA9/$L9 -> -0.20728604 | AE9: =AB9/$L9 -> -0.29024113 | AF9: =AS9/AG9 -> 0.30769231 | AG9: 39 | AH9: =W9/L9 -> 0.45122166 | AI9: =X9/$L9 -> 0.53417675 | AJ9: =Y9/$L9 -> 0.61713183 | AS9: 12
B10: RH-DR005MW-FBA | C10: KD | D10: 14.88 | E10: =14.5*15*6/12/12/12 -> 0.75520833 | F10: =E10*$F$3 -> 5.2864583 | G10: 99.99 | H10: 18 | I10: =G10*H10 -> 1799.82 | J10: =$J$3 -> 0.15 | K10: =rounddown(H10*(1-J10),0) -> 15 | L10: =K10*G10 -> 1499.85 | M10: =L10*$M$3+3%*(H10-K10)*G10 -> 233.9766 | N10: 11.71 | O10: =N10*(H10) -> 210.78 | P10: =L10-M10-O10 -> 1055.0934 | Q10: =I10*$Q$3 -> 449.955 | R10: =I10*$R$3 -> 98.9901 | S10: =P10-Q10-R10 -> 506.1483 | T10: =F10+D10 -> 20.166458 | U10: =D10*(1.02)*(0.25)+D10+F10 -> 23.960858 | V10: =D10*(1.02)*(0.5)+D10+F10 -> 27.755258 | W10: =$H10*T10 -> 362.99625 | X10: =$H10*U10 -> 431.29545 | Y10: =$H10*V10 -> 499.59465 | Z10: =$S10-W10 -> 143.15205 | AA10: =$S10-X10 -> 74.85285 | AB10: =$S10-Y10 -> 6.55365 | AC10: =Z10/$L10 -> 0.095444244 | AD10: =AA10/$L10 -> 0.049906891 | AE10: =AB10/$L10 -> 0.004369537 | AF10: =AS10/AG10 -> 0.10714286 | AG10: 56 | AH10: =W10/L10 -> 0.2420217 | AI10: =X10/$L10 -> 0.28755906 | AJ10: =Y10/$L10 -> 0.33309641 | AS10: 6
B11: Aggregate | I11: =sum(I5:I10) -> 16978.93 | L11: =sum(L5:L10) -> 14061.11 | M11: =sum(M5:M10) -> 2196.7011 | O11: =sum(O5:O10) -> 2215.91 | P11: =sum(P5:P10) -> 9648.4989 | Q11: =sum(Q5:Q10) -> 4244.7325 | R11: =sum(R5:R10) -> 933.84115 | S11: =sum(S5:S10) -> 4469.9253 | W11: =sum(W5:W10) -> 4030.6825 | X11: =sum(X5:X10) -> 4644.6103 | Y11: =sum(Y5:Y10) -> 5258.5381 | Z11: =sum(Z5:Z10) -> 439.24278 | AA11: =sum(AA5:AA10) -> -174.68502 | AB11: =sum(AB5:AB10) -> -788.61282 | AC11: =Z11/$L11 -> 0.03123813 | AD11: =AA11/$L11 -> -0.012423274 | AE11: =AB11/$L11 -> -0.056084677 | AF11: =AS11/AG11 -> 0.14695341 | AG11: =SUM(AG5:AG10) -> 279 | AH11: =W11/L11 -> 0.28665464 | AI11: =X11/$L11 -> 0.33031605 | AJ11: =Y11/$L11 -> 0.37397745 | AS11: =SUM(AS5:AS10) -> 41
S13: Discount on manufacturing cost | T13: 0.1
B15: SKU | T15: COGS 0% Tariff | U15: COGS 25% Tariff | V15: COGS 50% Tariff | W15: Gross COGS 0% Tariff | X15: Gross COGS 25% Tariff | Y15: Gross COGS 50% Tariff | Z15: Net Margin 0% Tariff | AA15: Net Margin 25% Tariff | AB15: Net Margin 50% Tariff | AC15: % Net Margin 0% Tariff | AD15: % Net margin 25% Tariff | AE15: % Net margin 50% Tariff
B16: RH-ET042MB(D)-FBA | T16: =F5+D5*(1-$T$13) -> 27.7385 | U16: =D5*(1.02)*(1.25)*(1-$T$13)+F5 -> 32.5994 | V16: =D5*(1.02)*(1.5)*(1-$T$13)+F5 -> 37.10678 | W16: =$H5*T16 -> 721.201 | X16: =$H5*U16 -> 847.5844 | Y16: =$H5*V16 -> 964.77628 | Z16: =$S5-W16 -> 448.4925 | AA16: =$S5-X16 -> 322.1091 | AB16: =$S5-Y16 -> 204.91722 | AC16: =Z16/$L5 -> 0.13591588 | AD16: =AA16/$L5 -> 0.097615326 | AE16: =AB16/$L5 -> 0.062100267
B17: RH-ET042MW-FBA | T17: =F6+D6*(1-$T$13) -> 27.7385 | U17: =D6*(1.02)*(1.25)*(1-$T$13)+F6 -> 32.5994 | V17: =D6*(1.02)*(1.5)*(1-$T$13)+F6 -> 37.10678 | W17: =$H6*T17 -> 721.201 | X17: =$H6*U17 -> 847.5844 | Y17: =$H6*V17 -> 964.77628 | Z17: =$S6-W17 -> 448.4925 | AA17: =$S6-X17 -> 322.1091 | AB17: =$S6-Y17 -> 204.91722 | AC17: =Z17/$L6 -> 0.13591588 | AD17: =AA17/$L6 -> 0.097615326 | AE17: =AB17/$L6 -> 0.062100267
B18: RH-DR002MTMW-FBA | T18: =F7+D7*(1-$T$13) -> 38.10424 | U18: =D7*(1.02)*(1.25)*(1-$T$13)+F7 -> 42.37609 | V18: =D7*(1.02)*(1.5)*(1-$T$13)+F7 -> 46.33726 | W18: =$H7*T18 -> 800.18904 | X18: =$H7*U18 -> 889.89789 | Y18: =$H7*V18 -> 973.08246 | Z18: =$S7-W18 -> -156.46829 | AA18: =$S7-X18 -> -246.17714 | AB18: =$S7-Y18 -> -329.36171 | AC18: =Z18/$L7 -> -0.061364206 | AD18: =AA18/$L7 -> -0.096546493 | AE18: =AB18/$L7 -> -0.12917007
B19: RH-DR001MW-FBA | T19: =F8+D8*(1-$T$13) -> 34.035519 | U19: =D8*(1.02)*(1.25)*(1-$T$13)+F8 -> 37.718319 | V19: =D8*(1.02)*(1.5)*(1-$T$13)+F8 -> 41.133279 | W19: =$H8*T19 -> 544.5683 | X19: =$H8*U19 -> 603.4931 | Y19: =$H8*V19 -> 658.13246 | Z19: =$S8-W19 -> -84.309096 | AA19: =$S8-X19 -> -143.2339 | AB19: =$S8-Y19 -> -197.87326 | AC19: =Z19/$L8 -> -0.046326988 | AD19: =AA19/$L8 -> -0.078705565 | AE19: =AB19/$L8 -> -0.10872934
B20: RH-ET003-N-FBA | T20: =F9+D9*(1-$T$13) -> 66.655488 | U20: =D9*(1.02)*(1.25)*(1-$T$13)+F9 -> 79.473513 | V20: =D9*(1.02)*(1.5)*(1-$T$13)+F9 -> 91.359318 | W20: =$H9*T20 -> 666.55488 | X20: =$H9*U20 -> 794.73513 | Y20: =$H9*V20 -> 913.59318 | Z20: =$S9-W20 -> -146.14488 | AA20: =$S9-X20 -> -274.32513 | AB20: =$S9-Y20 -> -393.18318 | AC20: =Z20/$L9 -> -0.091799547 | AD20: =AA20/$L9 -> -0.17231478 | AE20: =AB20/$L9 -> -0.24697436
B21: RH-DR005MW-FBA | T21: =F10+D10*(1-$T$13) -> 18.678458 | U21: =D10*(1.02)*(1.25)*(1-$T$13)+F10 -> 22.361258 | V21: =D10*(1.02)*(1.5)*(1-$T$13)+F10 -> 25.776218 | W21: =$H10*T21 -> 336.21225 | X21: =$H10*U21 -> 402.50265 | Y21: =$H10*V21 -> 463.97193 | Z21: =$S10-W21 -> 169.93605 | AA21: =$S10-X21 -> 103.64565 | AB21: =$S10-Y21 -> 42.17637 | AC21: =Z21/$L10 -> 0.11330203 | AD21: =AA21/$L10 -> 0.06910401 | AE21: =AB21/$L10 -> 0.028120392
B22: Aggregate | W22: =sum(W16:W21) -> 3789.9265 | X22: =sum(X16:X21) -> 4385.7976 | Y22: =sum(Y16:Y21) -> 4938.3326 | Z22: =sum(Z16:Z21) -> 679.99878 | AA22: =sum(AA16:AA21) -> 84.127682 | AB22: =sum(AB16:AB21) -> -468.40734 | AC22: =Z22/$L11 -> 0.048360249 | AD22: =AA22/$L11 -> 0.0059830043 | AE22: =AB22/$L11 -> -0.033312259
H24: 30 | I24: 79.99 | J24: =H24*I24 -> 2399.7 | T24: Line of action
H25: 2 | I25: 699.99 | J25: =H25*I25 -> 1399.98
H26: 4 | I26: 169.99 | J26: =H26*I26 -> 679.96 | T26: Jodhpur visit
H27: 32 | I27: 189.99 | J27: =H27*I27 -> 6079.68 | T27: - Jugaad billing to bypass tariffs
H28: 22 | I28: 419.99 | J28: =H28*I28 -> 9239.78 | T28: - Non-KD to KD
H29: 24 | I29: 379.99 | J29: =H29*I29 -> 9119.76 | T29: - KD mein 10% Factory price reduction
H30: 34 | I30: 309.99 | J30: =H30*I30 -> 10539.66 | T30: - Inventory sponshirship from Supplier - atleast 1 supplier
H31: 26 | I31: 249.99 | J31: =H31*I31 -> 6499.74
H32: 2 | I32: =249.99+199.99 -> 449.98 | J32: =H32*I32 -> 899.96 | T32: Full potential
H33: 2 | I33: =199.99+229.99 -> 429.98 | J33: =H33*I33 -> 859.96 | T33: - How much can these scale on Amazon
H34: 17 | I34: 279.99 | J34: =H34*I34 -> 4759.83 | T34: - Figure out how big this business can become
H35: 4 | I35: 649.99 | J35: =H35*I35 -> 2599.96 | T35: - Figure out how fast can this business grow
H36: 2 | I36: 449.99 | J36: =H36*I36 -> 899.98 | T36: - This business definition - Selling small KD furniture pieces on amazon which are priced atleast 20-30% higher than median price
H37: 29 | I37: 279.99 | J37: =H37*I37 -> 8119.71 | T37: - Consumer Survey to assess the demand for this business
H38: 7 | I38: 154.99 | J38: =H38*I38 -> 1084.93 | T38: - D2C - How big, How fast, GTM, Unit economics. What learnings can you derive from amazon for this? This question is more for future else there is a risk of getting restricted to becoming AZ seller
H39: 33 | I39: 139.99 | J39: =H39*I39 -> 4619.67
H40: 12 | I40: 139.99 | J40: =H40*I40 -> 1679.88 | T40: India Furniture market - Mayank conversation
H41: 19 | I41: 149.99 | J41: =H41*I41 -> 2849.81 | T41: - Define the business & market questions you want to talk about
H42: 28 | I42: 94.99 | J42: =H42*I42 -> 2659.72 | T42: - Understand his position - What does he wants to do?
H43: 33 | I43: 259.99 | J43: =H43*I43 -> 8579.67
H44: 44 | I44: 199.99 | J44: =H44*I44 -> 8799.56 | T44: New cross-border consumer angles
J45: =sum(J24:J44) -> 94370.9 | T45: - Creating a Temu/Shein from India for products where there is a disproportionate production & supply chain advantage
T47: India focussed business - New Ideas

Sheet Amazon Unit Economics Model @15
F2: $7 per CFT | M2: 15% of net + 3% return admin on returned items | Q2: 25% of Gross sales | R2: 5% of Gross sales | W2: Net COGS in dollars calculated on gross sale units as returns will not be resold
F3: 7 | J3: 0.15 | M3: 0.15 | Q3: 0.25 | R3: 0.055
B4: SKU | C4: KD/Non-KD | D4: Factory cost | E4: CFT | F4: SEND Shipping | G4: ASP | H4: Gross Units | I4: Gross Sales | J4: Return % | K4: Net Units | L4: Net Sales | M4: AZ Selling Fees | N4: FBA Fulfilment Fees | O4: AZ Fulfillment fees | P4: OM1 | Q4: Ads | R4: Other costs | S4: Profit Before COGS | T4: Unit COGS 0% Tariff | U4: Unit COGS 15% Tariff | V4: Unit COGS 50% Tariff | W4: Gross COGS 0% Tariff | X4: Gross COGS 15% Tariff | Y4: Gross COGS 50% Tariff | Z4: Net Margin 0% Tariff | AA4: Net Margin 15% Tariff | AB4: Net Margin 50% Tariff | AC4: % Net Margin 0% Tariff | AD4: % Net margin 15% Tariff | AE4: % Net margin 50% Tariff | AF4: % returns | AG4: Gross sales (4 months) | AH4: Gross COGS % 0% Tariff | AI4: Gross COGS% 15% Tariff | AJ4: Gross COGS% 50% Tariff | AS4: Returns (4 months)
B5: RH-ET042MB(D)-FBA | C5: KD | D5: 19.64 | E5: =23*6*18/12/12/12 -> 1.4375 | F5: =E5*$F$3 -> 10.0625 | G5: 149.99 | H5: 26 | I5: =G5*H5 -> 3899.74 | J5: =$J$3 -> 0.15 | K5: =H5*(1-J5) -> 22.1 | L5: =K5*G5 -> 3314.779 | M5: =L5*$M$3+3%*(H5-K5)*G5 -> 514.76568 | N5: 16.45 | O5: =N5*(H5) -> 427.7 | P5: =L5-M5-O5 -> 2372.3133 | Q5: =I5*$Q$3 -> 974.935 | R5: =I5*$R$3 -> 214.4857 | S5: =P5-Q5-R5 -> 1182.8926 | T5: =F5+D5 -> 29.7025 | U5: =D5*(1.05)*(0.15)+D5+F5 -> 32.7958 | V5: =D5*(1.02)*(0.5)+D5+F5 -> 39.7189 | W5: =$H5*T5 -> 772.265 | X5: =$H5*U5 -> 852.6908 | Y5: =$H5*V5 -> 1032.6914 | Z5: =$S5-W5 -> 410.62762 | AA5: =$S5-X5 -> 330.20182 | AB5: =$S5-Y5 -> 150.20122 | AC5: =Z5/$L5 -> 0.12387783 | AD5: =AA5/$L5 -> 0.099615033 | AE5: =AB5/$L5 -> 0.045312589 | AF5: =AS5/AG5 -> 0.057142857 | AG5: 35 | AH5: =W5/$L5 -> 0.23297632 | AI5: =X5/$L5 -> 0.25723911 | AJ5: =Y5/$L5 -> 0.31154155 | AS5: 2
B6: RH-ET042MW-FBA | C6: KD | D6: 19.64 | E6: =23*6*18/12/12/12 -> 1.4375 | F6: =E6*$F$3 -> 10.0625 | G6: 149.99 | H6: 26 | I6: =G6*H6 -> 3899.74 | J6: =$J$3 -> 0.15 | K6: =H6*(1-J6) -> 22.1 | L6: =K6*G6 -> 3314.779 | M6: =L6*$M$3+3%*(H6-K6)*G6 -> 514.76568 | N6: 16.45 | O6: =N6*(H6) -> 427.7 | P6: =L6-M6-O6 -> 2372.3133 | Q6: =I6*$Q$3 -> 974.935 | R6: =I6*$R$3 -> 214.4857 | S6: =P6-Q6-R6 -> 1182.8926 | T6: =F6+D6 -> 29.7025 | U6: =D6*(1.05)*(0.15)+D6+F6 -> 32.7958 | V6: =D6*(1.02)*(0.5)+D6+F6 -> 39.7189 | W6: =$H6*T6 -> 772.265 | X6: =$H6*U6 -> 852.6908 | Y6: =$H6*V6 -> 1032.6914 | Z6: =$S6-W6 -> 410.62762 | AA6: =$S6-X6 -> 330.20182 | AB6: =$S6-Y6 -> 150.20122 | AC6: =Z6/$L6 -> 0.12387783 | AD6: =AA6/$L6 -> 0.099615033 | AE6: =AB6/$L6 -> 0.045312589 | AF6: =AS6/AG6 -> 0.081081081 | AG6: 37 | AH6: =W6/L6 -> 0.23297632 | AI6: =X6/$L6 -> 0.25723911 | AJ6: =Y6/$L6 -> 0.31154155 | AS6: 3
B7: RH-DR002MTMW-FBA | C7: Non-KD | D7: 17.26 | E7: =14.5*14.5*26.5/12/12/12 -> 3.22432 | F7: =E7*$F$3 -> 22.57024 | G7: 149.99 | H7: 21 | I7: =G7*H7 -> 3149.79 | J7: =$J$3 -> 0.15 | K7: =H7*(1-J7) -> 17.85 | L7: =K7*G7 -> 2677.3215 | M7: =L7*$M$3+3%*(H7-K7)*G7 -> 415.77228 | N7: 25.95 | O7: =N7*(H7) -> 544.95 | P7: =L7-M7-O7 -> 1716.5992 | Q7: =I7*$Q$3 -> 787.4475 | R7: =I7*$R$3 -> 173.23845 | S7: =P7-Q7-R7 -> 755.91327 | T7: =F7+D7 -> 39.83024 | U7: =D7*(1.05)*(0.15)+D7+F7 -> 42.54869 | V7: =D7*(1.02)*(0.5)+D7+F7 -> 48.63284 | W7: =$H7*T7 -> 836.43504 | X7: =$H7*U7 -> 893.52249 | Y7: =$H7*V7 -> 1021.2896 | Z7: =$S7-W7 -> -80.521773 | AA7: =$S7-X7 -> -137.60922 | AB7: =$S7-Y7 -> -265.37637 | AC7: =Z7/$L7 -> -0.030075496 | AD7: =AA7/$L7 -> -0.051398094 | AE7: =AB7/$L7 -> -0.099120099 | AF7: =AS7/AG7 -> 0.1369863 | AG7: 73 | AH7: =W7/L7 -> 0.31241487 | AI7: =X7/$L7 -> 0.33373747 | AJ7: =Y7/$L7 -> 0.38145947 | AS7: 10
B8: RH-DR001MW-FBA | C8: Non-KD | D8: 14.88 | E8: =14*14*26/12/12/12 -> 2.9490741 | F8: =E8*$F$3 -> 20.643519 | G8: 139.99 | H8: 16 | I8: =G8*H8 -> 2239.84 | J8: =$J$3 -> 0.15 | K8: =H8*(1-J8) -> 13.6 | L8: =K8*G8 -> 1903.864 | M8: =L8*$M$3+3%*(H8-K8)*G8 -> 295.65888 | N8: 24.43 | O8: =N8*(H8) -> 390.88 | P8: =L8-M8-O8 -> 1217.3251 | Q8: =I8*$Q$3 -> 559.96 | R8: =I8*$R$3 -> 123.1912 | S8: =P8-Q8-R8 -> 534.17392 | T8: =F8+D8 -> 35.523519 | U8: =D8*(1.05)*(0.15)+D8+F8 -> 37.867119 | V8: =D8*(1.02)*(0.5)+D8+F8 -> 43.112319 | W8: =$H8*T8 -> 568.3763 | X8: =$H8*U8 -> 605.8739 | Y8: =$H8*V8 -> 689.7971 | Z8: =$S8-W8 -> -34.202376 | AA8: =$S8-X8 -> -71.699976 | AB8: =$S8-Y8 -> -155.62318 | AC8: =Z8/$L8 -> -0.017964716 | AD8: =AA8/$L8 -> -0.037660241 | AE8: =AB8/$L8 -> -0.0817407 | AF8: =AS8/AG8 -> 0.20512821 | AG8: 39 | AH8: =W8/L8 -> 0.29853829 | AI8: =X8/$L8 -> 0.31823381 | AJ8: =Y8/$L8 -> 0.36231427 | AS8: 8
B9: RH-ET003-N-FBA | C9: KD | D9: 51.79 | E9: =17.5*19.5*14.5/12/12/12 -> 2.8634983 | F9: =E9*$F$3 -> 20.044488 | G9: 249.99 | H9: 10 | I9: =G9*H9 -> 2499.9 | J9: =$J$3 -> 0.15 | K9: =H9*(1-J9) -> 8.5 | L9: =K9*G9 -> 2124.915 | M9: =L9*$M$3+3%*(H9-K9)*G9 -> 329.9868 | N9: 21.39 | O9: =N9*(H9) -> 213.9 | P9: =L9-M9-O9 -> 1581.0282 | Q9: =I9*$Q$3 -> 624.975 | R9: =I9*$R$3 -> 137.4945 | S9: =P9-Q9-R9 -> 818.5587 | T9: =F9+D9 -> 71.834488 | U9: =D9*(1.05)*(0.15)+D9+F9 -> 79.991413 | V9: =D9*(1.02)*(0.5)+D9+F9 -> 98.247388 | W9: =$H9*T9 -> 718.34488 | X9: =$H9*U9 -> 799.91413 | Y9: =$H9*V9 -> 982.47388 | Z9: =$S9-W9 -> 100.21382 | AA9: =$S9-X9 -> 18.644572 | AB9: =$S9-Y9 -> -163.91518 | AC9: =Z9/$L9 -> 0.047161332 | AD9: =AA9/$L9 -> 0.008774267 | AE9: =AB9/$L9 -> -0.07713964 | AF9: =AS9/AG9 -> 0.30769231 | AG9: 39 | AH9: =W9/L9 -> 0.33805817 | AI9: =X9/$L9 -> 0.37644524 | AJ9: =Y9/$L9 -> 0.46235914 | AS9: 12
B10: RH-DR005MW-FBA | C10: KD | D10: 14.88 | E10: =14.5*15*6/12/12/12 -> 0.75520833 | F10: =E10*$F$3 -> 5.2864583 | G10: 99.99 | H10: 18 | I10: =G10*H10 -> 1799.82 | J10: =$J$3 -> 0.15 | K10: =H10*(1-J10) -> 15.3 | L10: =K10*G10 -> 1529.847 | M10: =L10*$M$3+3%*(H10-K10)*G10 -> 237.57624 | N10: 11.71 | O10: =N10*(H10) -> 210.78 | P10: =L10-M10-O10 -> 1081.4908 | Q10: =I10*$Q$3 -> 449.955 | R10: =I10*$R$3 -> 98.9901 | S10: =P10-Q10-R10 -> 532.54566 | T10: =F10+D10 -> 20.166458 | U10: =D10*(1.05)*(0.15)+D10+F10 -> 22.510058 | V10: =D10*(1.02)*(0.5)+D10+F10 -> 27.755258 | W10: =$H10*T10 -> 362.99625 | X10: =$H10*U10 -> 405.18105 | Y10: =$H10*V10 -> 499.59465 | Z10: =$S10-W10 -> 169.54941 | AA10: =$S10-X10 -> 127.36461 | AB10: =$S10-Y10 -> 32.95101 | AC10: =Z10/$L10 -> 0.11082769 | AD10: =AA10/$L10 -> 0.083253168 | AE10: =AB10/$L10 -> 0.021538762 | AF10: =AS10/AG10 -> 0.10714286 | AG10: 56 | AH10: =W10/L10 -> 0.23727618 | AI10: =X10/$L10 -> 0.2648507 | AJ10: =Y10/$L10 -> 0.32656511 | AS10: 6
B11: ET009 | C11: Non-KD | D11: {=INDEX('Ex-Factory cost'!$C$3:$C$108,MATCH(B11,'Ex-Factory cost'!$B$3:$B$108,0))} -> 26.67 | E11: {=INDEX('Ex-Factory cost'!$D$3:$D$108,MATCH(B11,'Ex-Factory cost'!$B$3:$B$108,0))} -> 2.9 | F11: =E11*$F$3 -> 20.3 | G11: 149.99 | H11: 26 | I11: =G11*H11 -> 3899.74 | J11: =$J$3 -> 0.15 | K11: =H11*(1-J11) -> 22.1 | L11: =K11*G11 -> 3314.779 | M11: =L11*$M$3+3%*(H11-K11)*G11 -> 514.76568 | N11: 24.33 | O11: =N11*(H11) -> 632.58 | P11: =L11-M11-O11 -> 2167.4333 | Q11: =I11*$Q$3 -> 974.935 | R11: =I11*$R$3 -> 214.4857 | S11: =P11-Q11-R11 -> 978.01262 | T11: =F11+D11 -> 46.97 | U11: =D11*(1.05)*(0.15)+D11+F11 -> 51.170525 | V11: =D11*(1.02)*(0.5)+D11+F11 -> 60.5717 | W11: =$H11*T11 -> 1221.22 | X11: =$H11*U11 -> 1330.4336 | Y11: =$H11*V11 -> 1574.8642 | Z11: =$S11-W11 -> -243.20738 | AA11: =$S11-X11 -> -352.42103 | AB11: =$S11-Y11 -> -596.85158 | AC11: =Z11/$L11 -> -0.073370617 | AD11: =AA11/$L11 -> -0.10631811 | AE11: =AB11/$L11 -> -0.18005773 | AF11: =AS11/AG11 -> 0 | AG11: 56 | AH11: =W11/L11 -> 0.36841672 | AI11: =X11/$L11 -> 0.40136421 | AJ11: =Y11/$L11 -> 0.47510383
B12: ET043MTMS | C12: KD | D12: {=INDEX('Ex-Factory cost'!$C$3:$C$108,MATCH(B12,'Ex-Factory cost'!$B$3:$B$108,0))} -> 14.29 | E12: {=INDEX('Ex-Factory cost'!$D$3:$D$108,MATCH(B12,'Ex-Factory cost'!$B$3:$B$108,0))} -> 1.5 | F12: =E12*$F$3 -> 10.5 | G12: 79 | H12: 17 | I12: =G12*H12 -> 1343 | J12: =$J$3 -> 0.15 | K12: =H12*(1-J12) -> 14.45 | L12: =K12*G12 -> 1141.55 | M12: =L12*$M$3+3%*(H12-K12)*G12 -> 177.276 | N12: 18.25 | O12: =N12*(H12) -> 310.25 | P12: =L12-M12-O12 -> 654.024 | Q12: =I12*$Q$3 -> 335.75 | R12: =I12*$R$3 -> 73.865 | S12: =P12-Q12-R12 -> 244.409 | T12: =F12+D12 -> 24.79 | U12: =D12*(1.05)*(0.15)+D12+F12 -> 27.040675 | V12: =D12*(1.02)*(0.5)+D12+F12 -> 32.0779 | W12: =$H12*T12 -> 421.43 | X12: =$H12*U12 -> 459.69148 | Y12: =$H12*V12 -> 545.3243 | Z12: =$S12-W12 -> -177.021 | AA12: =$S12-X12 -> -215.28248 | AB12: =$S12-Y12 -> -300.9153 | AC12: =Z12/$L12 -> -0.15507074 | AD12: =AA12/$L12 -> -0.18858786 | AE12: =AB12/$L12 -> -0.26360238 | AF12: =AS12/AG12 -> 0 | AG12: 56 | AH12: =W12/L12 -> 0.36917349 | AI12: =X12/$L12 -> 0.40269062 | AJ12: =Y12/$L12 -> 0.47770514
B13: DR003MWW(D) | C13: KD | D13: {=INDEX('Ex-Factory cost'!$C$3:$C$108,MATCH(B13,'Ex-Factory cost'!$B$3:$B$108,0))} -> 13.69 | E13: {=INDEX('Ex-Factory cost'!$D$3:$D$108,MATCH(B13,'Ex-Factory cost'!$B$3:$B$108,0))} -> 0.7 | F13: =E13*$F$3 -> 4.9 | G13: 59.99 | H13: 16 | I13: =G13*H13 -> 959.84 | J13: =$J$3 -> 0.15 | K13: =H13*(1-J13) -> 13.6 | L13: =K13*G13 -> 815.864 | M13: =L13*$M$3+3%*(H13-K13)*G13 -> 126.69888 | N13: 14.07 | O13: =N13*(H13) -> 225.12 | P13: =L13-M13-O13 -> 464.04512 | Q13: =I13*$Q$3 -> 239.96 | R13: =I13*$R$3 -> 52.7912 | S13: =P13-Q13-R13 -> 171.29392 | T13: =F13+D13 -> 18.59 | U13: =D13*(1.05)*(0.15)+D13+F13 -> 20.746175 | V13: =D13*(1.02)*(0.5)+D13+F13 -> 25.5719 | W13: =$H13*T13 -> 297.44 | X13: =$H13*U13 -> 331.9388 | Y13: =$H13*V13 -> 409.1504 | Z13: =$S13-W13 -> -126.14608 | AA13: =$S13-X13 -> -160.64488 | AB13: =$S13-Y13 -> -237.85648 | AC13: =Z13/$L13 -> -0.15461655 | AD13: =AA13/$L13 -> -0.19690154 | AE13: =AB13/$L13 -> -0.29153937 | AF13: =AS13/AG13 -> 0 | AG13: 56 | AH13: =W13/L13 -> 0.36457057 | AI13: =X13/$L13 -> 0.40685555 | AJ13: =Y13/$L13 -> 0.50149339
B14: DR004MB | C14: KD | D14: {=INDEX('Ex-Factory cost'!$C$3:$C$108,MATCH(B14,'Ex-Factory cost'!$B$3:$B$108,0))} -> 14.88 | E14: {=INDEX('Ex-Factory cost'!$D$3:$D$108,MATCH(B14,'Ex-Factory cost'!$B$3:$B$108,0))} -> 0.9 | F14: =E14*$F$3 -> 6.3 | G14: 66.99 | H14: 15 | I14: =G14*H14 -> 1004.85 | J14: =$J$3 -> 0.15 | K14: =H14*(1-J14) -> 12.75 | L14: =K14*G14 -> 854.1225 | M14: =L14*$M$3+3%*(H14-K14)*G14 -> 132.6402 | N14: 14.83 | O14: =N14*(H14) -> 222.45 | P14: =L14-M14-O14 -> 499.0323 | Q14: =I14*$Q$3 -> 251.2125 | R14: =I14*$R$3 -> 55.26675 | S14: =P14-Q14-R14 -> 192.55305 | T14: =F14+D14 -> 21.18 | U14: =D14*(1.05)*(0.15)+D14+F14 -> 23.5236 | V14: =D14*(1.02)*(0.5)+D14+F14 -> 28.7688 | W14: =$H14*T14 -> 317.7 | X14: =$H14*U14 -> 352.854 | Y14: =$H14*V14 -> 431.532 | Z14: =$S14-W14 -> -125.14695 | AA14: =$S14-X14 -> -160.30095 | AB14: =$S14-Y14 -> -238.97895 | AC14: =Z14/$L14 -> -0.14652108 | AD14: =AA14/$L14 -> -0.18767911 | AE14: =AB14/$L14 -> -0.2797947 | AF14: =AS14/AG14 -> 0 | AG14: 56 | AH14: =W14/L14 -> 0.3719607 | AI14: =X14/$L14 -> 0.41311873 | AJ14: =Y14/$L14 -> 0.50523432
B15: ET003-W | C15: KD | D15: {=INDEX('Ex-Factory cost'!$C$3:$C$108,MATCH(B15,'Ex-Factory cost'!$B$3:$B$108,0))} -> 51.79 | E15: {=INDEX('Ex-Factory cost'!$D$3:$D$108,MATCH(B15,'Ex-Factory cost'!$B$3:$B$108,0))} -> 2.9 | F15: =E15*$F$3 -> 20.3 | G15: 191.99 | H15: 14 | I15: =G15*H15 -> 2687.86 | J15: =$J$3 -> 0.15 | K15: =H15*(1-J15) -> 11.9 | L15: =K15*G15 -> 2284.681 | M15: =L15*$M$3+3%*(H15-K15)*G15 -> 354.79752 | N15: 21 | O15: =N15*(H15) -> 294 | P15: =L15-M15-O15 -> 1635.8835 | Q15: =I15*$Q$3 -> 671.965 | R15: =I15*$R$3 -> 147.8323 | S15: =P15-Q15-R15 -> 816.08618 | T15: =F15+D15 -> 72.09 | U15: =D15*(1.05)*(0.15)+D15+F15 -> 80.246925 | V15: =D15*(1.02)*(0.5)+D15+F15 -> 98.5029 | W15: =$H15*T15 -> 1009.26 | X15: =$H15*U15 -> 1123.457 | Y15: =$H15*V15 -> 1379.0406 | Z15: =$S15-W15 -> -193.17382 | AA15: =$S15-X15 -> -307.37077 | AB15: =$S15-Y15 -> -562.95442 | AC15: =Z15/$L15 -> -0.084551769 | AD15: =AA15/$L15 -> -0.13453553 | AE15: =AB15/$L15 -> -0.24640395 | AF15: =AS15/AG15 -> 0 | AG15: 56 | AH15: =W15/L15 -> 0.44175095 | AI15: =X15/$L15 -> 0.49173471 | AJ15: =Y15/$L15 -> 0.60360313
B16: ET008 | C16: Non-KD | D16: {=INDEX('Ex-Factory cost'!$C$3:$C$108,MATCH(B16,'Ex-Factory cost'!$B$3:$B$108,0))} -> 29.76 | E16: {=INDEX('Ex-Factory cost'!$D$3:$D$108,MATCH(B16,'Ex-Factory cost'!$B$3:$B$108,0))} -> 4.6 | F16: =E16*$F$3 -> 32.2 | G16: 209 | H16: 16 | I16: =G16*H16 -> 3344 | J16: =$J$3 -> 0.15 | K16: =H16*(1-J16) -> 13.6 | L16: =K16*G16 -> 2842.4 | M16: =L16*$M$3+3%*(H16-K16)*G16 -> 441.408 | N16: 45.18 | O16: =N16*(H16) -> 722.88 | P16: =L16-M16-O16 -> 1678.112 | Q16: =I16*$Q$3 -> 836 | R16: =I16*$R$3 -> 183.92 | S16: =P16-Q16-R16 -> 658.192 | T16: =F16+D16 -> 61.96 | U16: =D16*(1.05)*(0.15)+D16+F16 -> 66.6472 | V16: =D16*(1.02)*(0.5)+D16+F16 -> 77.1376 | W16: =$H16*T16 -> 991.36 | X16: =$H16*U16 -> 1066.3552 | Y16: =$H16*V16 -> 1234.2016 | Z16: =$S16-W16 -> -333.168 | AA16: =$S16-X16 -> -408.1632 | AB16: =$S16-Y16 -> -576.0096 | AC16: =Z16/$L16 -> -0.11721362 | AD16: =AA16/$L16 -> -0.14359809 | AE16: =AB16/$L16 -> -0.20264903 | AF16: =AS16/AG16 -> 0 | AG16: 56 | AH16: =W16/L16 -> 0.34877568 | AI16: =X16/$L16 -> 0.37516015 | AJ16: =Y16/$L16 -> 0.43421109
B17: DR003MW | C17: KD | D17: {=INDEX('Ex-Factory cost'!$C$3:$C$108,MATCH(B17,'Ex-Factory cost'!$B$3:$B$108,0))} -> 13.69 | E17: {=INDEX('Ex-Factory cost'!$D$3:$D$108,MATCH(B17,'Ex-Factory cost'!$B$3:$B$108,0))} -> 0.7 | F17: =E17*$F$3 -> 4.9 | G17: 59.99 | H17: 7 | I17: =G17*H17 -> 419.93 | J17: =$J$3 -> 0.15 | K17: =H17*(1-J17) -> 5.95 | L17: =K17*G17 -> 356.9405 | M17: =L17*$M$3+3%*(H17-K17)*G17 -> 55.43076 | N17: 14.07 | O17: =N17*(H17) -> 98.49 | P17: =L17-M17-O17 -> 203.01974 | Q17: =I17*$Q$3 -> 104.9825 | R17: =I17*$R$3 -> 23.09615 | S17: =P17-Q17-R17 -> 74.94109 | T17: =F17+D17 -> 18.59 | U17: =D17*(1.05)*(0.15)+D17+F17 -> 20.746175 | V17: =D17*(1.02)*(0.5)+D17+F17 -> 25.5719 | W17: =$H17*T17 -> 130.13 | X17: =$H17*U17 -> 145.22323 | Y17: =$H17*V17 -> 179.0033 | Z17: =$S17-W17 -> -55.18891 | AA17: =$S17-X17 -> -70.282135 | AB17: =$S17-Y17 -> -104.06221 | AC17: =Z17/$L17 -> -0.15461655 | AD17: =AA17/$L17 -> -0.19690154 | AE17: =AB17/$L17 -> -0.29153937 | AF17: =AS17/AG17 -> 0 | AG17: 56 | AH17: =W17/L17 -> 0.36457057 | AI17: =X17/$L17 -> 0.40685555 | AJ17: =Y17/$L17 -> 0.50149339
B18: CT001MW-18H | C18: KD | D18: {=INDEX('Ex-Factory cost'!$C$3:$C$108,MATCH(B18,'Ex-Factory cost'!$B$3:$B$108,0))} -> 82.14 | E18: {=INDEX('Ex-Factory cost'!$D$3:$D$108,MATCH(B18,'Ex-Factory cost'!$B$3:$B$108,0))} -> 4.9 | F18: =E18*$F$3 -> 34.3 | G18: 369.99 | H18: 6 | I18: =G18*H18 -> 2219.94 | J18: =$J$3 -> 0.15 | K18: =H18*(1-J18) -> 5.1 | L18: =K18*G18 -> 1886.949 | M18: =L18*$M$3+3%*(H18-K18)*G18 -> 293.03208 | N18: =12%*G18 -> 44.3988 | O18: =N18*(H18) -> 266.3928 | P18: =L18-M18-O18 -> 1327.5241 | Q18: =I18*$Q$3 -> 554.985 | R18: =I18*$R$3 -> 122.0967 | S18: =P18-Q18-R18 -> 650.44242 | T18: =F18+D18 -> 116.44 | U18: =D18*(1.05)*(0.15)+D18+F18 -> 129.37705 | V18: =D18*(1.02)*(0.5)+D18+F18 -> 158.3314 | W18: =$H18*T18 -> 698.64 | X18: =$H18*U18 -> 776.2623 | Y18: =$H18*V18 -> 949.9884 | Z18: =$S18-W18 -> -48.19758 | AA18: =$S18-X18 -> -125.81988 | AB18: =$S18-Y18 -> -299.54598 | AC18: =Z18/$L18 -> -0.025542598 | AD18: =AA18/$L18 -> -0.066679004 | AE18: =AB18/$L18 -> -0.1587462 | AF18: =AS18/AG18 -> 0 | AG18: 56 | AH18: =W18/L18 -> 0.37024848 | AI18: =X18/$L18 -> 0.41138489 | AJ18: =Y18/$L18 -> 0.50345208
B19: CT001 | C19: KD | D19: {=INDEX('Ex-Factory cost'!$C$3:$C$108,MATCH(B19,'Ex-Factory cost'!$B$3:$B$108,0))} -> 73.81 | E19: {=INDEX('Ex-Factory cost'!$D$3:$D$108,MATCH(B19,'Ex-Factory cost'!$B$3:$B$108,0))} -> 4.5 | F19: =E19*$F$3 -> 31.5 | G19: 369.99 | H19: 7 | I19: =G19*H19 -> 2589.93 | J19: =$J$3 -> 0.15 | K19: =H19*(1-J19) -> 5.95 | L19: =K19*G19 -> 2201.4405 | M19: =L19*$M$3+3%*(H19-K19)*G19 -> 341.87076 | N19: =12%*G19 -> 44.3988 | O19: =N19*(H19) -> 310.7916 | P19: =L19-M19-O19 -> 1548.7781 | Q19: =I19*$Q$3 -> 647.4825 | R19: =I19*$R$3 -> 142.44615 | S19: =P19-Q19-R19 -> 758.84949 | T19: =F19+D19 -> 105.31 | U19: =D19*(1.05)*(0.15)+D19+F19 -> 116.93507 | V19: =D19*(1.02)*(0.5)+D19+F19 -> 142.9531 | W19: =$H19*T19 -> 737.17 | X19: =$H19*U19 -> 818.54552 | Y19: =$H19*V19 -> 1000.6717 | Z19: =$S19-W19 -> 21.67949 | AA19: =$S19-X19 -> -59.696035 | AB19: =$S19-Y19 -> -241.82221 | AC19: =Z19/$L19 -> 0.0098478655 | AD19: =AA19/$L19 -> -0.027116806 | AE19: =AB19/$L19 -> -0.10984726 | AF19: =AS19/AG19 -> 0 | AG19: 56 | AH19: =W19/L19 -> 0.33485802 | AI19: =X19/$L19 -> 0.37182269 | AJ19: =Y19/$L19 -> 0.45455314
B20: CT009 | C20: Non-KD | D20: {=INDEX('Ex-Factory cost'!$C$3:$C$108,MATCH(B20,'Ex-Factory cost'!$B$3:$B$108,0))} -> 88.1 | E20: {=INDEX('Ex-Factory cost'!$D$3:$D$108,MATCH(B20,'Ex-Factory cost'!$B$3:$B$108,0))} -> 12.4 | F20: =E20*$F$3 -> 86.8 | G20: 571.99 | H20: 8 | I20: =G20*H20 -> 4575.92 | J20: =$J$3 -> 0.15 | K20: =H20*(1-J20) -> 6.8 | L20: =K20*G20 -> 3889.532 | M20: =L20*$M$3+3%*(H20-K20)*G20 -> 604.02144 | N20: 203 | O20: =N20*(H20) -> 1624 | P20: =L20-M20-O20 -> 1661.5106 | Q20: =I20*$Q$3 -> 1143.98 | R20: =I20*$R$3 -> 251.6756 | S20: =P20-Q20-R20 -> 265.85496 | T20: =F20+D20 -> 174.9 | U20: =D20*(1.05)*(0.15)+D20+F20 -> 188.77575 | V20: =D20*(1.02)*(0.5)+D20+F20 -> 219.831 | W20: =$H20*T20 -> 1399.2 | X20: =$H20*U20 -> 1510.206 | Y20: =$H20*V20 -> 1758.648 | Z20: =$S20-W20 -> -1133.345 | AA20: =$S20-X20 -> -1244.351 | AB20: =$S20-Y20 -> -1492.793 | AC20: =Z20/$L20 -> -0.2913834 | AD20: =AA20/$L20 -> -0.31992308 | AE20: =AB20/$L20 -> -0.3837976 | AF20: =AS20/AG20 -> 0 | AG20: 56 | AH20: =W20/L20 -> 0.3597348 | AI20: =X20/$L20 -> 0.38827448 | AJ20: =Y20/$L20 -> 0.452149
B21: ET004 | C21: Non-KD | D21: {=INDEX('Ex-Factory cost'!$C$3:$C$108,MATCH(B21,'Ex-Factory cost'!$B$3:$B$108,0))} -> 46.27 | E21: {=INDEX('Ex-Factory cost'!$D$3:$D$108,MATCH(B21,'Ex-Factory cost'!$B$3:$B$108,0))} -> 4.8 | F21: =E21*$F$3 -> 33.6 | G21: 175 | H21: 10 | I21: =G21*H21 -> 1750 | J21: =$J$3 -> 0.15 | K21: =H21*(1-J21) -> 8.5 | L21: =K21*G21 -> 1487.5 | M21: =L21*$M$3+3%*(H21-K21)*G21 -> 231 | N21: =17%*G21 -> 29.75 | O21: =N21*(H21) -> 297.5 | P21: =L21-M21-O21 -> 959 | Q21: =I21*$Q$3 -> 437.5 | R21: =I21*$R$3 -> 96.25 | S21: =P21-Q21-R21 -> 425.25 | T21: =F21+D21 -> 79.87 | U21: =D21*(1.05)*(0.15)+D21+F21 -> 87.157525 | V21: =D21*(1.02)*(0.5)+D21+F21 -> 103.4677 | W21: =$H21*T21 -> 798.7 | X21: =$H21*U21 -> 871.57525 | Y21: =$H21*V21 -> 1034.677 | Z21: =$S21-W21 -> -373.45 | AA21: =$S21-X21 -> -446.32525 | AB21: =$S21-Y21 -> -609.427 | AC21: =Z21/$L21 -> -0.25105882 | AD21: =AA21/$L21 -> -0.30005059 | AE21: =AB21/$L21 -> -0.40969882 | AF21: =AS21/AG21 -> 0 | AG21: 56 | AH21: =W21/L21 -> 0.53694118 | AI21: =X21/$L21 -> 0.58593294 | AJ21: =Y21/$L21 -> 0.69558118
B22: ET005 | C22: Non-KD | D22: {=INDEX('Ex-Factory cost'!$C$3:$C$108,MATCH(B22,'Ex-Factory cost'!$B$3:$B$108,0))} -> 57.14 | E22: {=INDEX('Ex-Factory cost'!$D$3:$D$108,MATCH(B22,'Ex-Factory cost'!$B$3:$B$108,0))} -> 5.7 | F22: =E22*$F$3 -> 39.9 | G22: 248 | H22: 7 | I22: =G22*H22 -> 1736 | J22: =$J$3 -> 0.15 | K22: =H22*(1-J22) -> 5.95 | L22: =K22*G22 -> 1475.6 | M22: =L22*$M$3+3%*(H22-K22)*G22 -> 229.152 | N22: =17%*G22 -> 42.16 | O22: =N22*(H22) -> 295.12 | P22: =L22-M22-O22 -> 951.328 | Q22: =I22*$Q$3 -> 434 | R22: =I22*$R$3 -> 95.48 | S22: =P22-Q22-R22 -> 421.848 | T22: =F22+D22 -> 97.04 | U22: =D22*(1.05)*(0.15)+D22+F22 -> 106.03955 | V22: =D22*(1.02)*(0.5)+D22+F22 -> 126.1814 | W22: =$H22*T22 -> 679.28 | X22: =$H22*U22 -> 742.27685 | Y22: =$H22*V22 -> 883.2698 | Z22: =$S22-W22 -> -257.432 | AA22: =$S22-X22 -> -320.42885 | AB22: =$S22-Y22 -> -461.4218 | AC22: =Z22/$L22 -> -0.1744592 | AD22: =AA22/$L22 -> -0.21715157 | AE22: =AB22/$L22 -> -0.31270114 | AF22: =AS22/AG22 -> 0 | AG22: 56 | AH22: =W22/L22 -> 0.46034156 | AI22: =X22/$L22 -> 0.50303392 | AJ22: =Y22/$L22 -> 0.59858349
B23: ET013 | C23: Non-KD | D23: {=INDEX('Ex-Factory cost'!$C$3:$C$108,MATCH(B23,'Ex-Factory cost'!$B$3:$B$108,0))} -> 47.62 | E23: {=INDEX('Ex-Factory cost'!$D$3:$D$108,MATCH(B23,'Ex-Factory cost'!$B$3:$B$108,0))} -> 6.4 | F23: =E23*$F$3 -> 44.8 | G23: 189 | H23: 14 | I23: =G23*H23 -> 2646 | J23: =$J$3 -> 0.15 | K23: =H23*(1-J23) -> 11.9 | L23: =K23*G23 -> 2249.1 | M23: =L23*$M$3+3%*(H23-K23)*G23 -> 349.272 | N23: =17%*G23 -> 32.13 | O23: =N23*(H23) -> 449.82 | P23: =L23-M23-O23 -> 1450.008 | Q23: =I23*$Q$3 -> 661.5 | R23: =I23*$R$3 -> 145.53 | S23: =P23-Q23-R23 -> 642.978 | T23: =F23+D23 -> 92.42 | U23: =D23*(1.05)*(0.15)+D23+F23 -> 99.92015 | V23: =D23*(1.02)*(0.5)+D23+F23 -> 116.7062 | W23: =$H23*T23 -> 1293.88 | X23: =$H23*U23 -> 1398.8821 | Y23: =$H23*V23 -> 1633.8868 | Z23: =$S23-W23 -> -650.902 | AA23: =$S23-X23 -> -755.9041 | AB23: =$S23-Y23 -> -990.9088 | AC23: =Z23/$L23 -> -0.28940554 | AD23: =AA23/$L23 -> -0.33609181 | AE23: =AB23/$L23 -> -0.44058014 | AF23: =AS23/AG23 -> 0 | AG23: 56 | AH23: =W23/L23 -> 0.57528789 | AI23: =X23/$L23 -> 0.62197417 | AJ23: =Y23/$L23 -> 0.7264625
B24: ET012 | C24: KD | D24: {=INDEX('Ex-Factory cost'!$C$3:$C$108,MATCH(B24,'Ex-Factory cost'!$B$3:$B$108,0))} -> 26.19 | E24: {=INDEX('Ex-Factory cost'!$D$3:$D$108,MATCH(B24,'Ex-Factory cost'!$B$3:$B$108,0))} -> 3.2 | F24: =E24*$F$3 -> 22.4 | G24: 179.99 | H24: 10 | I24: =G24*H24 -> 1799.9 | J24: =$J$3 -> 0.15 | K24: =H24*(1-J24) -> 8.5 | L24: =K24*G24 -> 1529.915 | M24: =L24*$M$3+3%*(H24-K24)*G24 -> 237.5868 | N24: =11%*G24 -> 19.7989 | O24: =N24*(H24) -> 197.989 | P24: =L24-M24-O24 -> 1094.3392 | Q24: =I24*$Q$3 -> 449.975 | R24: =I24*$R$3 -> 98.9945 | S24: =P24-Q24-R24 -> 545.3697 | T24: =F24+D24 -> 48.59 | U24: =D24*(1.05)*(0.15)+D24+F24 -> 52.714925 | V24: =D24*(1.02)*(0.5)+D24+F24 -> 61.9469 | W24: =$H24*T24 -> 485.9 | X24: =$H24*U24 -> 527.14925 | Y24: =$H24*V24 -> 619.469 | Z24: =$S24-W24 -> 59.4697 | AA24: =$S24-X24 -> 18.22045 | AB24: =$S24-Y24 -> -74.0993 | AC24: =Z24/$L24 -> 0.038871244 | AD24: =AA24/$L24 -> 0.011909452 | AE24: =AB24/$L24 -> -0.048433606 | AF24: =AS24/AG24 -> 0 | AG24: 56 | AH24: =W24/L24 -> 0.31759934 | AI24: =X24/$L24 -> 0.34456114 | AJ24: =Y24/$L24 -> 0.40490419
B25: ET067MB | C25: KD | D25: {=INDEX('Ex-Factory cost'!$C$3:$C$108,MATCH(B25,'Ex-Factory cost'!$B$3:$B$108,0))} -> 29.76 | E25: {=INDEX('Ex-Factory cost'!$D$3:$D$108,MATCH(B25,'Ex-Factory cost'!$B$3:$B$108,0))} -> 1.9 | F25: =E25*$F$3 -> 13.3 | G25: 179 | H25: 1 | I25: =G25*H25 -> 179 | J25: =$J$3 -> 0.15 | K25: =H25*(1-J25) -> 0.85 | L25: =K25*G25 -> 152.15 | M25: =L25*$M$3+3%*(H25-K25)*G25 -> 23.628 | N25: =11%*G25 -> 19.69 | O25: =N25*(H25) -> 19.69 | P25: =L25-M25-O25 -> 108.832 | Q25: =I25*$Q$3 -> 44.75 | R25: =I25*$R$3 -> 9.845 | S25: =P25-Q25-R25 -> 54.237 | T25: =F25+D25 -> 43.06 | U25: =D25*(1.05)*(0.15)+D25+F25 -> 47.7472 | V25: =D25*(1.02)*(0.5)+D25+F25 -> 58.2376 | W25: =$H25*T25 -> 43.06 | X25: =$H25*U25 -> 47.7472 | Y25: =$H25*V25 -> 58.2376 | Z25: =$S25-W25 -> 11.177 | AA25: =$S25-X25 -> 6.4898 | AB25: =$S25-Y25 -> -4.0006 | AC25: =Z25/$L25 -> 0.073460401 | AD25: =AA25/$L25 -> 0.04265396 | AE25: =AB25/$L25 -> -0.026293789 | AF25: =AS25/AG25 -> 0 | AG25: 56 | AH25: =W25/L25 -> 0.28301019 | AI25: =X25/$L25 -> 0.31381663 | AJ25: =Y25/$L25 -> 0.38276438
B26: ET044MC | C26: KD | D26: {=INDEX('Ex-Factory cost'!$C$3:$C$108,MATCH(B26,'Ex-Factory cost'!$B$3:$B$108,0))} -> 53.57 | E26: {=INDEX('Ex-Factory cost'!$D$3:$D$108,MATCH(B26,'Ex-Factory cost'!$B$3:$B$108,0))} -> 3.8 | F26: =E26*$F$3 -> 26.6 | G26: 179 | H26: 1 | I26: =G26*H26 -> 179 | J26: =$J$3 -> 0.15 | K26: =H26*(1-J26) -> 0.85 | L26: =K26*G26 -> 152.15 | M26: =L26*$M$3+3%*(H26-K26)*G26 -> 23.628 | N26: =11%*G26 -> 19.69 | O26: =N26*(H26) -> 19.69 | P26: =L26-M26-O26 -> 108.832 | Q26: =I26*$Q$3 -> 44.75 | R26: =I26*$R$3 -> 9.845 | S26: =P26-Q26-R26 -> 54.237 | T26: =F26+D26 -> 80.17 | U26: =D26*(1.05)*(0.15)+D26+F26 -> 88.607275 | V26: =D26*(1.02)*(0.5)+D26+F26 -> 107.4907 | W26: =$H26*T26 -> 80.17 | X26: =$H26*U26 -> 88.607275 | Y26: =$H26*V26 -> 107.4907 | Z26: =$S26-W26 -> -25.933 | AA26: =$S26-X26 -> -34.370275 | AB26: =$S26-Y26 -> -53.2537 | AC26: =Z26/$L26 -> -0.17044364 | AD26: =AA26/$L26 -> -0.22589731 | AE26: =AB26/$L26 -> -0.35000789 | AF26: =AS26/AG26 -> 0 | AG26: 56 | AH26: =W26/L26 -> 0.52691423 | AI26: =X26/$L26 -> 0.58236789 | AJ26: =Y26/$L26 -> 0.70647848
B27: CT007 | C27: KD | D27: {=INDEX('Ex-Factory cost'!$C$3:$C$108,MATCH(B27,'Ex-Factory cost'!$B$3:$B$108,0))} -> 94.05 | E27: {=INDEX('Ex-Factory cost'!$D$3:$D$108,MATCH(B27,'Ex-Factory cost'!$B$3:$B$108,0))} -> 4.7 | F27: =E27*$F$3 -> 32.9 | T27: =F27+D27 -> 126.95 | U27: =D27*(1.05)*(0.15)+D27+F27 -> 141.76288 | V27: =D27*(1.02)*(0.5)+D27+F27 -> 174.9155
B28: CT009MW-18H | C28: Non-KD | D28: {=INDEX('Ex-Factory cost'!$C$3:$C$108,MATCH(B28,'Ex-Factory cost'!$B$3:$B$108,0))} -> 92.86 | E28: {=INDEX('Ex-Factory cost'!$D$3:$D$108,MATCH(B28,'Ex-Factory cost'!$B$3:$B$108,0))} -> 14.5 | F28: =E28*$F$3 -> 101.5 | T28: =F28+D28 -> 194.36 | U28: =D28*(1.05)*(0.15)+D28+F28 -> 208.98545 | V28: =D28*(1.02)*(0.5)+D28+F28 -> 241.7186
B29: CT068MC | D29: {=INDEX('Ex-Factory cost'!$C$3:$C$108,MATCH(B29,'Ex-Factory cost'!$B$3:$B$108,0))} -> 82.14 | E29: {=INDEX('Ex-Factory cost'!$D$3:$D$108,MATCH(B29,'Ex-Factory cost'!$B$3:$B$108,0))} -> 8.3 | F29: =E29*$F$3 -> 58.1 | T29: =F29+D29 -> 140.24 | U29: =D29*(1.05)*(0.15)+D29+F29 -> 153.17705 | V29: =D29*(1.02)*(0.5)+D29+F29 -> 182.1314
B30: ET041MW | C30: KD | D30: {=INDEX('Ex-Factory cost'!$C$3:$C$108,MATCH(B30,'Ex-Factory cost'!$B$3:$B$108,0))} -> 32.14 | E30: {=INDEX('Ex-Factory cost'!$D$3:$D$108,MATCH(B30,'Ex-Factory cost'!$B$3:$B$108,0))} -> 2.6 | F30: =E30*$F$3 -> 18.2 | G30: 190.99 | H30: 6 | I30: =G30*H30 -> 1145.94 | J30: =$J$3 -> 0.15 | K30: =H30*(1-J30) -> 5.1 | L30: =K30*G30 -> 974.049 | M30: =L30*$M$3+3%*(H30-K30)*G30 -> 151.26408 | N30: 21.67 | O30: =N30*(H30) -> 130.02 | P30: =L30-M30-O30 -> 692.76492 | Q30: =I30*$Q$3 -> 286.485 | R30: =I30*$R$3 -> 63.0267 | S30: =P30-Q30-R30 -> 343.25322 | T30: =F30+D30 -> 50.34 | U30: =D30*(1.05)*(0.15)+D30+F30 -> 55.40205 | V30: =D30*(1.02)*(0.5)+D30+F30 -> 66.7314 | W30: =$H30*T30 -> 302.04 | X30: =$H30*U30 -> 332.4123 | Y30: =$H30*V30 -> 400.3884 | Z30: =$S30-W30 -> 41.21322 | AA30: =$S30-X30 -> 10.84092 | AB30: =$S30-Y30 -> -57.13518 | AC30: =Z30/$L30 -> 0.042311239 | AD30: =AA30/$L30 -> 0.011129748 | AE30: =AB30/$L30 -> -0.058657398 | AF30: =AS30/AG30 -> 0 | AG30: 56 | AH30: =W30/L30 -> 0.31008707 | AI30: =X30/$L30 -> 0.34126856 | AJ30: =Y30/$L30 -> 0.41105571
B31: Aggregate | I31: =SUM(I3:I30) -> 49969.68 | L31: =SUM(L3:L30) -> 42474.228 | M31: =SUM(M3:M30) -> 6596.1478 | O31: =SUM(O3:O30) -> 8332.6934 | P31: =SUM(P3:P30) -> 27545.537 | Q31: =SUM(Q3:Q30) -> 12492.67 | R31: =SUM(R3:R30) -> 2748.3874 | S31: =SUM(S3:S30) -> 12304.784 | W31: =sum(W5:W10) -> 4030.6825 | X31: =sum(X5:X10) -> 4409.8732 | Y31: =sum(Y5:Y10) -> 5258.5381 | Z31: =SUM(Z3:Z30) -> -2632.478 | AA31: =SUM(AA3:AA30) -> -4028.7061 | AB31: =SUM(AB3:AB30) -> -7153.5974 | AC31: =Z31/$L31 -> -0.061978243 | AD31: =AA31/$L31 -> -0.094850602 | AE31: =AB31/$L31 -> -0.16842207 | AF31: =AS31/AG31 -> 0.14695341 | AG31: =SUM(AG5:AG10) -> 279 | AH31: =W31/L31 -> 0.094897133 | AI31: =X31/$L31 -> 0.10382468 | AJ31: =Y31/$L31 -> 0.12380538 | AS31: =SUM(AS5:AS10) -> 41
N33: =N5/G5 -> 0.10967398 | S33: Discount on manufacturing cost | T33: 0.1
N34: =N6/G6 -> 0.10967398
B35: SKU | N35: =N7/G7 -> 0.17301153 | T35: COGS 0% Tariff | U35: COGS 15% Tariff | V35: COGS 50% Tariff | W35: Gross COGS 0% Tariff | X35: Gross COGS 25% Tariff | Y35: Gross COGS 50% Tariff | Z35: Net Margin 0% Tariff | AA35: Net Margin 25% Tariff | AB35: Net Margin 50% Tariff | AC35: % Net Margin 0% Tariff | AD35: % Net margin 25% Tariff | AE35: % Net margin 50% Tariff
B36: RH-ET042MB(D)-FBA | N36: =N8/G8 -> 0.17451247 | T36: =F5+D5*(1-$T$33) -> 27.7385 | U36: =D5*(1.02)*(1.25)*(1-$T$33)+F5 -> 32.5994 | V36: =D5*(1.02)*(1.5)*(1-$T$33)+F5 -> 37.10678 | W36: =$H5*T36 -> 721.201 | X36: =$H5*U36 -> 847.5844 | Y36: =$H5*V36 -> 964.77628 | Z36: =$S5-W36 -> 461.69162 | AA36: =$S5-X36 -> 335.30822 | AB36: =$S5-Y36 -> 218.11634 | AC36: =Z36/$L5 -> 0.13928278 | AD36: =AA36/$L5 -> 0.10115553 | AE36: =AB36/$L5 -> 0.065801171
B37: RH-ET042MW-FBA | N37: =N9/G9 -> 0.085563423 | T37: =F6+D6*(1-$T$33) -> 27.7385 | U37: =D6*(1.02)*(1.25)*(1-$T$33)+F6 -> 32.5994 | V37: =D6*(1.02)*(1.5)*(1-$T$33)+F6 -> 37.10678 | W37: =$H6*T37 -> 721.201 | X37: =$H6*U37 -> 847.5844 | Y37: =$H6*V37 -> 964.77628 | Z37: =$S6-W37 -> 461.69162 | AA37: =$S6-X37 -> 335.30822 | AB37: =$S6-Y37 -> 218.11634 | AC37: =Z37/$L6 -> 0.13928278 | AD37: =AA37/$L6 -> 0.10115553 | AE37: =AB37/$L6 -> 0.065801171
B38: RH-DR002MTMW-FBA | N38: =N10/G10 -> 0.11711171 | T38: =F7+D7*(1-$T$33) -> 38.10424 | U38: =D7*(1.02)*(1.25)*(1-$T$33)+F7 -> 42.37609 | V38: =D7*(1.02)*(1.5)*(1-$T$33)+F7 -> 46.33726 | W38: =$H7*T38 -> 800.18904 | X38: =$H7*U38 -> 889.89789 | Y38: =$H7*V38 -> 973.08246 | Z38: =$S7-W38 -> -44.275773 | AA38: =$S7-X38 -> -133.98462 | AB38: =$S7-Y38 -> -217.16919 | AC38: =Z38/$L7 -> -0.016537339 | AD38: =AA38/$L7 -> -0.050044279 | AE38: =AB38/$L7 -> -0.08111435
B39: RH-DR001MW-FBA | N39: =N11/G11 -> 0.16221081 | T39: =F8+D8*(1-$T$33) -> 34.035519 | U39: =D8*(1.02)*(1.25)*(1-$T$33)+F8 -> 37.718319 | V39: =D8*(1.02)*(1.5)*(1-$T$33)+F8 -> 41.133279 | W39: =$H8*T39 -> 544.5683 | X39: =$H8*U39 -> 603.4931 | Y39: =$H8*V39 -> 658.13246 | Z39: =$S8-W39 -> -10.394376 | AA39: =$S8-X39 -> -69.319176 | AB39: =$S8-Y39 -> -123.95854 | AC39: =Z39/$L8 -> -0.0054596212 | AD39: =AA39/$L8 -> -0.036409731 | AE39: =AB39/$L8 -> -0.065108924
B40: RH-ET003-N-FBA | T40: =F9+D9*(1-$T$33) -> 66.655488 | U40: =D9*(1.02)*(1.25)*(1-$T$33)+F9 -> 79.473513 | V40: =D9*(1.02)*(1.5)*(1-$T$33)+F9 -> 91.359318 | W40: =$H9*T40 -> 666.55488 | X40: =$H9*U40 -> 794.73513 | Y40: =$H9*V40 -> 913.59318 | Z40: =$S9-W40 -> 152.00382 | AA40: =$S9-X40 -> 23.823572 | AB40: =$S9-Y40 -> -95.034478 | AC40: =Z40/$L9 -> 0.071534071 | AD40: =AA40/$L9 -> 0.011211541 | AE40: =AB40/$L9 -> -0.044723896
B41: RH-DR005MW-FBA | T41: =F10+D10*(1-$T$33) -> 18.678458 | U41: =D10*(1.02)*(1.25)*(1-$T$33)+F10 -> 22.361258 | V41: =D10*(1.02)*(1.5)*(1-$T$33)+F10 -> 25.776218 | W41: =$H10*T41 -> 336.21225 | X41: =$H10*U41 -> 402.50265 | Y41: =$H10*V41 -> 463.97193 | Z41: =$S10-W41 -> 196.33341 | AA41: =$S10-X41 -> 130.04301 | AB41: =$S10-Y41 -> 68.57373 | AC41: =Z41/$L10 -> 0.12833532 | AD41: =AA41/$L10 -> 0.085003932 | AE41: =AB41/$L10 -> 0.044823914
B42: Aggregate | W42: =sum(W36:W41) -> 3789.9265 | X42: =sum(X36:X41) -> 4385.7976 | Y42: =sum(Y36:Y41) -> 4938.3326 | Z42: =sum(Z36:Z41) -> 1217.0503 | AA42: =sum(AA36:AA41) -> 621.17922 | AB42: =sum(AB36:AB41) -> 68.644202 | AC42: =Z42/$L31 -> 0.028653854 | AD42: =AA42/$L31 -> 0.01462485 | AE42: =AB42/$L31 -> 0.0016161377
H44: 30 | I44: 79.99 | J44: =H44*I44 -> 2399.7 | T44: Line of action
H45: 2 | I45: 699.99 | J45: =H45*I45 -> 1399.98
H46: 4 | I46: 169.99 | J46: =H46*I46 -> 679.96 | T46: Jodhpur visit
H47: 32 | I47: 189.99 | J47: =H47*I47 -> 6079.68 | T47: - Jugaad billing to bypass tariffs
H48: 22 | I48: 419.99 | J48: =H48*I48 -> 9239.78 | T48: - Non-KD to KD
H49: 24 | I49: 379.99 | J49: =H49*I49 -> 9119.76 | T49: - KD mein 10% Factory price reduction
H50: 34 | I50: 309.99 | J50: =H50*I50 -> 10539.66 | T50: - Inventory sponshirship from Supplier - atleast 1 supplier
H51: 26 | I51: 249.99 | J51: =H51*I51 -> 6499.74
H52: 2 | I52: =249.99+199.99 -> 449.98 | J52: =H52*I52 -> 899.96 | T52: Full potential
H53: 2 | I53: =199.99+229.99 -> 429.98 | J53: =H53*I53 -> 859.96 | T53: - How much can these scale on Amazon
H54: 17 | I54: 279.99 | J54: =H54*I54 -> 4759.83 | T54: - Figure out how big this business can become
H55: 4 | I55: 649.99 | J55: =H55*I55 -> 2599.96 | T55: - Figure out how fast can this business grow
H56: 2 | I56: 449.99 | J56: =H56*I56 -> 899.98 | T56: - This business definition - Selling small KD furniture pieces on amazon which are priced atleast 20-30% higher than median price
H57: 29 | I57: 279.99 | J57: =H57*I57 -> 8119.71 | T57: - Consumer Survey to assess the demand for this business
H58: 7 | I58: 154.99 | J58: =H58*I58 -> 1084.93 | T58: - D2C - How big, How fast, GTM, Unit economics. What learnings can you derive from amazon for this? This question is more for future else there is a risk of getting restricted to becoming AZ seller
H59: 33 | I59: 139.99 | J59: =H59*I59 -> 4619.67
H60: 12 | I60: 139.99 | J60: =H60*I60 -> 1679.88 | T60: India Furniture market - Mayank conversation
H61: 19 | I61: 149.99 | J61: =H61*I61 -> 2849.81 | T61: - Define the business & market questions you want to talk about
H62: 28 | I62: 94.99 | J62: =H62*I62 -> 2659.72 | T62: - Understand his position - What does he wants to do?
H63: 33 | I63: 259.99 | J63: =H63*I63 -> 8579.67
H64: 44 | I64: 199.99 | J64: =H64*I64 -> 8799.56 | T64: New cross-border consumer angles
J65: =sum(J44:J64) -> 94370.9 | T65: - Creating a Temu/Shein from India for products where there is a disproportionate production & supply chain advantage
T67: India focussed business - New Ideas
G69: current amazon sale
G70: Factory cost targets where unit economics becomes viable
G71: Revising price for these SKUs and then letting them sell
G72: How to make a decision on new products - New SKUs in Furniture or Newer categories - This with a long term vision
G78: No. of reviews | H78: Rating
G79: 7 | H79: 3.9 | I79: =G79*H79 -> 27.3
G80: 36 | H80: 4.4 | I80: =G80*H80 -> 158.4
G81: 3 | H81: 5 | I81: =G81*H81 -> 15
G82: 8 | H82: 3.9 | I82: =G82*H82 -> 31.2
G83: 8 | H83: 3.8 | I83: =G83*H83 -> 30.4
G84: 5 | H84: 4 | I84: =G84*H84 -> 20
G85: =SUM(G79:G84) -> 67 | I85: =SUM(I79:I84) -> 282.3 | K85: =I85/G85 -> 4.2134328
G88: =G85/0.15 -> 446.66667
G92: =19 -> 19 | H92: Mn
G93: =G92/4 -> 4.75 | H93: Mn
G95: =31/432 -> 0.071759259

Sheet Factory cost targets @15% tarif
F2: $7 per CFT | M2: 15% of net + 3% return admin on returned items | Q2: 25% of Gross sales | R2: 5% of Gross sales | W2: Net COGS in dollars calculated on gross sale units as returns will not be resold
D3: 0.1 | F3: 7 | J3: 0.15 | M3: 0.15 | Q3: 0.25 | R3: 0.055
B4: SKU | C4: KD/Non-KD | D4: Factory cost | E4: CFT | F4: SEND Shipping | G4: ASP | H4: Gross Units | I4: Gross Sales | J4: Return % | K4: Net Units | L4: Net Sales | M4: AZ Selling Fees | N4: FBA Fulfilment Fees | O4: AZ Fulfillment fees | P4: OM1 | Q4: Ads | R4: Other costs | S4: Profit Before COGS | T4: Unit COGS 0% Tariff | U4: Unit COGS 15% Tariff | V4: Unit COGS 50% Tariff | W4: Gross COGS 0% Tariff | X4: Gross COGS 15% Tariff | Y4: Gross COGS 50% Tariff | Z4: Net Margin 0% Tariff | AA4: Net Margin 15% Tariff | AB4: Net Margin 50% Tariff | AC4: % Net Margin 0% Tariff | AD4: % Net margin 15% Tariff | AE4: % Net margin 50% Tariff | AF4: % returns | AG4: Gross sales (4 months) | AH4: Gross COGS % 0% Tariff | AI4: Gross COGS% 15% Tariff | AJ4: Gross COGS% 50% Tariff | AS4: Returns (4 months)
B5: RH-ET042MB(D)-FBA | C5: KD | D5: 19.64 | E5: =23*6*18/12/12/12 -> 1.4375 | F5: =E5*$F$3 -> 10.0625 | G5: 149.99 | H5: 26 | I5: =G5*H5 -> 3899.74 | J5: =$J$3 -> 0.15 | K5: =H5*(1-J5) -> 22.1 | L5: =K5*G5 -> 3314.779 | M5: =L5*$M$3+3%*(H5-K5)*G5 -> 514.76568 | N5: 16.45 | O5: =N5*(H5) -> 427.7 | P5: =L5-M5-O5 -> 2372.3133 | Q5: =I5*$Q$3 -> 974.935 | R5: =I5*$R$3 -> 214.4857 | S5: =P5-Q5-R5 -> 1182.8926 | T5: =F5+D5 -> 29.7025 | U5: =D5*(1.05)*(0.15)+D5+F5 -> 32.7958 | V5: =D5*(1.07)*(1.5)+F5 -> 41.5847 | W5: =$H5*T5 -> 772.265 | X5: =$H5*U5 -> 852.6908 | Y5: =$H5*V5 -> 1081.2022 | Z5: =$S5-W5 -> 410.62762 | AA5: =$S5-X5 -> 330.20182 | AB5: =$S5-Y5 -> 101.69042 | AC5: =Z5/$L5 -> 0.12387783 | AD5: =AA5/$I5 -> 0.084672778 | AE5: =AB5/$L5 -> 0.030677888 | AF5: =AS5/AG5 -> 0.057142857 | AG5: 35 | AH5: =W5/$L5 -> 0.23297632 | AI5: =X5/$L5 -> 0.25723911 | AJ5: =Y5/$L5 -> 0.32617625 | AS5: 2
B6: RH-ET042MW-FBA | C6: KD | D6: 19.64 | E6: =23*6*18/12/12/12 -> 1.4375 | F6: =E6*$F$3 -> 10.0625 | G6: 149.99 | H6: 26 | I6: =G6*H6 -> 3899.74 | J6: =$J$3 -> 0.15 | K6: =H6*(1-J6) -> 22.1 | L6: =K6*G6 -> 3314.779 | M6: =L6*$M$3+3%*(H6-K6)*G6 -> 514.76568 | N6: 16.45 | O6: =N6*(H6) -> 427.7 | P6: =L6-M6-O6 -> 2372.3133 | Q6: =I6*$Q$3 -> 974.935 | R6: =I6*$R$3 -> 214.4857 | S6: =P6-Q6-R6 -> 1182.8926 | T6: =F6+D6 -> 29.7025 | U6: =D6*(1.05)*(0.15)+D6+F6 -> 32.7958 | V6: =D6*(1.07)*(1.5)+F6 -> 41.5847 | W6: =$H6*T6 -> 772.265 | X6: =$H6*U6 -> 852.6908 | Y6: =$H6*V6 -> 1081.2022 | Z6: =$S6-W6 -> 410.62762 | AA6: =$S6-X6 -> 330.20182 | AB6: =$S6-Y6 -> 101.69042 | AC6: =Z6/$L6 -> 0.12387783 | AD6: =AA6/$I6 -> 0.084672778 | AE6: =AB6/$L6 -> 0.030677888 | AF6: =AS6/AG6 -> 0.081081081 | AG6: 37 | AH6: =W6/L6 -> 0.23297632 | AI6: =X6/$L6 -> 0.25723911 | AJ6: =Y6/$L6 -> 0.32617625 | AS6: 3
A7: 17.26 | B7: RH-DR002MTMW-FBA | C7: Non-KD | D7: =A7*(1-$D$3) -> 15.534 | E7: 3.2 | F7: =E7*$F$3 -> 22.4 | G7: 149.99 | H7: 21 | I7: =G7*H7 -> 3149.79 | J7: =$J$3 -> 0.15 | K7: =H7*(1-J7) -> 17.85 | L7: =K7*G7 -> 2677.3215 | M7: =L7*$M$3+3%*(H7-K7)*G7 -> 415.77228 | N7: 25.85 | O7: =N7*(H7) -> 542.85 | P7: =L7-M7-O7 -> 1718.6992 | Q7: =I7*$Q$3 -> 787.4475 | R7: =I7*$R$3 -> 173.23845 | S7: =P7-Q7-R7 -> 758.01327 | T7: =F7+D7 -> 37.934 | U7: =D7*(1.05)*(0.15)+D7+F7 -> 40.380605 | V7: =D7*(1.07)*(1.5)+F7 -> 47.33207 | W7: =$H7*T7 -> 796.614 | X7: =$H7*U7 -> 847.99271 | Y7: =$H7*V7 -> 993.97347 | Z7: =$S7-W7 -> -38.60073 | AA7: =$S7-X7 -> -89.979435 | AB7: =$S7-Y7 -> -235.9602 | AC7: =Z7/$L7 -> -0.014417667 | AD7: =AA7/$I7 -> -0.028566804 | AE7: =AB7/$L7 -> -0.088132934 | AF7: =AS7/AG7 -> 0.1369863 | AG7: 73 | AH7: =W7/L7 -> 0.2975414 | AI7: =X7/$L7 -> 0.31673174 | AJ7: =Y7/$L7 -> 0.37125667 | AS7: 10
A8: 14.88 | B8: RH-DR001MW-FBA | C8: Non-KD | D8: =A8*(1-$D$3) -> 13.392 | E8: 2.9 | F8: =E8*$F$3 -> 20.3 | G8: 139.99 | H8: 16 | I8: =G8*H8 -> 2239.84 | J8: =$J$3 -> 0.15 | K8: =H8*(1-J8) -> 13.6 | L8: =K8*G8 -> 1903.864 | M8: =L8*$M$3+3%*(H8-K8)*G8 -> 295.65888 | N8: 24.33 | O8: =N8*(H8) -> 389.28 | P8: =L8-M8-O8 -> 1218.9251 | Q8: =I8*$Q$3 -> 559.96 | R8: =I8*$R$3 -> 123.1912 | S8: =P8-Q8-R8 -> 535.77392 | T8: =F8+D8 -> 33.692 | U8: =D8*(1.05)*(0.15)+D8+F8 -> 35.80124 | V8: =D8*(1.07)*(1.5)+F8 -> 41.79416 | W8: =$H8*T8 -> 539.072 | X8: =$H8*U8 -> 572.81984 | Y8: =$H8*V8 -> 668.70656 | Z8: =$S8-W8 -> -3.29808 | AA8: =$S8-X8 -> -37.04592 | AB8: =$S8-Y8 -> -132.93264 | AC8: =Z8/$L8 -> -0.0017323086 | AD8: =AA8/$I8 -> -0.016539539 | AE8: =AB8/$L8 -> -0.06982255 | AF8: =AS8/AG8 -> 0.20512821 | AG8: 39 | AH8: =W8/L8 -> 0.28314628 | AI8: =X8/$L8 -> 0.30087225 | AJ8: =Y8/$L8 -> 0.35123652 | AS8: 8
A9: 51.79 | B9: RH-ET003-N-FBA | C9: KD | D9: =A9*(1-$D$3) -> 46.611 | E9: =17.5*19.5*14.5/12/12/12 -> 2.8634983 | F9: =E9*$F$3 -> 20.044488 | G9: 249 | H9: 10 | I9: =G9*H9 -> 2490 | J9: =$J$3 -> 0.15 | K9: =H9*(1-J9) -> 8.5 | L9: =K9*G9 -> 2116.5 | M9: =L9*$M$3+3%*(H9-K9)*G9 -> 328.68 | N9: 23.95 | O9: =N9*(H9) -> 239.5 | P9: =L9-M9-O9 -> 1548.32 | Q9: =I9*$Q$3 -> 622.5 | R9: =I9*$R$3 -> 136.95 | S9: =P9-Q9-R9 -> 788.87 | T9: =F9+D9 -> 66.655488 | U9: =D9*(1.05)*(0.15)+D9+F9 -> 73.99672 | V9: =D9*(1.07)*(1.5)+F9 -> 94.855143 | W9: =$H9*T9 -> 666.55488 | X9: =$H9*U9 -> 739.9672 | Y9: =$H9*V9 -> 948.55143 | Z9: =$S9-W9 -> 122.31512 | AA9: =$S9-X9 -> 48.902797 | AB9: =$S9-Y9 -> -159.68143 | AC9: =Z9/$L9 -> 0.057791222 | AD9: =AA9/$I9 -> 0.019639677 | AE9: =AB9/$L9 -> -0.075445986 | AF9: =AS9/AG9 -> 0.30769231 | AG9: 39 | AH9: =W9/L9 -> 0.31493261 | AI9: =X9/$L9 -> 0.34961833 | AJ9: =Y9/$L9 -> 0.44816982 | AS9: 12
B10: RH-DR005MW-FBA | C10: KD | D10: 14.88 | E10: =14.5*15*6/12/12/12 -> 0.75520833 | F10: =E10*$F$3 -> 5.2864583 | G10: 99.99 | H10: 18 | I10: =G10*H10 -> 1799.82 | J10: =$J$3 -> 0.15 | K10: =H10*(1-J10) -> 15.3 | L10: =K10*G10 -> 1529.847 | M10: =L10*$M$3+3%*(H10-K10)*G10 -> 237.57624 | N10: 11.71 | O10: =N10*(H10) -> 210.78 | P10: =L10-M10-O10 -> 1081.4908 | Q10: =I10*$Q$3 -> 449.955 | R10: =I10*$R$3 -> 98.9901 | S10: =P10-Q10-R10 -> 532.54566 | T10: =F10+D10 -> 20.166458 | U10: =D10*(1.05)*(0.15)+D10+F10 -> 22.510058 | V10: =D10*(1.07)*(1.5)+F10 -> 29.168858 | W10: =$H10*T10 -> 362.99625 | X10: =$H10*U10 -> 405.18105 | Y10: =$H10*V10 -> 525.03945 | Z10: =$S10-W10 -> 169.54941 | AA10: =$S10-X10 -> 127.36461 | AB10: =$S10-Y10 -> 7.50621 | AC10: =Z10/$L10 -> 0.11082769 | AD10: =AA10/$I10 -> 0.070765193 | AE10: =AB10/$L10 -> 0.0049065103 | AF10: =AS10/AG10 -> 0.10714286 | AG10: 56 | AH10: =W10/L10 -> 0.23727618 | AI10: =X10/$L10 -> 0.2648507 | AJ10: =Y10/$L10 -> 0.34319736 | AS10: 6
A11: 26.67 | B11: ET009 | C11: Non-KD | D11: =A11*(1-$D$3) -> 24.003 | E11: 1.6042 | F11: =E11*$F$3 -> 11.2294 | G11: 149.99 | H11: 26 | I11: =G11*H11 -> 3899.74 | J11: 0.15 | K11: =H11*(1-J11) -> 22.1 | L11: =K11*G11 -> 3314.779 | M11: =L11*$M$3+3%*(H11-K11)*G11 -> 514.76568 | N11: 18.33 | O11: =N11*(H11) -> 476.58 | P11: =L11-M11-O11 -> 2323.4333 | Q11: =I11*$Q$3 -> 974.935 | R11: =I11*$R$3 -> 214.4857 | S11: =P11-Q11-R11 -> 1134.0126 | T11: =F11+D11 -> 35.2324 | U11: =D11*(1.05)*(0.15)+D11+F11 -> 39.012873 | V11: =D11*(1.07)*(1.5)+F11 -> 49.754215 | W11: =$H11*T11 -> 916.0424 | X11: =$H11*U11 -> 1014.3347 | Y11: =$H11*V11 -> 1293.6096 | Z11: =$S11-W11 -> 217.97022 | AA11: =$S11-X11 -> 119.67794 | AB11: =$S11-Y11 -> -159.59697 | AC11: =Z11/$L11 -> 0.06575709 | AD11: =AA11/$I11 -> 0.030688696 | AE11: =AB11/$L11 -> -0.048147092 | AF11: =AS11/AG11 -> 0 | AG11: 56 | AH11: =W11/L11 -> 0.27635097 | AI11: =X11/$L11 -> 0.30600371 | AJ11: =Y11/$L11 -> 0.39025515
A12: 14.29 | B12: ET043MTMS | C12: KD | D12: =A12*(1-$D$3) -> 12.861 | E12: {=INDEX('Ex-Factory cost'!$D$3:$D$108,MATCH(B12,'Ex-Factory cost'!$B$3:$B$108,0))} -> 1.5 | F12: =E12*$F$3 -> 10.5 | G12: 71.99 | H12: 17 | I12: =G12*H12 -> 1223.83 | J12: =$J$3 -> 0.15 | K12: =H12*(1-J12) -> 14.45 | L12: =K12*G12 -> 1040.2555 | M12: =L12*$M$3+3%*(H12-K12)*G12 -> 161.54556 | N12: 18.25 | O12: =N12*(H12) -> 310.25 | P12: =L12-M12-O12 -> 568.45994 | Q12: =I12*$Q$3 -> 305.9575 | R12: =I12*$R$3 -> 67.31065 | S12: =P12-Q12-R12 -> 195.19179 | T12: =F12+D12 -> 23.361 | U12: =D12*(1.05)*(0.15)+D12+F12 -> 25.386608 | V12: =D12*(1.07)*(1.5)+F12 -> 31.141905 | W12: =$H12*T12 -> 397.137 | X12: =$H12*U12 -> 431.57233 | Y12: =$H12*V12 -> 529.41238 | Z12: =$S12-W12 -> -201.94521 | AA12: =$S12-X12 -> -236.38054 | AB12: =$S12-Y12 -> -334.2206 | AC12: =Z12/$L12 -> -0.19413039 | AD12: =AA12/$I12 -> -0.19314818 | AE12: =AB12/$L12 -> -0.32128703 | AF12: =AS12/AG12 -> 0 | AG12: 56 | AH12: =W12/L12 -> 0.38176871 | AI12: =X12/$L12 -> 0.41487147 | AJ12: =Y12/$L12 -> 0.50892534
A13: 13.69 | B13: DR003MWW(D) | C13: KD | D13: =A13*(1-$D$3) -> 12.321 | E13: {=INDEX('Ex-Factory cost'!$D$3:$D$108,MATCH(B13,'Ex-Factory cost'!$B$3:$B$108,0))} -> 0.7 | F13: =E13*$F$3 -> 4.9 | G13: 59.99 | H13: 13 | I13: =G13*H13 -> 779.87 | J13: =$J$3 -> 0.15 | K13: =H13*(1-J13) -> 11.05 | L13: =K13*G13 -> 662.8895 | M13: =L13*$M$3+3%*(H13-K13)*G13 -> 102.94284 | N13: 14.07 | O13: =N13*(H13) -> 182.91 | P13: =L13-M13-O13 -> 377.03666 | Q13: =I13*$Q$3 -> 194.9675 | R13: =I13*$R$3 -> 42.89285 | S13: =P13-Q13-R13 -> 139.17631 | T13: =F13+D13 -> 17.221 | U13: =D13*(1.05)*(0.15)+D13+F13 -> 19.161558 | V13: =D13*(1.07)*(1.5)+F13 -> 24.675205 | W13: =$H13*T13 -> 223.873 | X13: =$H13*U13 -> 249.10025 | Y13: =$H13*V13 -> 320.77767 | Z13: =$S13-W13 -> -84.69669 | AA13: =$S13-X13 -> -109.92394 | AB13: =$S13-Y13 -> -181.60136 | AC13: =Z13/$L13 -> -0.12776894 | AD13: =AA13/$I13 -> -0.14095162 | AE13: =AB13/$L13 -> -0.27395419 | AF13: =AS13/AG13 -> 0 | AG13: 56 | AH13: =W13/L13 -> 0.33772295 | AI13: =X13/$L13 -> 0.37577944 | AJ13: =Y13/$L13 -> 0.4839082
A14: 14.88 | B14: DR004MB | C14: KD | D14: =A14*(1-$D$3) -> 13.392 | E14: {=INDEX('Ex-Factory cost'!$D$3:$D$108,MATCH(B14,'Ex-Factory cost'!$B$3:$B$108,0))} -> 0.9 | F14: =E14*$F$3 -> 6.3 | G14: 66.99 | H14: 17 | I14: =G14*H14 -> 1138.83 | J14: =$J$3 -> 0.15 | K14: =H14*(1-J14) -> 14.45 | L14: =K14*G14 -> 968.0055 | M14: =L14*$M$3+3%*(H14-K14)*G14 -> 150.32556 | N14: 14.83 | O14: =N14*(H14) -> 252.11 | P14: =L14-M14-O14 -> 565.56994 | Q14: =I14*$Q$3 -> 284.7075 | R14: =I14*$R$3 -> 62.63565 | S14: =P14-Q14-R14 -> 218.22679 | T14: =F14+D14 -> 19.692 | U14: =D14*(1.05)*(0.15)+D14+F14 -> 21.80124 | V14: =D14*(1.07)*(1.5)+F14 -> 27.79416 | W14: =$H14*T14 -> 334.764 | X14: =$H14*U14 -> 370.62108 | Y14: =$H14*V14 -> 472.50072 | Z14: =$S14-W14 -> -116.53721 | AA14: =$S14-X14 -> -152.39429 | AB14: =$S14-Y14 -> -254.27393 | AC14: =Z14/$L14 -> -0.120389 | AD14: =AA14/$I14 -> -0.13381654 | AE14: =AB14/$L14 -> -0.26267819 | AF14: =AS14/AG14 -> 0 | AG14: 56 | AH14: =W14/L14 -> 0.34582861 | AI14: =X14/$L14 -> 0.38287084 | AJ14: =Y14/$L14 -> 0.48811781
A15: 51.79 | B15: ET003-W | C15: KD | D15: =A15*(1-$D$3) -> 46.611 | E15: {=INDEX('Ex-Factory cost'!$D$3:$D$108,MATCH(B15,'Ex-Factory cost'!$B$3:$B$108,0))} -> 2.9 | F15: =E15*$F$3 -> 20.3 | G15: 249.99 | H15: 10 | I15: =G15*H15 -> 2499.9 | J15: =$J$3 -> 0.15 | K15: =H15*(1-J15) -> 8.5 | L15: =K15*G15 -> 2124.915 | M15: =L15*$M$3+3%*(H15-K15)*G15 -> 329.9868 | N15: 21 | O15: =N15*(H15) -> 210 | P15: =L15-M15-O15 -> 1584.9282 | Q15: =I15*$Q$3 -> 624.975 | R15: =I15*$R$3 -> 137.4945 | S15: =P15-Q15-R15 -> 822.4587 | T15: =F15+D15 -> 66.911 | U15: =D15*(1.05)*(0.15)+D15+F15 -> 74.252233 | V15: =D15*(1.07)*(1.5)+F15 -> 95.110655 | W15: =$H15*T15 -> 669.11 | X15: =$H15*U15 -> 742.52233 | Y15: =$H15*V15 -> 951.10655 | Z15: =$S15-W15 -> 153.3487 | AA15: =$S15-X15 -> 79.936375 | AB15: =$S15-Y15 -> -128.64785 | AC15: =Z15/$L15 -> 0.072166981 | AD15: =AA15/$I15 -> 0.031975829 | AE15: =AB15/$L15 -> -0.060542586 | AF15: =AS15/AG15 -> 0 | AG15: 56 | AH15: =W15/L15 -> 0.31488789 | AI15: =X15/$L15 -> 0.34943625 | AJ15: =Y15/$L15 -> 0.44759746
A16: 29.76 | B16: ET008 | C16: Non-KD | D16: =A16*(1-$D$3) -> 26.784 | E16: 2.3 | F16: =E16*$F$3 -> 16.1 | G16: 199.99 | H16: 16 | I16: =G16*H16 -> 3199.84 | J16: =$J$3 -> 0.15 | K16: =H16*(1-J16) -> 13.6 | L16: =K16*G16 -> 2719.864 | M16: =L16*$M$3+3%*(H16-K16)*G16 -> 422.37888 | N16: =11%*G16 -> 21.9989 | O16: =N16*(H16) -> 351.9824 | P16: =L16-M16-O16 -> 1945.5027 | Q16: =I16*$Q$3 -> 799.96 | R16: =I16*$R$3 -> 175.9912 | S16: =P16-Q16-R16 -> 969.55152 | T16: =F16+D16 -> 42.884 | U16: =D16*(1.05)*(0.15)+D16+F16 -> 47.10248 | V16: =D16*(1.07)*(1.5)+F16 -> 59.08832 | W16: =$H16*T16 -> 686.144 | X16: =$H16*U16 -> 753.63968 | Y16: =$H16*V16 -> 945.41312 | Z16: =$S16-W16 -> 283.40752 | AA16: =$S16-X16 -> 215.91184 | AB16: =$S16-Y16 -> 24.1384 | AC16: =Z16/$L16 -> 0.10419915 | AD16: =AA16/$I16 -> 0.067475824 | AE16: =AB16/$L16 -> 0.0088748555 | AF16: =AS16/AG16 -> 0 | AG16: 56 | AH16: =W16/L16 -> 0.25227144 | AI16: =X16/$L16 -> 0.27708727 | AJ16: =Y16/$L16 -> 0.34759573
A17: 13.69 | B17: DR003MW | C17: KD | D17: =A17*(1-$D$3) -> 12.321 | E17: {=INDEX('Ex-Factory cost'!$D$3:$D$108,MATCH(B17,'Ex-Factory cost'!$B$3:$B$108,0))} -> 0.7 | F17: =E17*$F$3 -> 4.9 | G17: 59.99 | H17: 10 | I17: =G17*H17 -> 599.9 | J17: =$J$3 -> 0.15 | K17: =H17*(1-J17) -> 8.5 | L17: =K17*G17 -> 509.915 | M17: =L17*$M$3+3%*(H17-K17)*G17 -> 79.1868 | N17: 14.07 | O17: =N17*(H17) -> 140.7 | P17: =L17-M17-O17 -> 290.0282 | Q17: =I17*$Q$3 -> 149.975 | R17: =I17*$R$3 -> 32.9945 | S17: =P17-Q17-R17 -> 107.0587 | T17: =F17+D17 -> 17.221 | U17: =D17*(1.05)*(0.15)+D17+F17 -> 19.161558 | V17: =D17*(1.07)*(1.5)+F17 -> 24.675205 | W17: =$H17*T17 -> 172.21 | X17: =$H17*U17 -> 191.61558 | Y17: =$H17*V17 -> 246.75205 | Z17: =$S17-W17 -> -65.1513 | AA17: =$S17-X17 -> -84.556875 | AB17: =$S17-Y17 -> -139.69335 | AC17: =Z17/$L17 -> -0.12776894 | AD17: =AA17/$I17 -> -0.14095162 | AE17: =AB17/$L17 -> -0.27395419 | AF17: =AS17/AG17 -> 0 | AG17: 56 | AH17: =W17/L17 -> 0.33772295 | AI17: =X17/$L17 -> 0.37577944 | AJ17: =Y17/$L17 -> 0.4839082
A18: 82.14 | B18: CT001MW-18H | C18: KD | D18: =A18*(1-$D$3) -> 73.926 | E18: {=INDEX('Ex-Factory cost'!$D$3:$D$108,MATCH(B18,'Ex-Factory cost'!$B$3:$B$108,0))} -> 4.9 | F18: =E18*$F$3 -> 34.3 | G18: 369.99 | H18: 6 | I18: =G18*H18 -> 2219.94 | J18: =$J$3 -> 0.15 | K18: =H18*(1-J18) -> 5.1 | L18: =K18*G18 -> 1886.949 | M18: =L18*$M$3+3%*(H18-K18)*G18 -> 293.03208 | N18: =12%*G18 -> 44.3988 | O18: =N18*(H18) -> 266.3928 | P18: =L18-M18-O18 -> 1327.5241 | Q18: =I18*$Q$3 -> 554.985 | R18: =I18*$R$3 -> 122.0967 | S18: =P18-Q18-R18 -> 650.44242 | T18: =F18+D18 -> 108.226 | U18: =D18*(1.05)*(0.15)+D18+F18 -> 119.86934 | V18: =D18*(1.07)*(1.5)+F18 -> 152.95123 | W18: =$H18*T18 -> 649.356 | X18: =$H18*U18 -> 719.21607 | Y18: =$H18*V18 -> 917.70738 | Z18: =$S18-W18 -> 1.08642 | AA18: =$S18-X18 -> -68.77365 | AB18: =$S18-Y18 -> -267.26496 | AC18: =Z18/$L18 -> 0.00057575483 | AD18: =AA18/$I18 -> -0.030979959 | AE18: =AB18/$L18 -> -0.14163868 | AF18: =AS18/AG18 -> 0 | AG18: 56 | AH18: =W18/L18 -> 0.34413013 | AI18: =X18/$L18 -> 0.38115289 | AJ18: =Y18/$L18 -> 0.48634456
A19: 73.81 | B19: CT001 | C19: KD | D19: =A19*(1-$D$3) -> 66.429 | E19: {=INDEX('Ex-Factory cost'!$D$3:$D$108,MATCH(B19,'Ex-Factory cost'!$B$3:$B$108,0))} -> 4.5 | F19: =E19*$F$3 -> 31.5 | G19: 369 | H19: 7 | I19: =G19*H19 -> 2583 | J19: =$J$3 -> 0.15 | K19: =H19*(1-J19) -> 5.95 | L19: =K19*G19 -> 2195.55 | M19: =L19*$M$3+3%*(H19-K19)*G19 -> 340.956 | N19: =12%*G19 -> 44.28 | O19: =N19*(H19) -> 309.96 | P19: =L19-M19-O19 -> 1544.634 | Q19: =I19*$Q$3 -> 645.75 | R19: =I19*$R$3 -> 142.065 | S19: =P19-Q19-R19 -> 756.819 | T19: =F19+D19 -> 97.929 | U19: =D19*(1.05)*(0.15)+D19+F19 -> 108.39157 | V19: =D19*(1.07)*(1.5)+F19 -> 138.11855 | W19: =$H19*T19 -> 685.503 | X19: =$H19*U19 -> 758.74097 | Y19: =$H19*V19 -> 966.82982 | Z19: =$S19-W19 -> 71.316 | AA19: =$S19-X19 -> -1.9219725 | AB19: =$S19-Y19 -> -210.01082 | AC19: =Z19/$L19 -> 0.032482066 | AD19: =AA19/$I19 -> -0.00074408537 | AE19: =AB19/$L19 -> -0.095652941 | AF19: =AS19/AG19 -> 0 | AG19: 56 | AH19: =W19/L19 -> 0.31222382 | AI19: =X19/$L19 -> 0.34558128 | AJ19: =Y19/$L19 -> 0.44035882
A20: 88.1 | B20: CT009 | C20: Non-KD | D20: =A20*(1-$D$3) -> 79.29 | E20: {=INDEX('Ex-Factory cost'!$D$3:$D$108,MATCH(B20,'Ex-Factory cost'!$B$3:$B$108,0))} -> 12.4 | F20: =E20*$F$3 -> 86.8 | G20: 571.99 | H20: 8 | I20: =G20*H20 -> 4575.92 | J20: =$J$3 -> 0.15 | K20: =H20*(1-J20) -> 6.8 | L20: =K20*G20 -> 3889.532 | M20: =L20*$M$3+3%*(H20-K20)*G20 -> 604.02144 | N20: 203 | O20: =N20*(H20) -> 1624 | P20: =L20-M20-O20 -> 1661.5106 | Q20: =I20*$Q$3 -> 1143.98 | R20: =I20*$R$3 -> 251.6756 | S20: =P20-Q20-R20 -> 265.85496 | T20: =F20+D20 -> 166.09 | U20: =D20*(1.05)*(0.15)+D20+F20 -> 178.57817 | V20: =D20*(1.07)*(1.5)+F20 -> 214.06045 | W20: =$H20*T20 -> 1328.72 | X20: =$H20*U20 -> 1428.6254 | Y20: =$H20*V20 -> 1712.4836 | Z20: =$S20-W20 -> -1062.865 | AA20: =$S20-X20 -> -1162.7704 | AB20: =$S20-Y20 -> -1446.6286 | AC20: =Z20/$L20 -> -0.27326296 | AD20: =AA20/$I20 -> -0.25410637 | AE20: =AB20/$L20 -> -0.37192872 | AF20: =AS20/AG20 -> 0 | AG20: 56 | AH20: =W20/L20 -> 0.34161436 | AI20: =X20/$L20 -> 0.36730008 | AJ20: =Y20/$L20 -> 0.44028012
A21: 46.27 | B21: ET004 | C21: Non-KD | D21: =A21*(1-$D$3) -> 41.643 | E21: {=INDEX('Ex-Factory cost'!$D$3:$D$108,MATCH(B21,'Ex-Factory cost'!$B$3:$B$108,0))} -> 4.8 | F21: =E21*$F$3 -> 33.6 | G21: 249 | H21: 10 | I21: =G21*H21 -> 2490 | J21: =$J$3 -> 0.15 | K21: =H21*(1-J21) -> 8.5 | L21: =K21*G21 -> 2116.5 | M21: =L21*$M$3+3%*(H21-K21)*G21 -> 328.68 | N21: =17%*G21 -> 42.33 | O21: =N21*(H21) -> 423.3 | P21: =L21-M21-O21 -> 1364.52 | Q21: =I21*$Q$3 -> 622.5 | R21: =I21*$R$3 -> 136.95 | S21: =P21-Q21-R21 -> 605.07 | T21: =F21+D21 -> 75.243 | U21: =D21*(1.05)*(0.15)+D21+F21 -> 81.801772 | V21: =D21*(1.07)*(1.5)+F21 -> 100.43702 | W21: =$H21*T21 -> 752.43 | X21: =$H21*U21 -> 818.01773 | Y21: =$H21*V21 -> 1004.3701 | Z21: =$S21-W21 -> -147.36 | AA21: =$S21-X21 -> -212.94772 | AB21: =$S21-Y21 -> -399.30015 | AC21: =Z21/$L21 -> -0.06962438 | AD21: =AA21/$I21 -> -0.085521175 | AE21: =AB21/$L21 -> -0.1886606 | AF21: =AS21/AG21 -> 0 | AG21: 56 | AH21: =W21/L21 -> 0.35550673 | AI21: =X21/$L21 -> 0.3864955 | AJ21: =Y21/$L21 -> 0.47454295
A22: 57.14 | B22: ET005 | C22: Non-KD | D22: =A22*(1-$D$3) -> 51.426 | E22: {=INDEX('Ex-Factory cost'!$D$3:$D$108,MATCH(B22,'Ex-Factory cost'!$B$3:$B$108,0))} -> 5.7 | F22: =E22*$F$3 -> 39.9 | G22: 248 | H22: 7 | I22: =G22*H22 -> 1736 | J22: =$J$3 -> 0.15 | K22: =H22*(1-J22) -> 5.95 | L22: =K22*G22 -> 1475.6 | M22: =L22*$M$3+3%*(H22-K22)*G22 -> 229.152 | N22: =17%*G22 -> 42.16 | O22: =N22*(H22) -> 295.12 | P22: =L22-M22-O22 -> 951.328 | Q22: =I22*$Q$3 -> 434 | R22: =I22*$R$3 -> 95.48 | S22: =P22-Q22-R22 -> 421.848 | T22: =F22+D22 -> 91.326 | U22: =D22*(1.05)*(0.15)+D22+F22 -> 99.425595 | V22: =D22*(1.07)*(1.5)+F22 -> 122.43873 | W22: =$H22*T22 -> 639.282 | X22: =$H22*U22 -> 695.97916 | Y22: =$H22*V22 -> 857.07111 | Z22: =$S22-W22 -> -217.434 | AA22: =$S22-X22 -> -274.13117 | AB22: =$S22-Y22 -> -435.22311 | AC22: =Z22/$L22 -> -0.14735294 | AD22: =AA22/$I22 -> -0.15790966 | AE22: =AB22/$L22 -> -0.29494654 | AF22: =AS22/AG22 -> 0 | AG22: 56 | AH22: =W22/L22 -> 0.43323529 | AI22: =X22/$L22 -> 0.47165842 | AJ22: =Y22/$L22 -> 0.58082889
A23: 47.62 | B23: ET013 | C23: Non-KD | D23: =A23*(1-$D$3) -> 42.858 | E23: {=INDEX('Ex-Factory cost'!$D$3:$D$108,MATCH(B23,'Ex-Factory cost'!$B$3:$B$108,0))} -> 6.4 | F23: =E23*$F$3 -> 44.8 | G23: 189 | H23: 14 | I23: =G23*H23 -> 2646 | J23: =$J$3 -> 0.15 | K23: =H23*(1-J23) -> 11.9 | L23: =K23*G23 -> 2249.1 | M23: =L23*$M$3+3%*(H23-K23)*G23 -> 349.272 | N23: =17%*G23 -> 32.13 | O23: =N23*(H23) -> 449.82 | P23: =L23-M23-O23 -> 1450.008 | Q23: =I23*$Q$3 -> 661.5 | R23: =I23*$R$3 -> 145.53 | S23: =P23-Q23-R23 -> 642.978 | T23: =F23+D23 -> 87.658 | U23: =D23*(1.05)*(0.15)+D23+F23 -> 94.408135 | V23: =D23*(1.07)*(1.5)+F23 -> 113.58709 | W23: =$H23*T23 -> 1227.212 | X23: =$H23*U23 -> 1321.7139 | Y23: =$H23*V23 -> 1590.2193 | Z23: =$S23-W23 -> -584.234 | AA23: =$S23-X23 -> -678.73589 | AB23: =$S23-Y23 -> -947.24126 | AC23: =Z23/$L23 -> -0.25976346 | AD23: =AA23/$I23 -> -0.25651394 | AE23: =AB23/$L23 -> -0.42116458 | AF23: =AS23/AG23 -> 0 | AG23: 56 | AH23: =W23/L23 -> 0.54564581 | AI23: =X23/$L23 -> 0.58766346 | AJ23: =Y23/$L23 -> 0.70704693
A24: 26.19 | B24: ET012 | C24: KD | D24: =A24*(1-$D$3) -> 23.571 | E24: {=INDEX('Ex-Factory cost'!$D$3:$D$108,MATCH(B24,'Ex-Factory cost'!$B$3:$B$108,0))} -> 3.2 | F24: =E24*$F$3 -> 22.4 | G24: 177 | H24: 10 | I24: =G24*H24 -> 1770 | J24: =$J$3 -> 0.15 | K24: =H24*(1-J24) -> 8.5 | L24: =K24*G24 -> 1504.5 | M24: =L24*$M$3+3%*(H24-K24)*G24 -> 233.64 | N24: =11%*G24 -> 19.47 | O24: =N24*(H24) -> 194.7 | P24: =L24-M24-O24 -> 1076.16 | Q24: =I24*$Q$3 -> 442.5 | R24: =I24*$R$3 -> 97.35 | S24: =P24-Q24-R24 -> 536.31 | T24: =F24+D24 -> 45.971 | U24: =D24*(1.05)*(0.15)+D24+F24 -> 49.683433 | V24: =D24*(1.07)*(1.5)+F24 -> 60.231455 | W24: =$H24*T24 -> 459.71 | X24: =$H24*U24 -> 496.83432 | Y24: =$H24*V24 -> 602.31455 | Z24: =$S24-W24 -> 76.6 | AA24: =$S24-X24 -> 39.475675 | AB24: =$S24-Y24 -> -66.00455 | AC24: =Z24/$L24 -> 0.050913925 | AD24: =AA24/$I24 -> 0.022302641 | AE24: =AB24/$L24 -> -0.043871419 | AF24: =AS24/AG24 -> 0 | AG24: 56 | AH24: =W24/L24 -> 0.30555666 | AI24: =X24/$L24 -> 0.33023219 | AJ24: =Y24/$L24 -> 0.40034201
B25: ET041MW | C25: KD | D25: {=INDEX('Ex-Factory cost'!$C$3:$C$108,MATCH(B25,'Ex-Factory cost'!$B$3:$B$108,0))} -> 32.14 | E25: {=INDEX('Ex-Factory cost'!$D$3:$D$108,MATCH(B25,'Ex-Factory cost'!$B$3:$B$108,0))} -> 2.6 | F25: =E25*$F$3 -> 18.2 | G25: 190.99 | H25: 6 | I25: =G25*H25 -> 1145.94 | J25: =$J$3 -> 0.15 | K25: =H25*(1-J25) -> 5.1 | L25: =K25*G25 -> 974.049 | M25: =L25*$M$3+3%*(H25-K25)*G25 -> 151.26408 | N25: 21.67 | O25: =N25*(H25) -> 130.02 | P25: =L25-M25-O25 -> 692.76492 | Q25: =I25*$Q$3 -> 286.485 | R25: =I25*$R$3 -> 63.0267 | S25: =P25-Q25-R25 -> 343.25322 | T25: =F25+D25 -> 50.34 | U25: =D25*(1.05)*(0.15)+D25+F25 -> 55.40205 | V25: =D25*(1.07)*(1.5)+F25 -> 69.7847 | W25: =$H25*T25 -> 302.04 | X25: =$H25*U25 -> 332.4123 | Y25: =$H25*V25 -> 418.7082 | Z25: =$S25-W25 -> 41.21322 | AA25: =$S25-X25 -> 10.84092 | AB25: =$S25-Y25 -> -75.45498 | AC25: =Z25/$L25 -> 0.042311239 | AD25: =AA25/$I25 -> 0.0094602859 | AE25: =AB25/$L25 -> -0.077465282 | AF25: =AS25/AG25 -> 0 | AG25: 56 | AH25: =W25/L25 -> 0.31008707 | AI25: =X25/$L25 -> 0.34126856 | AJ25: =Y25/$L25 -> 0.42986359
B26: Aggregate | I26: =SUM(I3:I25) -> 49987.64 | L26: =SUM(L3:L25) -> 42489.494 | M26: =SUM(M3:M25) -> 6598.5185 | N26: =SUM(N3:N25) -> 690.7277 | O26: =SUM(O3:O25) -> 7855.6552 | P26: =SUM(P3:P25) -> 28035.47 | Q26: =SUM(Q3:Q25) -> 12497.16 | R26: =SUM(R3:R25) -> 2749.3752 | S26: =SUM(S3:S25) -> 12789.24 | W26: =sum(W5:W10) -> 3909.7671 | X26: =sum(X5:X10) -> 4271.3424 | Y26: =sum(Y5:Y10) -> 5298.6753 | Z26: =SUM(Z3:Z25) -> -564.06041 | AA26: =SUM(AA3:AA25) -> -1807.048 | AB26: =SUM(AB3:AB25) -> -5338.7113 | AC26: =Z26/$L26 -> -0.013275291 | AD26: =AA26/$I26 -> -0.036149897 | AE26: =AB26/$L26 -> -0.1256478 | AF26: =AS26/AG26 -> 0.14695341 | AG26: =SUM(AG5:AG10) -> 279 | AH26: =W26/L26 -> 0.092017267 | AI26: =X26/$L26 -> 0.10052702 | AJ26: =Y26/$L26 -> 0.12470554 | AS26: =SUM(AS5:AS10) -> 41
S28: Discount on manufacturing cost | T28: 0.1
B30: SKU | H30: =214/26 -> 8.2307692 | T30: COGS 0% Tariff | U30: COGS 15% Tariff | V30: COGS 50% Tariff | W30: Gross COGS 0% Tariff | X30: Gross COGS 25% Tariff | Y30: Gross COGS 50% Tariff | Z30: Net Margin 0% Tariff | AA30: Net Margin 25% Tariff | AB30: Net Margin 50% Tariff | AC30: % Net Margin 0% Tariff | AD30: % Net margin 25% Tariff | AE30: % Net margin 50% Tariff
B31: RH-ET042MB(D)-FBA | T31: =F5+D5*(1-$T$28) -> 27.7385 | U31: =D5*(1.02)*(1.25)*(1-$T$28)+F5 -> 32.5994 | V31: =D5*(1.02)*(1.5)*(1-$T$28)+F5 -> 37.10678 | W31: =$H5*T31 -> 721.201 | X31: =$H5*U31 -> 847.5844 | Y31: =$H5*V31 -> 964.77628 | Z31: =$S5-W31 -> 461.69162 | AA31: =$S5-X31 -> 335.30822 | AB31: =$S5-Y31 -> 218.11634 | AC31: =Z31/$L5 -> 0.13928278 | AD31: =AA31/$L5 -> 0.10115553 | AE31: =AB31/$L5 -> 0.065801171
B32: RH-ET042MW-FBA | T32: =F6+D6*(1-$T$28) -> 27.7385 | U32: =D6*(1.02)*(1.25)*(1-$T$28)+F6 -> 32.5994 | V32: =D6*(1.02)*(1.5)*(1-$T$28)+F6 -> 37.10678 | W32: =$H6*T32 -> 721.201 | X32: =$H6*U32 -> 847.5844 | Y32: =$H6*V32 -> 964.77628 | Z32: =$S6-W32 -> 461.69162 | AA32: =$S6-X32 -> 335.30822 | AB32: =$S6-Y32 -> 218.11634 | AC32: =Z32/$L6 -> 0.13928278 | AD32: =AA32/$L6 -> 0.10115553 | AE32: =AB32/$L6 -> 0.065801171
B33: RH-DR002MTMW-FBA | L33: ET009 | M33: - if KD and factory cost reduced by 10%, then CM3 is 5%+ at 15% tariff | T33: =F7+D7*(1-$T$28) -> 36.3806 | U33: =D7*(1.02)*(1.25)*(1-$T$28)+F7 -> 40.225265 | V33: =D7*(1.02)*(1.5)*(1-$T$28)+F7 -> 43.790318 | W33: =$H7*T33 -> 763.9926 | X33: =$H7*U33 -> 844.73056 | Y33: =$H7*V33 -> 919.59668 | Z33: =$S7-W33 -> -5.97933 | AA33: =$S7-X33 -> -86.717295 | AB33: =$S7-Y33 -> -161.58341 | AC33: =Z33/$L7 -> -0.0022333254 | AD33: =AA33/$L7 -> -0.032389571 | AE33: =AB33/$L7 -> -0.060352635
B34: RH-DR001MW-FBA | T34: =F8+D8*(1-$T$28) -> 32.3528 | U34: =D8*(1.02)*(1.25)*(1-$T$28)+F8 -> 35.66732 | V34: =D8*(1.02)*(1.5)*(1-$T$28)+F8 -> 38.740784 | W34: =$H8*T34 -> 517.6448 | X34: =$H8*U34 -> 570.67712 | Y34: =$H8*V34 -> 619.85254 | Z34: =$S8-W34 -> 18.12912 | AA34: =$S8-X34 -> -34.9032 | AB34: =$S8-Y34 -> -84.078624 | AC34: =Z34/$L8 -> 0.0095222768 | AD34: =AA34/$L8 -> -0.018332822 | AE34: =AB34/$L8 -> -0.044162096
B35: RH-ET003-N-FBA | T35: =F9+D9*(1-$T$28) -> 61.994388 | U35: =D9*(1.02)*(1.25)*(1-$T$28)+F9 -> 73.53061 | V35: =D9*(1.02)*(1.5)*(1-$T$28)+F9 -> 84.227835 | W35: =$H9*T35 -> 619.94388 | X35: =$H9*U35 -> 735.3061 | Y35: =$H9*V35 -> 842.27835 | Z35: =$S9-W35 -> 168.92612 | AA35: =$S9-X35 -> 53.563897 | AB35: =$S9-Y35 -> -53.408348 | AC35: =Z35/$L9 -> 0.079813901 | AD35: =AA35/$L9 -> 0.025307771 | AE35: =AB35/$L9 -> -0.025234278
B36: RH-DR005MW-FBA | T36: =F10+D10*(1-$T$28) -> 18.678458 | U36: =D10*(1.02)*(1.25)*(1-$T$28)+F10 -> 22.361258 | V36: =D10*(1.02)*(1.5)*(1-$T$28)+F10 -> 25.776218 | W36: =$H10*T36 -> 336.21225 | X36: =$H10*U36 -> 402.50265 | Y36: =$H10*V36 -> 463.97193 | Z36: =$S10-W36 -> 196.33341 | AA36: =$S10-X36 -> 130.04301 | AB36: =$S10-Y36 -> 68.57373 | AC36: =Z36/$L10 -> 0.12833532 | AD36: =AA36/$L10 -> 0.085003932 | AE36: =AB36/$L10 -> 0.044823914
B37: Aggregate | W37: =sum(W31:W36) -> 3680.1955 | X37: =sum(X31:X36) -> 4248.3852 | Y37: =sum(Y31:Y36) -> 4775.2521 | Z37: =sum(Z31:Z36) -> 1300.7926 | AA37: =sum(AA31:AA36) -> 732.60285 | AB37: =sum(AB31:AB36) -> 205.73603 | AC37: =Z37/$L26 -> 0.030614452 | AD37: =AA37/$L26 -> 0.017241976 | AE37: =AB37/$L26 -> 0.0048420447
H39: 30 | I39: 79.99 | J39: =H39*I39 -> 2399.7 | T39: Line of action
H40: 2 | I40: 699.99 | J40: =H40*I40 -> 1399.98
H41: 4 | I41: 169.99 | J41: =H41*I41 -> 679.96 | T41: Jodhpur visit
H42: 32 | I42: 189.99 | J42: =H42*I42 -> 6079.68 | O42: 39.01 | T42: - Jugaad billing to bypass tariffs
H43: 22 | I43: 419.99 | J43: =H43*I43 -> 9239.78 | O43: 18.33 | T43: - Non-KD to KD
H44: 24 | I44: 379.99 | J44: =H44*I44 -> 9119.76 | O44: 8.23 | T44: - KD mein 10% Factory price reduction
H45: 34 | I45: 309.99 | J45: =H45*I45 -> 10539.66 | O45: =sum(O42:O44) -> 65.57 | T45: - Inventory sponshirship from Supplier - atleast 1 supplier
H46: 26 | I46: 249.99 | J46: =H46*I46 -> 6499.74
H47: 2 | I47: =249.99+199.99 -> 449.98 | J47: =H47*I47 -> 899.96 | T47: Full potential
H48: 2 | I48: =199.99+229.99 -> 429.98 | J48: =H48*I48 -> 859.96 | T48: - How much can these scale on Amazon
H49: 17 | I49: 279.99 | J49: =H49*I49 -> 4759.83 | T49: - Figure out how big this business can become
H50: 4 | I50: 649.99 | J50: =H50*I50 -> 2599.96 | T50: - Figure out how fast can this business grow
H51: 2 | I51: 449.99 | J51: =H51*I51 -> 899.98 | T51: - This business definition - Selling small KD furniture pieces on amazon which are priced atleast 20-30% higher than median price
H52: 29 | I52: 279.99 | J52: =H52*I52 -> 8119.71 | T52: - Consumer Survey to assess the demand for this business
H53: 7 | I53: 154.99 | J53: =H53*I53 -> 1084.93 | T53: - D2C - How big, How fast, GTM, Unit economics. What learnings can you derive from amazon for this? This question is more for future else there is a risk of getting restricted to becoming AZ seller
H54: 33 | I54: 139.99 | J54: =H54*I54 -> 4619.67
H55: 12 | I55: 139.99 | J55: =H55*I55 -> 1679.88 | T55: India Furniture market - Mayank conversation
H56: 19 | I56: 149.99 | J56: =H56*I56 -> 2849.81 | T56: - Define the business & market questions you want to talk about
H57: 28 | I57: 94.99 | J57: =H57*I57 -> 2659.72 | T57: - Understand his position - What does he wants to do?
H58: 33 | I58: 259.99 | J58: =H58*I58 -> 8579.67
H59: 44 | I59: 199.99 | J59: =H59*I59 -> 8799.56 | T59: New cross-border consumer angles
J60: =sum(J39:J59) -> 94370.9 | T60: - Creating a Temu/Shein from India for products where there is a disproportionate production & supply chain advantage
T62: India focussed business - New Ideas
G64: current amazon sale
G65: Factory cost targets where unit economics becomes viable
G66: Revising price for these SKUs and then letting them sell
G67: How to make a decision on new products - New SKUs in Furniture or Newer categories - This with a long term vision
K78: =12000*85 -> 1020000

Sheet Ex-Factory cost
E1: 84
B2: SKU | C2: Ex-factory Cost | D2: CFT | E2: Ex-factory Cost (INR)
B3: CT001 | C3: 73.81 | D3: 4.5 | E3: =C3*$E$1 -> 6200.04
B4: CT001MW-18H | C4: 82.14 | D4: 4.9 | E4: =C4*$E$1 -> 6899.76
B5: CT001Nest-MN14-MW18 | C5: 155.95 | D5: 9.5 | E5: =C5*$E$1 -> 13099.8
B6: CT002 | C6: 66.67 | D6: 7.5 | E6: =C6*$E$1 -> 5600.28
B7: CT002SH-18H | C7: 69.05 | D7: 9.6 | E7: =C7*$E$1 -> 5800.2
B8: CT004 | C8: 202.38 | D8: 19.9 | E8: =C8*$E$1 -> 16999.92
B9: CT005 | C9: 101.19 | D9: 20.1 | E9: =C9*$E$1 -> 8499.96
B10: CT006 | C10: 77.38 | D10: 9.4 | E10: =C10*$E$1 -> 6499.92
B11: CT006MW-18H | C11: 97.62 | D11: 11.7 | E11: =C11*$E$1 -> 8200.08
B12: CT007 | C12: 94.05 | D12: 4.7 | E12: =C12*$E$1 -> 7900.2
B13: CT008SH-14H | C13: 26.79 | D13: 6.3 | E13: =C13*$E$1 -> 2250.36
B14: CT008SH-18H | C14: 35.71 | D14: 7.4 | E14: =C14*$E$1 -> 2999.64
... B35: ET003-N | C35: 51.79 | D35: 2 | E35: =C35*$E$1 -> 4350.36
B36: ET003-N | E36: =C36*$E$1 -> 0
B37: ET003-N (Set of 2) | C37: 103.57 | D37: 4.6 | E37: =C37*$E$1 -> 8699.88
B38: ET003-NW | C38: 51.79 | D38: 2 | E38: =C38*$E$1 -> 4350.36
B39: ET003-W | C39: 51.79 | D39: 2.9 | E39: =C39*$E$1 -> 4350.36
B40: ET004 | C40: 46.27 | D40: 4.8 | E40: =C40*$E$1 -> 3886.68
B41: ET005 | C41: 57.14 | D41: 5.7 | E41: =C41*$E$1 -> 4799.76
B42: ET005MR | C42: 50 | D42: 5.5 | E42: =C42*$E$1 -> 4200
B43: ET006 | C43: 60.71 | D43: 5 | E43: =C43*$E$1 -> 5099.64
B44: ET007 | C44: 71.25 | D44: 3.2 | E44: =C44*$E$1 -> 5985
B45: ET008 | C45: 29.76 | D45: 4.6 | E45: =C45*$E$1 -> 2499.84
B46: ET009 | C46: 26.67 | D46: 2.9 | E46: =C46*$E$1 -> 2240.28
B47: ET010 | C47: 35.42 | D47: 4.5 | E47: =C47*$E$1 -> 2975.28
B48: ET011 | C48: 57.19 | D48: 5.6 | E48: =C48*$E$1 -> 4803.96
... B102: DR004MB | C102: 14.88 | D102: 0.9 | E102: =C102*$E$1 -> 1249.92
B103: DR005MW | C103: 14.88 | D103: 0.8 | E103: =C103*$E$1 -> 1249.92 | G103: =C103*84 -> 1249.92
B104: SB011 | C104: 101.19 | D104: 13.4 | E104: =C104*$E$1 -> 8499.96
B105: SB012 | C105: 101.19 | D105: 13.4 | E105: =C105*$E$1 -> 8499.96
B106: SB013 | C106: 101.19 | D106: 13.4 | E106: =C106*$E$1 -> 8499.96
B107: SB014 | C107: 107.14 | D107: 13.4 | E107: =C107*$E$1 -> 8999.76
B108: SB015 | C108: 113.1 | D108: 16.2 | E108: =C108*$E$1 -> 9500.4
D110: =2200/14 -> 157.14286

Sheet New Products Pricing 
G2: $7 per CFT | N2: 15% of net + 3% return admin on returned items | R2: 25% of Gross sales | S2: 5% of Gross sales | X2: Net COGS in dollars calculated on gross sale units as returns will not be resold
G3: 7 | K3: 0.15 | N3: 0.15 | R3: 0.25 | S3: 0.055
B4: SKU | C4: KD/Non-KD | E4: Factory price | F4: CFT | G4: SEND Shipping | H4: ASP | I4: Gross Units | J4: Gross Sales | K4: Return % | L4: Net Units | M4: Net Sales | N4: AZ Selling Fees | O4: FBA Fulfilment Fees | P4: AZ Fulfillment fees | Q4: OM1 | R4: Ads | S4: Other costs | T4: Profit Before COGS | U4: Unit COGS 0% Tariff | V4: Unit COGS 25% Tariff | W4: Unit COGS 50% Tariff | X4: COGS 0% Tariff | Y4: COGS 25% Tariff | Z4: COGS 50% Tariff | AA4: Net Margin 0% Tariff | AB4: Net Margin 25% Tariff | AC4: Net Margin 50% Tariff | AD4: % Net Margin 0% Tariff | AE4: % Net margin 25% Tariff | AF4: % Net margin 50% Tariff | AG4: % returns | AH4: Gross sales (4 months) | AI4: Returns (4 months)
B5: RH-ET042MB(D)-FBA | C5: KD | E5: 19.64 | F5: =23*6*18/12/12/12 -> 1.4375 | G5: =F5*$G$3 -> 10.0625 | H5: 139 | I5: 26 | J5: =H5*I5 -> 3614 | K5: =$K$3 -> 0.15 | L5: =rounddown(I5*(1-K5),0) -> 22 | M5: =L5*H5 -> 3058 | N5: =M5*$N$3+3%*(I5-L5)*H5 -> 475.38 | O5: 16.45 | P5: =O5*(I5) -> 427.7 | Q5: =M5-N5-P5 -> 2154.92 | R5: =J5*$R$3 -> 903.5 | S5: =J5*$S$3 -> 198.77 | T5: =Q5-R5-S5 -> 1052.65 | U5: =G5+E5 -> 29.7025 | V5: =E5*(1.02)*(1.25)+G5 -> 35.1035 | W5: =E5*(1.02)*(1.5)+G5 -> 40.1117 | X5: =$I5*U5 -> 772.265 | Y5: =$I5*V5 -> 912.691 | Z5: =$I5*W5 -> 1042.9042 | AA5: =$T5-X5 -> 280.385 | AB5: =$T5-Y5 -> 139.959 | AC5: =$T5-Z5 -> 9.7458 | AD5: =AA5/$M5 -> 0.091689012 | AE5: =AB5/$M5 -> 0.045768149 | AF5: =AC5/$M5 -> 0.003186985 | AG5: =AI5/AH5 -> 0.057142857 | AH5: 35 | AI5: 2
B6: RH-ET042MW-FBA | C6: KD | E6: 19.64 | F6: =23*6*18/12/12/12 -> 1.4375 | G6: =F6*$G$3 -> 10.0625 | H6: 139 | I6: 26 | J6: =H6*I6 -> 3614 | K6: =$K$3 -> 0.15 | L6: =rounddown(I6*(1-K6),0) -> 22 | M6: =L6*H6 -> 3058 | N6: =M6*$N$3+3%*(I6-L6)*H6 -> 475.38 | O6: 16.45 | P6: =O6*(I6) -> 427.7 | Q6: =M6-N6-P6 -> 2154.92 | R6: =J6*$R$3 -> 903.5 | S6: =J6*$S$3 -> 198.77 | T6: =Q6-R6-S6 -> 1052.65 | U6: =G6+E6 -> 29.7025 | V6: =E6*(1.02)*(1.25)+G6 -> 35.1035 | W6: =E6*(1.02)*(1.5)+G6 -> 40.1117 | X6: =$I6*U6 -> 772.265 | Y6: =$I6*V6 -> 912.691 | Z6: =$I6*W6 -> 1042.9042 | AA6: =$T6-X6 -> 280.385 | AB6: =$T6-Y6 -> 139.959 | AC6: =$T6-Z6 -> 9.7458 | AD6: =AA6/$M6 -> 0.091689012 | AE6: =AB6/$M6 -> 0.045768149 | AF6: =AC6/$M6 -> 0.003186985 | AG6: =AI6/AH6 -> 0.081081081 | AH6: 37 | AI6: 3
B7: RH-DR002MTMW-FBA | C7: Non-KD | E7: 17.26 | F7: =14.5*14.5*26.5/12/12/12 -> 3.22432 | G7: =F7*$G$3 -> 22.57024 | H7: 154.99 | I7: 21 | J7: =H7*I7 -> 3254.79 | K7: =$K$3 -> 0.15 | L7: =rounddown(I7*(1-K7),0) -> 17 | M7: =L7*H7 -> 2634.83 | N7: =M7*$N$3+3%*(I7-L7)*H7 -> 413.8233 | O7: 25.95 | P7: =O7*(I7) -> 544.95 | Q7: =M7-N7-P7 -> 1676.0567 | R7: =J7*$R$3 -> 813.6975 | S7: =J7*$S$3 -> 179.01345 | T7: =Q7-R7-S7 -> 683.34575 | U7: =G7+E7 -> 39.83024 | V7: =E7*(1.02)*(1.25)+G7 -> 44.57674 | W7: =E7*(1.02)*(1.5)+G7 -> 48.97804 | X7: =$I7*U7 -> 836.43504 | Y7: =$I7*V7 -> 936.11154 | Z7: =$I7*W7 -> 1028.5388 | AA7: =$T7-X7 -> -153.08929 | AB7: =$T7-Y7 -> -252.76579 | AC7: =$T7-Z7 -> -345.19309 | AD7: =AA7/$M7 -> -0.058102152 | AE7: =AB7/$M7 -> -0.095932486 | AF7: =AC7/$M7 -> -0.13101152 | AG7: =AI7/AH7 -> 0.1369863 | AH7: 73 | AI7: 10
B8: RH-DR001MW-FBA | C8: Non-KD | E8: 14.88 | F8: =14*14*26/12/12/12 -> 2.9490741 | G8: =F8*$G$3 -> 20.643519 | H8: 139.99 | I8: 16 | J8: =H8*I8 -> 2239.84 | K8: =$K$3 -> 0.15 | L8: =rounddown(I8*(1-K8),0) -> 13 | M8: =L8*H8 -> 1819.87 | N8: =M8*$N$3+3%*(I8-L8)*H8 -> 285.5796 | O8: 24.43 | P8: =O8*(I8) -> 390.88 | Q8: =M8-N8-P8 -> 1143.4104 | R8: =J8*$R$3 -> 559.96 | S8: =J8*$S$3 -> 123.1912 | T8: =Q8-R8-S8 -> 460.2592 | U8: =G8+E8 -> 35.523519 | V8: =E8*(1.02)*(1.25)+G8 -> 39.615519 | W8: =E8*(1.02)*(1.5)+G8 -> 43.409919 | X8: =$I8*U8 -> 568.3763 | Y8: =$I8*V8 -> 633.8483 | Z8: =$I8*W8 -> 694.5587 | AA8: =$T8-X8 -> -108.1171 | AB8: =$T8-Y8 -> -173.5891 | AC8: =$T8-Z8 -> -234.2995 | AD8: =AA8/$M8 -> -0.059409241 | AE8: =AB8/$M8 -> -0.095385438 | AF8: =AC8/$M8 -> -0.12874518 | AG8: =AI8/AH8 -> 0.20512821 | AH8: 39 | AI8: 8
B9: RH-ET003-N-FBA | C9: KD | E9: 51.79 | F9: =17.5*19.5*14.5/12/12/12 -> 2.8634983 | G9: =F9*$G$3 -> 20.044488 | H9: 279 | I9: 10 | J9: =H9*I9 -> 2790 | K9: =$K$3 -> 0.15 | L9: =rounddown(I9*(1-K9),0) -> 8 | M9: =L9*H9 -> 2232 | N9: =M9*$N$3+3%*(I9-L9)*H9 -> 351.54 | O9: 21.39 | P9: =O9*(I9) -> 213.9 | Q9: =M9-N9-P9 -> 1666.56 | R9: =J9*$R$3 -> 697.5 | S9: =J9*$S$3 -> 153.45 | T9: =Q9-R9-S9 -> 815.61 | U9: =G9+E9 -> 71.834488 | V9: =E9*(1.02)*(1.25)+G9 -> 86.076738 | W9: =E9*(1.02)*(1.5)+G9 -> 99.283188 | X9: =$I9*U9 -> 718.34488 | Y9: =$I9*V9 -> 860.76738 | Z9: =$I9*W9 -> 992.83188 | AA9: =$T9-X9 -> 97.265122 | AB9: =$T9-Y9 -> -45.157378 | AC9: =$T9-Z9 -> -177.22188 | AD9: =AA9/$M9 -> 0.043577563 | AE9: =AB9/$M9 -> -0.0202318 | AF9: =AC9/$M9 -> -0.079400483 | AG9: =AI9/AH9 -> 0.30769231 | AH9: 39 | AI9: 12
B10: RH-DR005MW-FBA | C10: KD | E10: 14.88 | F10: =14.5*15*6/12/12/12 -> 0.75520833 | G10: =F10*$G$3 -> 5.2864583 | H10: 99.99 | I10: 18 | J10: =H10*I10 -> 1799.82 | K10: =$K$3 -> 0.15 | L10: =rounddown(I10*(1-K10),0) -> 15 | M10: =L10*H10 -> 1499.85 | N10: =M10*$N$3+3%*(I10-L10)*H10 -> 233.9766 | O10: 11.71 | P10: =O10*(I10) -> 210.78 | Q10: =M10-N10-P10 -> 1055.0934 | R10: =J10*$R$3 -> 449.955 | S10: =J10*$S$3 -> 98.9901 | T10: =Q10-R10-S10 -> 506.1483 | U10: =G10+E10 -> 20.166458 | V10: =E10*(1.02)*(1.25)+G10 -> 24.258458 | W10: =E10*(1.02)*(1.5)+G10 -> 28.052858 | X10: =$I10*U10 -> 362.99625 | Y10: =$I10*V10 -> 436.65225 | Z10: =$I10*W10 -> 504.95145 | AA10: =$T10-X10 -> 143.15205 | AB10: =$T10-Y10 -> 69.49605 | AC10: =$T10-Z10 -> 1.19685 | AD10: =AA10/$M10 -> 0.095444244 | AE10: =AB10/$M10 -> 0.046335334 | AF10: =AC10/$M10 -> 0.0007979798 | AG10: =AI10/AH10 -> 0.10714286 | AH10: 56 | AI10: 6
B11: ET003-N | C11: Non-KD | D11: 4350 | E11: =D11/84 -> 51.785714 | F11: 2.9 | G11: =F11*$G$3 -> 20.3 | H11: 279.99 | I11: 20 | J11: =H11*I11 -> 5599.8 | K11: =$K$3 -> 0.15 | L11: =rounddown(I11*(1-K11),0) -> 17 | M11: =L11*H11 -> 4759.83 | N11: =M11*$N$3+3%*(I11-L11)*H11 -> 739.1736 | O11: 21.29 | P11: =O11*(I11) -> 425.8 | Q11: =M11-N11-P11 -> 3594.8564 | R11: =J11*$R$3 -> 1399.95 | S11: =J11*$S$3 -> 307.989 | T11: =Q11-R11-S11 -> 1886.9174 | U11: =G11+E11 -> 72.085714 | V11: =E11*(1.02)*(1.25)+G11 -> 86.326786 | W11: =E11*(1.02)*(1.5)+G11 -> 99.532143 | X11: =$I11*U11 -> 1441.7143 | Y11: =$I11*V11 -> 1726.5357 | Z11: =$I11*W11 -> 1990.6429 | AA11: =$T11-X11 -> 445.20311 | AB11: =$T11-Y11 -> 160.38169 | AC11: =$T11-Z11 -> -103.72546 | AD11: =AA11/$M11 -> 0.093533407 | AE11: =AB11/$M11 -> 0.033694835 | AF11: =AC11/$M11 -> -0.021791841
B12: ET003-W | C12: Non-KD | D12: 4350 | E12: =D12/84 -> 51.785714 | F12: 2.9 | G12: =F12*$G$3 -> 20.3 | H12: 279.99 | I12: 20 | J12: =H12*I12 -> 5599.8 | K12: =$K$3 -> 0.15 | L12: =rounddown(I12*(1-K12),0) -> 17 | M12: =L12*H12 -> 4759.83 | N12: =M12*$N$3+3%*(I12-L12)*H12 -> 739.1736 | O12: 22.91 | P12: =O12*(I12) -> 458.2 | Q12: =M12-N12-P12 -> 3562.4564 | R12: =J12*$R$3 -> 1399.95 | S12: =J12*$S$3 -> 307.989 | T12: =Q12-R12-S12 -> 1854.5174 | U12: =G12+E12 -> 72.085714 | V12: =E12*(1.02)*(1.25)+G12 -> 86.326786 | W12: =E12*(1.02)*(1.5)+G12 -> 99.532143 | X12: =$I12*U12 -> 1441.7143 | Y12: =$I12*V12 -> 1726.5357 | Z12: =$I12*W12 -> 1990.6429 | AA12: =$T12-X12 -> 412.80311 | AB12: =$T12-Y12 -> 127.98169 | AC12: =$T12-Z12 -> -136.12546 | AD12: =AA12/$M12 -> 0.086726441 | AE12: =AB12/$M12 -> 0.026887869 | AF12: =AC12/$M12 -> -0.028598807
B13: ET004 | C13: Non-KD | D13: 3887 | E13: =D13/84 -> 46.27381 | F13: 4.01 | G13: =F13*$G$3 -> 28.07 | H13: 309.99 | I13: 20 | J13: =H13*I13 -> 6199.8 | K13: =$K$3 -> 0.15 | L13: =rounddown(I13*(1-K13),0) -> 17 | M13: =L13*H13 -> 5269.83 | N13: =M13*$N$3+3%*(I13-L13)*H13 -> 818.3736 | O13: 28.23 | P13: =O13*(I13) -> 564.6 | Q13: =M13-N13-P13 -> 3886.8564 | R13: =J13*$R$3 -> 1549.95 | S13: =J13*$S$3 -> 340.989 | T13: =Q13-R13-S13 -> 1995.9174 | U13: =G13+E13 -> 74.34381 | V13: =E13*(1.02)*(1.25)+G13 -> 87.069107 | W13: =E13*(1.02)*(1.5)+G13 -> 98.868929 | X13: =$I13*U13 -> 1486.8762 | Y13: =$I13*V13 -> 1741.3821 | Z13: =$I13*W13 -> 1977.3786 | AA13: =$T13-X13 -> 509.04121 | AB13: =$T13-Y13 -> 254.53526 | AC13: =$T13-Z13 -> 18.538829 | AD13: =AA13/$M13 -> 0.096595376 | AE13: =AB13/$M13 -> 0.048300468 | AF13: =AC13/$M13 -> 0.0035179178
B14: ET005-MR | C14: Non-KD | D14: 4200 | E14: =D14/84 -> 50 | F14: 5.46 | G14: =F14*$G$3 -> 38.22 | H14: 419.99 | I14: 20 | J14: =H14*I14 -> 8399.8 | K14: =$K$3 -> 0.15 | L14: =rounddown(I14*(1-K14),0) -> 17 | M14: =L14*H14 -> 7139.83 | N14: =M14*$N$3+3%*(I14-L14)*H14 -> 1108.7736 | O14: 56.31 | P14: =O14*(I14) -> 1126.2 | Q14: =M14-N14-P14 -> 4904.8564 | R14: =J14*$R$3 -> 2099.95 | S14: =J14*$S$3 -> 461.989 | T14: =Q14-R14-S14 -> 2342.9174 | U14: =G14+E14 -> 88.22 | V14: =E14*(1.02)*(1.25)+G14 -> 101.97 | W14: =E14*(1.02)*(1.5)+G14 -> 114.72 | X14: =$I14*U14 -> 1764.4 | Y14: =$I14*V14 -> 2039.4 | Z14: =$I14*W14 -> 2294.4 | AA14: =$T14-X14 -> 578.5174 | AB14: =$T14-Y14 -> 303.5174 | AC14: =$T14-Z14 -> 48.5174 | AD14: =AA14/$M14 -> 0.081026775 | AE14: =AB14/$M14 -> 0.042510452 | AF14: =AC14/$M14 -> 0.0067953159
B15: ET008 | C15: Non-KD | D15: 2300 | E15: =D15/84 -> 27.380952 | F15: 4.59 | G15: =F15*$G$3 -> 32.13 | H15: 279.99 | I15: 20 | J15: =H15*I15 -> 5599.8 | K15: =$K$3 -> 0.15 | L15: =rounddown(I15*(1-K15),0) -> 17 | M15: =L15*H15 -> 4759.83 | N15: =M15*$N$3+3%*(I15-L15)*H15 -> 739.1736 | O15: 42.37 | P15: =O15*(I15) -> 847.4 | Q15: =M15-N15-P15 -> 3173.2564 | R15: =J15*$R$3 -> 1399.95 | S15: =J15*$S$3 -> 307.989 | T15: =Q15-R15-S15 -> 1465.3174 | U15: =G15+E15 -> 59.510952 | V15: =E15*(1.02)*(1.25)+G15 -> 67.040714 | W15: =E15*(1.02)*(1.5)+G15 -> 74.022857 | X15: =$I15*U15 -> 1190.219 | Y15: =$I15*V15 -> 1340.8143 | Z15: =$I15*W15 -> 1480.4571 | AA15: =$T15-X15 -> 275.09835 | AB15: =$T15-Y15 -> 124.50311 | AC15: =$T15-Z15 -> -15.139743 | AD15: =AA15/$M15 -> 0.057795836 | AE15: =AB15/$M15 -> 0.026157051 | AF15: =AC15/$M15 -> -0.0031807318
B16: ET009 | C16: Non-KD | D16: 2240 | E16: =D16/84 -> 26.666667 | F16: 2.85 | G16: =F16*$G$3 -> 19.95 | H16: 199.99 | I16: 20 | J16: =H16*I16 -> 3999.8 | K16: =$K$3 -> 0.15 | L16: =rounddown(I16*(1-K16),0) -> 17 | M16: =L16*H16 -> 3399.83 | N16: =M16*$N$3+3%*(I16-L16)*H16 -> 527.9736 | O16: 23.29 | P16: =O16*(I16) -> 465.8 | Q16: =M16-N16-P16 -> 2406.0564 | R16: =J16*$R$3 -> 999.95 | S16: =J16*$S$3 -> 219.989 | T16: =Q16-R16-S16 -> 1186.1174 | U16: =G16+E16 -> 46.616667 | V16: =E16*(1.02)*(1.25)+G16 -> 53.95 | W16: =E16*(1.02)*(1.5)+G16 -> 60.75 | X16: =$I16*U16 -> 932.33333 | Y16: =$I16*V16 -> 1079 | Z16: =$I16*W16 -> 1215 | AA16: =$T16-X16 -> 253.78407 | AB16: =$T16-Y16 -> 107.1174 | AC16: =$T16-Z16 -> -28.8826 | AD16: =AA16/$M16 -> 0.074646105 | AE16: =AB16/$M16 -> 0.031506693 | AF16: =AC16/$M16 -> -0.0084953071
B17: ET012 | C17: KD | D17: 2200 | E17: =D17/84 -> 26.190476 | F17: 3.19 | G17: =F17*$G$3 -> 22.33 | H17: 249.99 | I17: 20 | J17: =H17*I17 -> 4999.8 | K17: =$K$3 -> 0.15 | L17: =rounddown(I17*(1-K17),0) -> 17 | M17: =L17*H17 -> 4249.83 | N17: =M17*$N$3+3%*(I17-L17)*H17 -> 659.9736 | O17: 24.81 | P17: =O17*(I17) -> 496.2 | Q17: =M17-N17-P17 -> 3093.6564 | R17: =J17*$R$3 -> 1249.95 | S17: =J17*$S$3 -> 274.989 | T17: =Q17-R17-S17 -> 1568.7174 | U17: =G17+E17 -> 48.520476 | V17: =E17*(1.02)*(1.25)+G17 -> 55.722857 | W17: =E17*(1.02)*(1.5)+G17 -> 62.401429 | X17: =$I17*U17 -> 970.40952 | Y17: =$I17*V17 -> 1114.4571 | Z17: =$I17*W17 -> 1248.0286 | AA17: =$T17-X17 -> 598.30788 | AB17: =$T17-Y17 -> 454.26026 | AC17: =$T17-Z17 -> 320.68883 | AD17: =AA17/$M17 -> 0.14078396 | AE17: =AB17/$M17 -> 0.10688904 | AF17: =AC17/$M17 -> 0.075459213
B18: ET013 | C18: Non-KD | D18: 4000 | E18: =D18/84 -> 47.619048 | F18: 6.38 | G18: =F18*$G$3 -> 44.66 | H18: 449.99 | I18: 20 | J18: =H18*I18 -> 8999.8 | K18: =$K$3 -> 0.15 | L18: =rounddown(I18*(1-K18),0) -> 17 | M18: =L18*H18 -> 7649.83 | N18: =M18*$N$3+3%*(I18-L18)*H18 -> 1187.9736 | O18: 61.56 | P18: =O18*(I18) -> 1231.2 | Q18: =M18-N18-P18 -> 5230.6564 | R18: =J18*$R$3 -> 2249.95 | S18: =J18*$S$3 -> 494.989 | T18: =Q18-R18-S18 -> 2485.7174 | U18: =G18+E18 -> 92.279048 | V18: =E18*(1.02)*(1.25)+G18 -> 105.37429 | W18: =E18*(1.02)*(1.5)+G18 -> 117.51714 | X18: =$I18*U18 -> 1845.581 | Y18: =$I18*V18 -> 2107.4857 | Z18: =$I18*W18 -> 2350.3429 | AA18: =$T18-X18 -> 640.13645 | AB18: =$T18-Y18 -> 378.23169 | AC18: =$T18-Z18 -> 135.37454 | AD18: =AA18/$M18 -> 0.083679827 | AE18: =AB18/$M18 -> 0.049443149 | AF18: =AC18/$M18 -> 0.017696412
B19: ET067 | C19: KD | D19: 2500 | E19: =D19/84 -> 29.761905 | F19: 1.92 | G19: =F19*$G$3 -> 13.44 | H19: 189.99 | I19: 20 | J19: =H19*I19 -> 3799.8 | K19: =$K$3 -> 0.15 | L19: =rounddown(I19*(1-K19),0) -> 17 | M19: =L19*H19 -> 3229.83 | N19: =M19*$N$3+3%*(I19-L19)*H19 -> 501.5736 | O19: 19.11 | P19: =O19*(I19) -> 382.2 | Q19: =M19-N19-P19 -> 2346.0564 | R19: =J19*$R$3 -> 949.95 | S19: =J19*$S$3 -> 208.989 | T19: =Q19-R19-S19 -> 1187.1174 | U19: =G19+E19 -> 43.201905 | V19: =E19*(1.02)*(1.25)+G19 -> 51.386429 | W19: =E19*(1.02)*(1.5)+G19 -> 58.975714 | X19: =$I19*U19 -> 864.0381 | Y19: =$I19*V19 -> 1027.7286 | Z19: =$I19*W19 -> 1179.5143 | AA19: =$T19-X19 -> 323.0793 | AB19: =$T19-Y19 -> 159.38883 | AC19: =$T19-Z19 -> 7.6031143 | AD19: =AA19/$M19 -> 0.10002982 | AE19: =AB19/$M19 -> 0.049348984 | AF19: =AC19/$M19 -> 0.0023540292
B20: Aggregate | J20: =sum(J5:J10) -> 17312.45 | M20: =sum(M5:M10) -> 14302.55 | N20: =sum(N5:N10) -> 2235.6795 | P20: =sum(P5:P10) -> 2215.91 | Q20: =sum(Q5:Q10) -> 9850.9605 | R20: =sum(R5:R10) -> 4328.1125 | S20: =sum(S5:S10) -> 952.18475 | T20: =sum(T5:T10) -> 4570.6632 | X20: =sum(X5:X10) -> 4030.6825 | Y20: =sum(Y5:Y10) -> 4692.7615 | Z20: =sum(Z5:Z10) -> 5306.6893 | AA20: =sum(AA5:AA10) -> 539.98078 | AB20: =sum(AB5:AB10) -> -122.09822 | AC20: =sum(AC5:AC10) -> -736.02602 | AD20: =AA20/$M20 -> 0.037754161 | AE20: =AB20/$M20 -> -0.0085368146 | AF20: =AC20/$M20 -> -0.051461174 | AG20: =AI20/AH20 -> 0.14695341 | AH20: =SUM(AH5:AH10) -> 279 | AI20: =SUM(AI5:AI10) -> 41
V22: Return Fees | W22: 0.03 | X22: of Returns
V23: Returns | W23: 0.15 | X23: of Gross
V24: Ads | W24: 0.25 | X24: of Gross
V25: Other costs | W25: 0.06 | X25: of Gross
V26: Platform fees | W26: 0.15 | X26: of Net
V27: Profit | W27: 0.15 | X27: of Net
V28: COGS | W28: 29.7
V29: FBA Fulfilment | W29: 16
T31: =T32*15% -> 12.75 | V31: Net Platform Fees | W31: =W26*(1-W23) + W22*W23 -> 0.132 | X31: of Gross
S32: Net sales | T32: =T35*T34*(1-T33) -> 85 | V32: Profit | W32: =W27*(1-W23) -> 0.1275 | X32: of Gross
S33: Return rate | T33: 0.15 | V33: All components except COGS | W33: =W32+W31+W24+W25 -> 0.5695 | X33: of Gross
S34: Gross Units | T34: 1 | W34: =1-W33 -> 0.4305 | X34: =W29+W28 -> 45.7
S35: ASP | T35: 100 | V35: ASP | X35: =X34/W34 -> 106.15563
X36: =W29/X35 -> 0.1507221
X37: =W28/X35 -> 0.2797779

Sheet Sheet3
A3: Row Labels | B3: Sum of Product sales2 | C3: Sum of Sales return | D3: Sum of Net sales | E3: Sum of Sales qty | F3: Sum of Return qty | G3: Sum of Net qty | H3: Sum of Amazon SF | I3: Sum of Amazon FF | J3: Sum of Amazon OF | K3: Sum of Amazon TF | L3: Sum of OM1
A4: RH-CS004MC-FBM | B4: 323.99 | C4: 0 | D4: 323.99 | E4: 1 | F4: 0 | G4: 1 | H4: -42.4 | I4: 0 | J4: -0.05 | K4: -42.45 | L4: 281.54
A5: RH-CT001MW-18H | B5: 378.39 | C5: 0 | D5: 378.39 | E5: 1 | F5: 0 | G5: 1 | H5: -47.84 | I5: 0 | J5: -0.05 | K5: -47.89 | L5: 330.5
A6: RH-CT007-FBA | B6: 429.99 | C6: -429.99 | D6: 0 | E6: 1 | F6: -1 | G6: 0 | H6: -5 | I6: -53.62 | J6: 0 | K6: -58.62 | L6: -58.62
A7: RH-CT009-FBA | B7: 1329.98 | C7: -1329.98 | D7: 0 | E7: 2 | F7: -2 | G7: 0 | H7: -10 | I7: -389.9 | J7: 0 | K7: -399.9 | L7: -399.9
A8: RH-CT009MW-18H-FBAA | B8: 692.99 | C8: -692.99 | D8: 0 | E8: 1 | F8: -1 | G8: 0 | H8: -5 | I8: -194.95 | J8: 0 | K8: -199.95 | L8: -199.95
A9: RH-CT009MW-18H-FBM | B9: 699.99 | C9: 0 | D9: 699.99 | E9: 1 | F9: 0 | G9: 1 | H9: -80 | I9: 0 | J9: 0 | K9: -80 | L9: 619.99
A10: RH-DR001MW-FBA | B10: 2067.12 | C10: 0 | D10: 2067.12 | E10: 16 | F10: 0 | G10: 16 | H10: -304.74 | I10: -426.37 | J10: 0 | K10: -731.11 | L10: 1336.01
A11: RH-DR002MTMW-FBA | B11: 2726.79 | C11: -125.99 | D11: 2600.8 | E11: 21 | F11: -1 | G11: 20 | H11: -365.44 | I11: -735.43 | J11: 0 | K11: -1100.87 | L11: 1499.93
A12: RH-DR005MW-FBA | B12: 1493.25 | C12: -352.46 | D12: 1140.79 | E12: 18 | F12: -4 | G12: 14 | H12: -181.11 | I12: -95.1 | J12: 0 | K12: -276.21 | L12: 864.58
A13: RH-ET003-N-FBA | B13: 2202.6 | C13: -439.88 | D13: 1762.72 | E13: 10 | F13: -2 | G13: 8 | H13: -261.73 | I13: -258.39 | J13: 0 | K13: -520.12 | L13: 1242.6
A14: RH-ET003-W | B14: 218.39 | C14: -218.39 | D14: 0 | E14: 1 | F14: -1 | G14: 0 | H14: -5 | I14: 0 | J14: -0.05 | K14: -5.05 | L14: -5.05
A15: RH-ET003-W-FBA | B15: 709.77 | C15: 0 | D15: 709.77 | E15: 3 | F15: 0 | G15: 3 | H15: -100.98 | I15: -68.73 | J15: 0 | K15: -169.71 | L15: 540.06
... A23: Grand Total | B23: 22085.21 | C23: -4630.31 | D23: 17454.9 | E23: 140 | F23: -19 | G23: 121 | H23: -2575.04 | I23: -3321.97 | J23: -0.3 | K23: -5897.31 | L23: 11557.59
B25: 1194
B26: =B25/GETPIVOTDATA("Sum of Product sales2",$A$3) -> #REF!

Sheet Sheet6
A3: Sum of P/L (0%) | B3: Sum of P/L(25%) | C3: Sum of P/L(50%)
A4: 885.4091 | B4: 238.1191 | C4: -409.6909

Sheet 2025Sep1-2025Sep30CustomUnified
A1: date/time | B1: settlement id | C1: type | D1: order id | E1: sku | F1: description | G1: quantity | H1: marketplace | I1: account type | J1: fulfillment | K1: order city | L1: order state | M1: order postal | N1: tax collection model | O1: product sales | P1: product sales tax | Q1: shipping credits | R1: shipping credits tax | S1: gift wrap credits | T1: giftwrap credits tax | U1: Regulatory Fee | V1: Tax On Regulatory Fee | W1: promotional rebates | X1: promotional rebates tax | Y1: marketplace withheld tax | Z1: selling fees | AA1: fba fees | AB1: other transaction fees | AC1: other | AD1: total | AE1: Product sales2 | AF1: Sales return | AG1: Net sales | AH1: Sales qty | AI1: Return qty | AJ1: Net qty | AK1: Amazon SF | AL1: Amazon FF | AM1: Amazon OF | AN1: Amazon TF | AO1: OM1
A2: Sep 1, 2025 12:54:36 AM PDT | B2: 24342675541 | C2: Order | D2: 113-3629197-4909060 | E2: RH-ET042MB(D)-FBA | F2: Stupa Solid Wood End Table - 22" Tall Round Side Table for Living Room or Bedroom, Handcrafted Accent Table in Distressed Black Finish, Easy Assembly, | G2: 1 | H2: amazon.com | I2: Standard Orders | J2: Amazon | K2: MARYSVILLE | L2: WA | M2: 98271 | N2: MarketplaceFacilitator | O2: 129.99 | P2: 11.61 | Q2: 0 | R2: 0 | S2: 0 | T2: 0 | U2: 0 | V2: 0 | W2: -6.5 | X2: 0 | Y2: -11.61 | Z2: -18.52 | AA2: -16.45 | AB2: 0 | AC2: 0 | AD2: 88.52 | AE2: =IF('2025Sep1-2025Sep30CustomUnified'!$C2="order",'2025Sep1-2025Sep30CustomUnified'!$O2,0) -> 129.99 | AF2: =IF('2025Sep1-2025Sep30CustomUnified'!$C2="refund",'2025Sep1-2025Sep30CustomUnified'!$O2,0) -> 0 | AG2: =SUM('2025Sep1-2025Sep30CustomUnified'!$AE2:$AF2) -> 129.99 | AH2: =IF('2025Sep1-2025Sep30CustomUnified'!$C2="order",'2025Sep1-2025Sep30CustomUnified'!$G2,0) -> 1 | AI2: =IF('2025Sep1-2025Sep30CustomUnified'!$C2="refund",-'2025Sep1-2025Sep30CustomUnified'!$G2,0) -> 0 | AJ2: =SUM('2025Sep1-2025Sep30CustomUnified'!$AH2:$AI2) -> 1 | AK2: ='2025Sep1-2025Sep30CustomUnified'!$Z2 -> -18.52 | AL2: ='2025Sep1-2025Sep30CustomUnified'!$AA2+'2025Sep1-2025Sep30CustomUnified'!$W2+'2025Sep1-2025Sep30CustomUnified'!$U2+'2025Sep1-2025Sep30CustomUnified'!$S2+'2025Sep1-2025Sep30CustomUnified'!$Q2 -> -22.95 | AM2: =SUM('2025Sep1-2025Sep30CustomUnified'!$AB2:$AC2) -> 0 | AN2: =SUM('2025Sep1-2025Sep30CustomUnified'!$AK2:$AM2) -> -41.47 | AO2: ='2025Sep1-2025Sep30CustomUnified'!$AG2+'2025Sep1-2025Sep30CustomUnified'!$AN2 -> 88.52
A3: Sep 1, 2025 7:05:27 AM PDT | B3: 24342675541 | C3: Order | D3: 111-6679077-1626666 | E3: RH-ET042MB(D)-FBA | F3: Stupa Solid Wood End Table - 22" Tall Round Side Table for Living Room or Bedroom, Handcrafted Accent Table in Distressed Black Finish, Easy Assembly, | G3: 1 | H3: amazon.com | I3: Standard Orders | J3: Amazon | K3: SACRAMENTO | L3: CA | M3: 95842 | N3: MarketplaceFacilitator | O3: 129.99 | P3: 10.07 | Q3: 0 | R3: 0 | S3: 0 | T3: 0 | U3: 0 | V3: 0 | W3: 0 | X3: 0 | Y3: -10.07 | Z3: -19.5 | AA3: -16.45 | AB3: 0 | AC3: 0 | AD3: 94.04 | AE3: =IF('2025Sep1-2025Sep30CustomUnified'!$C3="order",'2025Sep1-2025Sep30CustomUnified'!$O3,0) -> 129.99 | AF3: =IF('2025Sep1-2025Sep30CustomUnified'!$C3="refund",'2025Sep1-2025Sep30CustomUnified'!$O3,0) -> 0 | AG3: =SUM('2025Sep1-2025Sep30CustomUnified'!$AE3:$AF3) -> 129.99 | AH3: =IF('2025Sep1-2025Sep30CustomUnified'!$C3="order",'2025Sep1-2025Sep30CustomUnified'!$G3,0) -> 1 | AI3: =IF('2025Sep1-2025Sep30CustomUnified'!$C3="refund",-'2025Sep1-2025Sep30CustomUnified'!$G3,0) -> 0 | AJ3: =SUM('2025Sep1-2025Sep30CustomUnified'!$AH3:$AI3) -> 1 | AK3: ='2025Sep1-2025Sep30CustomUnified'!$Z3 -> -19.5 | AL3: ='2025Sep1-2025Sep30CustomUnified'!$AA3+'2025Sep1-2025Sep30CustomUnified'!$W3+'2025Sep1-2025Sep30CustomUnified'!$U3+'2025Sep1-2025Sep30CustomUnified'!$S3+'2025Sep1-2025Sep30CustomUnified'!$Q3 -> -16.45 | AM3: =SUM('2025Sep1-2025Sep30CustomUnified'!$AB3:$AC3) -> 0 | AN3: =SUM('2025Sep1-2025Sep30CustomUnified'!$AK3:$AM3) -> -35.95 | AO3: ='2025Sep1-2025Sep30CustomUnified'!$AG3+'2025Sep1-2025Sep30CustomUnified'!$AN3 -> 94.04
A4: Sep 1, 2025 7:44:34 AM PDT | B4: 24342675541 | C4: Order | D4: 112-9594610-6683422 | E4: RH-ET003-N-FBA | F4: Relso Gaia Round End Table for Living Room and Farmhouse | Solid Mango Wood for Rustic Elegance | Ideal for Side Tables, Nightstands & More | Wood Sid | G4: 1 | H4: amazon.com | I4: Standard Orders | J4: Amazon | K4: Shelter island | L4: NY | M4: 11964 | N4: MarketplaceFacilitator | O4: 219.99 | P4: 19.25 | Q4: 0 | R4: 0 | S4: 0 | T4: 0 | U4: 0 | V4: 0 | W4: 0 | X4: 0 | Y4: -19.25 | Z4: -32 | AA4: -21.39 | AB4: 0 | AC4: 0 | AD4: 166.6 | AE4: =IF('2025Sep1-2025Sep30CustomUnified'!$C4="order",'2025Sep1-2025Sep30CustomUnified'!$O4,0) -> 219.99 | AF4: =IF('2025Sep1-2025Sep30CustomUnified'!$C4="refund",'2025Sep1-2025Sep30CustomUnified'!$O4,0) -> 0 | AG4: =SUM('2025Sep1-2025Sep30CustomUnified'!$AE4:$AF4) -> 219.99 | AH4: =IF('2025Sep1-2025Sep30CustomUnified'!$C4="order",'2025Sep1-2025Sep30CustomUnified'!$G4,0) -> 1 | AI4: =IF('2025Sep1-2025Sep30CustomUnified'!$C4="refund",-'2025Sep1-2025Sep30CustomUnified'!$G4,0) -> 0 | AJ4: =SUM('2025Sep1-2025Sep30CustomUnified'!$AH4:$AI4) -> 1 | AK4: ='2025Sep1-2025Sep30CustomUnified'!$Z4 -> -32 | AL4: ='2025Sep1-2025Sep30CustomUnified'!$AA4+'2025Sep1-2025Sep30CustomUnified'!$W4+'2025Sep1-2025Sep30CustomUnified'!$U4+'2025Sep1-2025Sep30CustomUnified'!$S4+'2025Sep1-2025Sep30CustomUnified'!$Q4 -> -21.39 | AM4: =SUM('2025Sep1-2025Sep30CustomUnified'!$AB4:$AC4) -> 0 | AN4: =SUM('2025Sep1-2025Sep30CustomUnified'!$AK4:$AM4) -> -53.39 | AO4: ='2025Sep1-2025Sep30CustomUnified'!$AG4+'2025Sep1-2025Sep30CustomUnified'!$AN4 -> 166.6
A5: Sep 1, 2025 11:55:56 AM PDT | B5: 24342675541 | C5: Order | D5: 111-6811498-3707441 | E5: RH-ET042MB(D)-FBA | F5: Stupa Solid Wood End Table - 22" Tall Round Side Table for Living Room or Bedroom, Handcrafted Accent Table in Distressed Black Finish, Easy Assembly, | G5: 1 | H5: amazon.com | I5: Standard Orders | J5: Amazon | K5: CANBY | L5: OR | M5: 97013 | O5: 129.99 | P5: 0 | Q5: 0 | R5: 0 | S5: 0 | T5: 0 | U5: 0 | V5: 0 | W5: -6.5 | X5: 0 | Y5: 0 | Z5: -18.52 | AA5: -16.45 | AB5: 0 | AC5: 0 | AD5: 88.52 | AE5: =IF('2025Sep1-2025Sep30CustomUnified'!$C5="order",'2025Sep1-2025Sep30CustomUnified'!$O5,0) -> 129.99 | AF5: =IF('2025Sep1-2025Sep30CustomUnified'!$C5="refund",'2025Sep1-2025Sep30CustomUnified'!$O5,0) -> 0 | AG5: =SUM('2025Sep1-2025Sep30CustomUnified'!$AE5:$AF5) -> 129.99 | AH5: =IF('2025Sep1-2025Sep30CustomUnified'!$C5="order",'2025Sep1-2025Sep30CustomUnified'!$G5,0) -> 1 | AI5: =IF('2025Sep1-2025Sep30CustomUnified'!$C5="refund",-'2025Sep1-2025Sep30CustomUnified'!$G5,0) -> 0 | AJ5: =SUM('2025Sep1-2025Sep30CustomUnified'!$AH5:$AI5) -> 1 | AK5: ='2025Sep1-2025Sep30CustomUnified'!$Z5 -> -18.52 | AL5: ='2025Sep1-2025Sep30CustomUnified'!$AA5+'2025Sep1-2025Sep30CustomUnified'!$W5+'2025Sep1-2025Sep30CustomUnified'!$U5+'2025Sep1-2025Sep30CustomUnified'!$S5+'2025Sep1-2025Sep30CustomUnified'!$Q5 -> -22.95 | AM5: =SUM('2025Sep1-2025Sep30CustomUnified'!$AB5:$AC5) -> 0 | AN5: =SUM('2025Sep1-2025Sep30CustomUnified'!$AK5:$AM5) -> -41.47 | AO5: ='2025Sep1-2025Sep30CustomUnified'!$AG5+'2025Sep1-2025Sep30CustomUnified'!$AN5 -> 88.52
A6: Sep 1, 2025 3:25:35 PM PDT | B6: 24342675541 | C6: Refund | D6: 111-8445665-6491417 | E6: RH-DR002MTMW-FBA | F6: Ma'gro Drink Table - Solid Mango Wood Fluted Base with Real White Marble Top | Farmhouse Accent Side Table for Boho Decor, Bedside, Entryway, Plant St | G6: 1 | H6: amazon.com | I6: Standard Orders | J6: Amazon | K6: SOUTH HAVEN | L6: MI | M6: 49090 | N6: MarketplaceFacilitator | O6: -125.99 | P6: -7.18 | Q6: 0 | R6: 0 | S6: 0 | T6: 0 | U6: 0 | V6: 0 | W6: 6.3 | X6: 0 | Y6: 7.18 | Z6: 14.36 | AA6: 0 | AB6: 0 | AC6: 0 | AD6: -105.33 | AE6: =IF('2025Sep1-2025Sep30CustomUnified'!$C6="order",'2025Sep1-2025Sep30CustomUnified'!$O6,0) -> 0 | AF6: =IF('2025Sep1-2025Sep30CustomUnified'!$C6="refund",'2025Sep1-2025Sep30CustomUnified'!$O6,0) -> -125.99 | AG6: =SUM('2025Sep1-2025Sep30CustomUnified'!$AE6:$AF6) -> -125.99 | AH6: =IF('2025Sep1-2025Sep30CustomUnified'!$C6="order",'2025Sep1-2025Sep30CustomUnified'!$G6,0) -> 0 | AI6: =IF('2025Sep1-2025Sep30CustomUnified'!$C6="refund",-'2025Sep1-2025Sep30CustomUnified'!$G6,0) -> -1 | AJ6: =SUM('2025Sep1-2025Sep30CustomUnified'!$AH6:$AI6) -> -1 | AK6: ='2025Sep1-2025Sep30CustomUnified'!$Z6 -> 14.36 | AL6: ='2025Sep1-2025Sep30CustomUnified'!$AA6+'2025Sep1-2025Sep30CustomUnified'!$W6+'2025Sep1-2025Sep30CustomUnified'!$U6+'2025Sep1-2025Sep30CustomUnified'!$S6+'2025Sep1-2025Sep30CustomUnified'!$Q6 -> 6.3 | AM6: =SUM('2025Sep1-2025Sep30CustomUnified'!$AB6:$AC6) -> 0 | AN6: =SUM('2025Sep1-2025Sep30CustomUnified'!$AK6:$AM6) -> 20.66 | AO6: ='2025Sep1-2025Sep30CustomUnified'!$AG6+'2025Sep1-2025Sep30CustomUnified'!$AN6 -> -105.33
A7: Sep 2, 2025 12:15:42 AM PDT | B7: 24342675541 | C7: Order | D7: 111-6811498-3707441 | E7: RH-ET042MB(D)-FBA | F7: Stupa Solid Wood End Table - 22" Tall Round Side Table for Living Room or Bedroom, Handcrafted Accent Table in Distressed Black Finish, Easy Assembly, | G7: 1 | H7: amazon.com | I7: Standard Orders | J7: Amazon | K7: CANBY | L7: OR | M7: 97013 | O7: 129.99 | P7: 0 | Q7: 0 | R7: 0 | S7: 0 | T7: 0 | U7: 0 | V7: 0 | W7: -6.5 | X7: 0 | Y7: 0 | Z7: -18.52 | AA7: -16.45 | AB7: 0 | AC7: 0 | AD7: 88.52 | AE7: =IF('2025Sep1-2025Sep30CustomUnified'!$C7="order",'2025Sep1-2025Sep30CustomUnified'!$O7,0) -> 129.99 | AF7: =IF('2025Sep1-2025Sep30CustomUnified'!$C7="refund",'2025Sep1-2025Sep30CustomUnified'!$O7,0) -> 0 | AG7: =SUM('2025Sep1-2025Sep30CustomUnified'!$AE7:$AF7) -> 129.99 | AH7: =IF('2025Sep1-2025Sep30CustomUnified'!$C7="order",'2025Sep1-2025Sep30CustomUnified'!$G7,0) -> 1 | AI7: =IF('2025Sep1-2025Sep30CustomUnified'!$C7="refund",-'2025Sep1-2025Sep30CustomUnified'!$G7,0) -> 0 | AJ7: =SUM('2025Sep1-2025Sep30CustomUnified'!$AH7:$AI7) -> 1 | AK7: ='2025Sep1-2025Sep30CustomUnified'!$Z7 -> -18.52 | AL7: ='2025Sep1-2025Sep30CustomUnified'!$AA7+'2025Sep1-2025Sep30CustomUnified'!$W7+'2025Sep1-2025Sep30CustomUnified'!$U7+'2025Sep1-2025Sep30CustomUnified'!$S7+'2025Sep1-2025Sep30CustomUnified'!$Q7 -> -22.95 | AM7: =SUM('2025Sep1-2025Sep30CustomUnified'!$AB7:$AC7) -> 0 | AN7: =SUM('2025Sep1-2025Sep30CustomUnified'!$AK7:$AM7) -> -41.47 | AO7: ='2025Sep1-2025Sep30CustomUnified'!$AG7+'2025Sep1-2025Sep30CustomUnified'!$AN7 -> 88.52
A8: Sep 2, 2025 1:04:18 AM PDT | B8: 24342675541 | C8: Order | D8: 112-0028999-6002601 | E8: RH-ET042MB(D)-FBA | F8: Stupa Solid Wood End Table - 22" Tall Round Side Table for Living Room or Bedroom, Handcrafted Accent Table in Distressed Black Finish, Easy Assembly, | G8: 1 | H8: amazon.com | I8: Standard Orders | J8: Amazon | K8: COCONUT CREEK | L8: FL | M8: 33066 | N8: MarketplaceFacilitator | O8: 129.99 | P8: 9.1 | Q8: 0 | R8: 0 | S8: 0 | T8: 0 | U8: 0 | V8: 0 | W8: 0 | X8: 0 | Y8: -9.1 | Z8: -19.5 | AA8: -16.45 | AB8: 0 | AC8: 0 | AD8: 94.04 | AE8: =IF('2025Sep1-2025Sep30CustomUnified'!$C8="order",'2025Sep1-2025Sep30CustomUnified'!$O8,0) -> 129.99 | AF8: =IF('2025Sep1-2025Sep30CustomUnified'!$C8="refund",'2025Sep1-2025Sep30CustomUnified'!$O8,0) -> 0 | AG8: =SUM('2025Sep1-2025Sep30CustomUnified'!$AE8:$AF8) -> 129.99 | AH8: =IF('2025Sep1-2025Sep30CustomUnified'!$C8="order",'2025Sep1-2025Sep30CustomUnified'!$G8,0) -> 1 | AI8: =IF('2025Sep1-2025Sep30CustomUnified'!$C8="refund",-'2025Sep1-2025Sep30CustomUnified'!$G8,0) -> 0 | AJ8: =SUM('2025Sep1-2025Sep30CustomUnified'!$AH8:$AI8) -> 1 | AK8: ='2025Sep1-2025Sep30CustomUnified'!$Z8 -> -19.5 | AL8: ='2025Sep1-2025Sep30CustomUnified'!$AA8+'2025Sep1-2025Sep30CustomUnified'!$W8+'2025Sep1-2025Sep30CustomUnified'!$U8+'2025Sep1-2025Sep30CustomUnified'!$S8+'2025Sep1-2025Sep30CustomUnified'!$Q8 -> -16.45 | AM8: =SUM('2025Sep1-2025Sep30CustomUnified'!$AB8:$AC8) -> 0 | AN8: =SUM('2025Sep1-2025Sep30CustomUnified'!$AK8:$AM8) -> -35.95 | AO8: ='2025Sep1-2025Sep30CustomUnified'!$AG8+'2025Sep1-2025Sep30CustomUnified'!$AN8 -> 94.04
A9: Sep 2, 2025 5:18:04 AM PDT | B9: 24342675541 | C9: Order | D9: 111-8445665-6491417 | E9: RH-DR002MTMW-FBA | F9: Ma'gro Drink Table - Solid Mango Wood Fluted Base with Real White Marble Top | Farmhouse Accent Side Table for Boho Decor, Bedside, Entryway, Plant St | G9: 1 | H9: amazon.com | I9: Standard Orders | J9: Amazon | K9: SOUTH HAVEN | L9: MI | M9: 49090 | N9: MarketplaceFacilitator | O9: 125.99 | P9: 7.18 | Q9: 0 | R9: 0 | S9: 0 | T9: 0 | U9: 0 | V9: 0 | W9: -6.3 | X9: 0 | Y9: -7.18 | Z9: -17.95 | AA9: -25.95 | AB9: 0 | AC9: 0 | AD9: 75.79 | AE9: =IF('2025Sep1-2025Sep30CustomUnified'!$C9="order",'2025Sep1-2025Sep30CustomUnified'!$O9,0) -> 125.99 | AF9: =IF('2025Sep1-2025Sep30CustomUnified'!$C9="refund",'2025Sep1-2025Sep30CustomUnified'!$O9,0) -> 0 | AG9: =SUM('2025Sep1-2025Sep30CustomUnified'!$AE9:$AF9) -> 125.99 | AH9: =IF('2025Sep1-2025Sep30CustomUnified'!$C9="order",'2025Sep1-2025Sep30CustomUnified'!$G9,0) -> 1 | AI9: =IF('2025Sep1-2025Sep30CustomUnified'!$C9="refund",-'2025Sep1-2025Sep30CustomUnified'!$G9,0) -> 0 | AJ9: =SUM('2025Sep1-2025Sep30CustomUnified'!$AH9:$AI9) -> 1 | AK9: ='2025Sep1-2025Sep30CustomUnified'!$Z9 -> -17.95 | AL9: ='2025Sep1-2025Sep30CustomUnified'!$AA9+'2025Sep1-2025Sep30CustomUnified'!$W9+'2025Sep1-2025Sep30CustomUnified'!$U9+'2025Sep1-2025Sep30CustomUnified'!$S9+'2025Sep1-2025Sep30CustomUnified'!$Q9 -> -32.25 | AM9: =SUM('2025Sep1-2025Sep30CustomUnified'!$AB9:$AC9) -> 0 | AN9: =SUM('2025Sep1-2025Sep30CustomUnified'!$AK9:$AM9) -> -50.2 | AO9: ='2025Sep1-2025Sep30CustomUnified'!$AG9+'2025Sep1-2025Sep30CustomUnified'!$AN9 -> 75.79
A10: Sep 2, 2025 5:51:43 AM PDT | B10: 24342675541 | C10: Order | D10: 114-9137951-0633801 | E10: RH-ET042MB(D)-FBA | F10: Stupa Solid Wood End Table - 22" Tall Round Side Table for Living Room or Bedroom, Handcrafted Accent Table in Distressed Black Finish, Easy Assembly, | G10: 1 | H10: amazon.com | I10: Standard Orders | J10: Amazon | K10: MARIETTA | L10: GA | M10: 30064 | N10: MarketplaceFacilitator | O10: 129.99 | P10: 7.41 | Q10: 0 | R10: 0 | S10: 0 | T10: 0 | U10: 0 | V10: 0 | W10: -6.5 | X10: 0 | Y10: -7.41 | Z10: -18.52 | AA10: -16.45 | AB10: 0 | AC10: 0 | AD10: 88.52 | AE10: =IF('2025Sep1-2025Sep30CustomUnified'!$C10="order",'2025Sep1-2025Sep30CustomUnified'!$O10,0) -> 129.99 | AF10: =IF('2025Sep1-2025Sep30CustomUnified'!$C10="refund",'2025Sep1-2025Sep30CustomUnified'!$O10,0) -> 0 | AG10: =SUM('2025Sep1-2025Sep30CustomUnified'!$AE10:$AF10) -> 129.99 | AH10: =IF('2025Sep1-2025Sep30CustomUnified'!$C10="order",'2025Sep1-2025Sep30CustomUnified'!$G10,0) -> 1 | AI10: =IF('2025Sep1-2025Sep30CustomUnified'!$C10="refund",-'2025Sep1-2025Sep30CustomUnified'!$G10,0) -> 0 | AJ10: =SUM('2025Sep1-2025Sep30CustomUnified'!$AH10:$AI10) -> 1 | AK10: ='2025Sep1-2025Sep30CustomUnified'!$Z10 -> -18.52 | AL10: ='2025Sep1-2025Sep30CustomUnified'!$AA10+'2025Sep1-2025Sep30CustomUnified'!$W10+'2025Sep1-2025Sep30CustomUnified'!$U10+'2025Sep1-2025Sep30CustomUnified'!$S10+'2025Sep1-2025Sep30CustomUnified'!$Q10 -> -22.95 | AM10: =SUM('2025Sep1-2025Sep30CustomUnified'!$AB10:$AC10) -> 0 | AN10: =SUM('2025Sep1-2025Sep30CustomUnified'!$AK10:$AM10) -> -41.47 | AO10: ='2025Sep1-2025Sep30CustomUnified'!$AG10+'2025Sep1-2025Sep30CustomUnified'!$AN10 -> 88.52
A11: Sep 2, 2025 8:00:05 AM PDT | B11: 24342675541 | C11: Order | D11: 114-7098282-7403403 | E11: RH-ET003-N-FBA | F11: Relso Gaia Round End Table for Living Room and Farmhouse | Solid Mango Wood for Rustic Elegance | Ideal for Side Tables, Nightstands & More | Wood Sid | G11: 1 | H11: amazon.com | I11: Standard Orders | J11: Amazon | K11: DURHAM | L11: NC | M11: 27703 | N11: MarketplaceFacilitator | O11: 219.99 | P11: 14.85 | Q11: 0 | R11: 0 | S11: 0 | T11: 0 | U11: 0 | V11: 0 | W11: -22 | X11: 0 | Y11: -14.85 | Z11: -29.7 | AA11: -21.39 | AB11: 0 | AC11: 0 | AD11: 146.9 | AE11: =IF('2025Sep1-2025Sep30CustomUnified'!$C11="order",'2025Sep1-2025Sep30CustomUnified'!$O11,0) -> 219.99 | AF11: =IF('2025Sep1-2025Sep30CustomUnified'!$C11="refund",'2025Sep1-2025Sep30CustomUnified'!$O11,0) -> 0 | AG11: =SUM('2025Sep1-2025Sep30CustomUnified'!$AE11:$AF11) -> 219.99 | AH11: =IF('2025Sep1-2025Sep30CustomUnified'!$C11="order",'2025Sep1-2025Sep30CustomUnified'!$G11,0) -> 1 | AI11: =IF('2025Sep1-2025Sep30CustomUnified'!$C11="refund",-'2025Sep1-2025Sep30CustomUnified'!$G11,0) -> 0 | AJ11: =SUM('2025Sep1-2025Sep30CustomUnified'!$AH11:$AI11) -> 1 | AK11: ='2025Sep1-2025Sep30CustomUnified'!$Z11 -> -29.7 | AL11: ='2025Sep1-2025Sep30CustomUnified'!$AA11+'2025Sep1-2025Sep30CustomUnified'!$W11+'2025Sep1-2025Sep30CustomUnified'!$U11+'2025Sep1-2025Sep30CustomUnified'!$S11+'2025Sep1-2025Sep30CustomUnified'!$Q11 -> -43.39 | AM11: =SUM('2025Sep1-2025Sep30CustomUnified'!$AB11:$AC11) -> 0 | AN11: =SUM('2025Sep1-2025Sep30CustomUnified'!$AK11:$AM11) -> -73.09 | AO11: ='2025Sep1-2025Sep30CustomUnified'!$AG11+'2025Sep1-2025Sep30CustomUnified'!$AN11 -> 146.9
A12: Sep 2, 2025 8:49:27 AM PDT | B12: 24342675541 | C12: Order | D12: 113-4621835-4025016 | E12: RH-CT009MW-18H-FBM | F12: Octavian Coffee Table -Solid Wood Round Drum Center Table for Living Room with Geometric Faceted Design - Walnut Finish Center Table, Modern Decor, Fa | G12: 1 | H12: amazon.com | I12: Standard Orders | J12: Seller | K12: LOS ANGELES | L12: CA | M12: 90049 | N12: MarketplaceFacilitator | O12: 699.99 | P12: 68.25 | Q12: 0 | R12: 0 | S12: 0 | T12: 0 | U12: 0 | V12: 0 | W12: 0 | X12: 0 | Y12: -68.25 | Z12: -80 | AA12: 0 | AB12: 0 | AC12: 0 | AD12: 619.99 | AE12: =IF('2025Sep1-2025Sep30CustomUnified'!$C12="order",'2025Sep1-2025Sep30CustomUnified'!$O12,0) -> 699.99 | AF12: =IF('2025Sep1-2025Sep30CustomUnified'!$C12="refund",'2025Sep1-2025Sep30CustomUnified'!$O12,0) -> 0 | AG12: =SUM('2025Sep1-2025Sep30CustomUnified'!$AE12:$AF12) -> 699.99 | AH12: =IF('2025Sep1-2025Sep30CustomUnified'!$C12="order",'2025Sep1-2025Sep30CustomUnified'!$G12,0) -> 1 | AI12: =IF('2025Sep1-2025Sep30CustomUnified'!$C12="refund",-'2025Sep1-2025Sep30CustomUnified'!$G12,0) -> 0 | AJ12: =SUM('2025Sep1-2025Sep30CustomUnified'!$AH12:$AI12) -> 1 | AK12: ='2025Sep1-2025Sep30CustomUnified'!$Z12 -> -80 | AL12: ='2025Sep1-2025Sep30CustomUnified'!$AA12+'2025Sep1-2025Sep30CustomUnified'!$W12+'2025Sep1-2025Sep30CustomUnified'!$U12+'2025Sep1-2025Sep30CustomUnified'!$S12+'2025Sep1-2025Sep30CustomUnified'!$Q12 -> 0 | AM12: =SUM('2025Sep1-2025Sep30CustomUnified'!$AB12:$AC12) -> 0 | AN12: =SUM('2025Sep1-2025Sep30CustomUnified'!$AK12:$AM12) -> -80 | AO12: ='2025Sep1-2025Sep30CustomUnified'!$AG12+'2025Sep1-2025Sep30CustomUnified'!$AN12 -> 619.99
A13: Sep 3, 2025 12:38:31 AM PDT | B13: 24342675541 | C13: Refund | D13: 114-1022469-6537025 | E13: RH-CT009-FBA | F13: Relso Solid Wood Geometric Faceted Coffee Tables Living Room, Crafted for Versatile Use | Drum Round Shaped | for Living Rooms | Wooden Drum Coffee Ta | G13: 1 | H13: amazon.com | I13: Standard Orders | J13: Amazon | K13: LOS ANGELES | L13: CA | M13: 90049 | N13: MarketplaceFacilitator | O13: -649.99 | P13: -63.37 | Q13: 0 | R13: 0 | S13: 0 | T13: 0 | U13: 0 | V13: 0 | W13: 0 | X13: 0 | Y13: 63.37 | Z13: 70 | AA13: 0 | AB13: 0 | AC13: 0 | AD13: -579.99 | AE13: =IF('2025Sep1-2025Sep30CustomUnified'!$C13="order",'2025Sep1-2025Sep30CustomUnified'!$O13,0) -> 0 | AF13: =IF('2025Sep1-2025Sep30CustomUnified'!$C13="refund",'2025Sep1-2025Sep30CustomUnified'!$O13,0) -> -649.99 | AG13: =SUM('2025Sep1-2025Sep30CustomUnified'!$AE13:$AF13) -> -649.99 | AH13: =IF('2025Sep1-2025Sep30CustomUnified'!$C13="order",'2025Sep1-2025Sep30CustomUnified'!$G13,0) -> 0 | AI13: =IF('2025Sep1-2025Sep30CustomUnified'!$C13="refund",-'2025Sep1-2025Sep30CustomUnified'!$G13,0) -> -1 | AJ13: =SUM('2025Sep1-2025Sep30CustomUnified'!$AH13:$AI13) -> -1 | AK13: ='2025Sep1-2025Sep30CustomUnified'!$Z13 -> 70 | AL13: ='2025Sep1-2025Sep30CustomUnified'!$AA13+'2025Sep1-2025Sep30CustomUnified'!$W13+'2025Sep1-2025Sep30CustomUnified'!$U13+'2025Sep1-2025Sep30CustomUnified'!$S13+'2025Sep1-2025Sep30CustomUnified'!$Q13 -> 0 | AM13: =SUM('2025Sep1-2025Sep30CustomUnified'!$AB13:$AC13) -> 0 | AN13: =SUM('2025Sep1-2025Sep30CustomUnified'!$AK13:$AM13) -> 70 | AO13: ='2025Sep1-2025Sep30CustomUnified'!$AG13+'2025Sep1-2025Sep30CustomUnified'!$AN13 -> -579.99
A14: Sep 3, 2025 4:05:57 AM PDT | B14: 24342675541 | C14: Order | D14: 111-7082037-7503422 | E14: RH-ET042MW-FBA | F14: Relso Stupa Solid Wood End Table - 22" Tall Round Side Table for Living Room or Bedroom, Handcrafted Accent Table in Walnut Finish, Easy Assembly, Mod | G14: 1 | H14: amazon.com | I14: Standard Orders | J14: Amazon | K14: RIO RANCHO | L14: NM | M14: 87124 | N14: MarketplaceFacilitator | O14: 110.49 | P14: 7.81 | Q14: 0 | R14: 0 | S14: 0 | T14: 0 | U14: 0 | V14: 0 | W14: -5.53 | X14: 0 | Y14: -15.62 | Z14: -31.5 | AA14: -16.45 | AB14: 0 | AC14: 0 | AD14: 49.2 | AE14: =IF('2025Sep1-2025Sep30CustomUnified'!$C14="order",'2025Sep1-2025Sep30CustomUnified'!$O14,0) -> 110.49 | AF14: =IF('2025Sep1-2025Sep30CustomUnified'!$C14="refund",'2025Sep1-2025Sep30CustomUnified'!$O14,0) -> 0 | AG14: =SUM('2025Sep1-2025Sep30CustomUnified'!$AE14:$AF14) -> 110.49 | AH14: =IF('2025Sep1-2025Sep30CustomUnified'!$C14="order",'2025Sep1-2025Sep30CustomUnified'!$G14,0) -> 1 | AI14: =IF('2025Sep1-2025Sep30CustomUnified'!$C14="refund",-'2025Sep1-2025Sep30CustomUnified'!$G14,0) -> 0 | AJ14: =SUM('2025Sep1-2025Sep30CustomUnified'!$AH14:$AI14) -> 1 | AK14: ='2025Sep1-2025Sep30CustomUnified'!$Z14 -> -31.5 | AL14: ='2025Sep1-2025Sep30CustomUnified'!$AA14+'2025Sep1-2025Sep30CustomUnified'!$W14+'2025Sep1-2025Sep30CustomUnified'!$U14+'2025Sep1-2025Sep30CustomUnified'!$S14+'2025Sep1-2025Sep30CustomUnified'!$Q14 -> -21.98 | AM14: =SUM('2025Sep1-2025Sep30CustomUnified'!$AB14:$AC14) -> 0 | AN14: =SUM('2025Sep1-2025Sep30CustomUnified'!$AK14:$AM14) -> -53.48 | AO14: ='2025Sep1-2025Sep30CustomUnified'!$AG14+'2025Sep1-2025Sep30CustomUnified'!$AN14 -> 57.01
A15: Sep 3, 2025 4:05:57 AM PDT | B15: 24342675541 | C15: Order | D15: 111-7082037-7503422 | E15: RH-ET042MW-FBA | F15: Relso Stupa Solid Wood End Table - 22" Tall Round Side Table for Living Room or Bedroom, Handcrafted Accent Table in Walnut Finish, Easy Assembly, Mod | G15: 1 | H15: amazon.com | I15: Standard Orders | J15: Amazon | K15: RIO RANCHO | L15: NM | M15: 87124 | O15: 110.49 | P15: 7.81 | Q15: 0 | R15: 0 | S15: 0 | T15: 0 | U15: 0 | V15: 0 | W15: -5.52 | X15: 0 | Y15: 0 | Z15: 0 | AA15: -16.45 | AB15: 0 | AC15: 0 | AD15: 96.33 | AE15: =IF('2025Sep1-2025Sep30CustomUnified'!$C15="order",'2025Sep1-2025Sep30CustomUnified'!$O15,0) -> 110.49 | AF15: =IF('2025Sep1-2025Sep30CustomUnified'!$C15="refund",'2025Sep1-2025Sep30CustomUnified'!$O15,0) -> 0 | AG15: =SUM('2025Sep1-2025Sep30CustomUnified'!$AE15:$AF15) -> 110.49 | AH15: =IF('2025Sep1-2025Sep30CustomUnified'!$C15="order",'2025Sep1-2025Sep30CustomUnified'!$G15,0) -> 1 | AI15: =IF('2025Sep1-2025Sep30CustomUnified'!$C15="refund",-'2025Sep1-2025Sep30CustomUnified'!$G15,0) -> 0 | AJ15: =SUM('2025Sep1-2025Sep30CustomUnified'!$AH15:$AI15) -> 1 | AK15: ='2025Sep1-2025Sep30CustomUnified'!$Z15 -> 0 | AL15: ='2025Sep1-2025Sep30CustomUnified'!$AA15+'2025Sep1-2025Sep30CustomUnified'!$W15+'2025Sep1-2025Sep30CustomUnified'!$U15+'2025Sep1-2025Sep30CustomUnified'!$S15+'2025Sep1-2025Sep30CustomUnified'!$Q15 -> -21.97 | AM15: =SUM('2025Sep1-2025Sep30CustomUnified'!$AB15:$AC15) -> 0 | AN15: =SUM('2025Sep1-2025Sep30CustomUnified'!$AK15:$AM15) -> -21.97 | AO15: ='2025Sep1-2025Sep30CustomUnified'!$AG15+'2025Sep1-2025Sep30CustomUnified'!$AN15 -> 88.52
A16: Sep 3, 2025 6:52:10 AM PDT | B16: 24342675541 | C16: Order | D16: 114-1022469-6537025 | E16: RH-CT009-FBA | F16: Relso Solid Wood Geometric Faceted Coffee Tables Living Room, Crafted for Versatile Use | Drum Round Shaped | for Living Rooms | Wooden Drum Coffee Ta | G16: 1 | H16: amazon.com | I16: Standard Orders | J16: Amazon | K16: LOS ANGELES | L16: CA | M16: 90049 | N16: MarketplaceFacilitator | O16: 649.99 | P16: 63.37 | Q16: 0 | R16: 0 | S16: 0 | T16: 0 | U16: 0 | V16: 0 | W16: 0 | X16: 0 | Y16: -63.37 | Z16: -75 | AA16: -194.95 | AB16: 0 | AC16: 0 | AD16: 380.04 | AE16: =IF('2025Sep1-2025Sep30CustomUnified'!$C16="order",'2025Sep1-2025Sep30CustomUnified'!$O16,0) -> 649.99 | AF16: =IF('2025Sep1-2025Sep30CustomUnified'!$C16="refund",'2025Sep1-2025Sep30CustomUnified'!$O16,0) -> 0 | AG16: =SUM('2025Sep1-2025Sep30CustomUnified'!$AE16:$AF16) -> 649.99 | AH16: =IF('2025Sep1-2025Sep30CustomUnified'!$C16="order",'2025Sep1-2025Sep30CustomUnified'!$G16,0) -> 1 | AI16: =IF('2025Sep1-2025Sep30CustomUnified'!$C16="refund",-'2025Sep1-2025Sep30CustomUnified'!$G16,0) -> 0 | AJ16: =SUM('2025Sep1-2025Sep30CustomUnified'!$AH16:$AI16) -> 1 | AK16: ='2025Sep1-2025Sep30CustomUnified'!$Z16 -> -75 | AL16: ='2025Sep1-2025Sep30CustomUnified'!$AA16+'2025Sep1-2025Sep30CustomUnified'!$W16+'2025Sep1-2025Sep30CustomUnified'!$U16+'2025Sep1-2025Sep30CustomUnified'!$S16+'2025Sep1-2025Sep30CustomUnified'!$Q16 -> -194.95 | AM16: =SUM('2025Sep1-2025Sep30CustomUnified'!$AB16:$AC16) -> 0 | AN16: =SUM('2025Sep1-2025Sep30CustomUnified'!$AK16:$AM16) -> -269.95 | AO16: ='2025Sep1-2025Sep30CustomUnified'!$AG16+'2025Sep1-2025Sep30CustomUnified'!$AN16 -> 380.04
A17: Sep 3, 2025 7:52:49 AM PDT | B17: 24342675541 | C17: Order | D17: 112-5571817-6834602 | E17: RH-DR005MW-FBA | F17: Relso Stambha Solid Wood Drink Table - 24" Tall Round Accent Side Table for Living Room or Bedroom, Narrow End Table or Indoor Plant Stand, Walnut Fin | G17: 1 | H17: amazon.com | I17: Standard Orders | J17: Amazon | K17: CHICAGO | L17: IL | M17: 60626 | N17: MarketplaceFacilitator | O17: 77.89 | P17: 7.59 | Q17: 0 | R17: 0 | S17: 0 | T17: 0 | U17: 0 | V17: 0 | W17: -3.89 | X17: 0 | Y17: -7.59 | Z17: -11.1 | AA17: -13.03 | AB17: 0 | AC17: 0 | AD17: 49.87 | AE17: =IF('2025Sep1-2025Sep30CustomUnified'!$C17="order",'2025Sep1-2025Sep30CustomUnified'!$O17,0) -> 77.89 | AF17: =IF('2025Sep1-2025Sep30CustomUnified'!$C17="refund",'2025Sep1-2025Sep30CustomUnified'!$O17,0) -> 0 | AG17: =SUM('2025Sep1-2025Sep30CustomUnified'!$AE17:$AF17) -> 77.89 | AH17: =IF('2025Sep1-2025Sep30CustomUnified'!$C17="order",'2025Sep1-2025Sep30CustomUnified'!$G17,0) -> 1 | AI17: =IF('2025Sep1-2025Sep30CustomUnified'!$C17="refund",-'2025Sep1-2025Sep30CustomUnified'!$G17,0) -> 0 | AJ17: =SUM('2025Sep1-2025Sep30CustomUnified'!$AH17:$AI17) -> 1 | AK17: ='2025Sep1-2025Sep30CustomUnified'!$Z17 -> -11.1 | AL17: ='2025Sep1-2025Sep30CustomUnified'!$AA17+'2025Sep1-2025Sep30CustomUnified'!$W17+'2025Sep1-2025Sep30CustomUnified'!$U17+'2025Sep1-2025Sep30CustomUnified'!$S17+'2025Sep1-2025Sep30CustomUnified'!$Q17 -> -16.92 | AM17: =SUM('2025Sep1-2025Sep30CustomUnified'!$AB17:$AC17) -> 0 | AN17: =SUM('2025Sep1-2025Sep30CustomUnified'!$AK17:$AM17) -> -28.02 | AO17: ='2025Sep1-2025Sep30CustomUnified'!$AG17+'2025Sep1-2025Sep30CustomUnified'!$AN17 -> 49.87
A18: Sep 3, 2025 8:55:48 AM PDT | B18: 24342675541 | C18: Order | D18: 113-0234339-8266669 | E18: RH-DR002MTMW-FBA | F18: Ma'gro Drink Table - Solid Mango Wood Fluted Base with Real White Marble Top | Farmhouse Accent Side Table for Boho Decor, Bedside, Entryway, Plant St | G18: 1 | H18: amazon.com | I18: Standard Orders | J18: Amazon | K18: CHARLOTTE | L18: NC | M18: 28204 | N18: MarketplaceFacilitator | O18: 125.99 | P18: 8.68 | Q18: 0 | R18: 0 | S18: 0 | T18: 0 | U18: 0 | V18: 0 | W18: -6.3 | X18: 0 | Y18: -8.68 | Z18: -17.95 | AA18: -25.95 | AB18: 0 | AC18: 0 | AD18: 75.79 | AE18: =IF('2025Sep1-2025Sep30CustomUnified'!$C18="order",'2025Sep1-2025Sep30CustomUnified'!$O18,0) -> 125.99 | AF18: =IF('2025Sep1-2025Sep30CustomUnified'!$C18="refund",'2025Sep1-2025Sep30CustomUnified'!$O18,0) -> 0 | AG18: =SUM('2025Sep1-2025Sep30CustomUnified'!$AE18:$AF18) -> 125.99 | AH18: =IF('2025Sep1-2025Sep30CustomUnified'!$C18="order",'2025Sep1-2025Sep30CustomUnified'!$G18,0) -> 1 | AI18: =IF('2025Sep1-2025Sep30CustomUnified'!$C18="refund",-'2025Sep1-2025Sep30CustomUnified'!$G18,0) -> 0 | AJ18: =SUM('2025Sep1-2025Sep30CustomUnified'!$AH18:$AI18) -> 1 | AK18: ='2025Sep1-2025Sep30CustomUnified'!$Z18 -> -17.95 | AL18: ='2025Sep1-2025Sep30CustomUnified'!$AA18+'2025Sep1-2025Sep30CustomUnified'!$W18+'2025Sep1-2025Sep30CustomUnified'!$U18+'2025Sep1-2025Sep30CustomUnified'!$S18+'2025Sep1-2025Sep30CustomUnified'!$Q18 -> -32.25 | AM18: =SUM('2025Sep1-2025Sep30CustomUnified'!$AB18:$AC18) -> 0 | AN18: =SUM('2025Sep1-2025Sep30CustomUnified'!$AK18:$AM18) -> -50.2 | AO18: ='2025Sep1-2025Sep30CustomUnified'!$AG18+'2025Sep1-2025Sep30CustomUnified'!$AN18 -> 75.79
A19: Sep 3, 2025 12:25:14 PM PDT | B19: 24342675541 | C19: Order | D19: 113-8182218-6427415 | E19: RH-DR002MTMW-FBA | F19: Ma'gro Drink Table - Solid Mango Wood Fluted Base with Real White Marble Top | Farmhouse Accent Side Table for Boho Decor, Bedside, Entryway, Plant St | G19: 1 | H19: amazon.com | I19: Standard Orders | J19: Amazon | K19: St Cloud | L19: FL | M19: 34771 | N19: MarketplaceFacilitator | O19: 125.99 | P19: 8.98 | Q19: 0 | R19: 0 | S19: 0 | T19: 0 | U19: 0 | V19: 0 | W19: -6.3 | X19: 0 | Y19: -8.98 | Z19: -17.95 | AA19: -25.95 | AB19: 0 | AC19: 0 | AD19: 75.79 | AE19: =IF('2025Sep1-2025Sep30CustomUnified'!$C19="order",'2025Sep1-2025Sep30CustomUnified'!$O19,0) -> 125.99 | AF19: =IF('2025Sep1-2025Sep30CustomUnified'!$C19="refund",'2025Sep1-2025Sep30CustomUnified'!$O19,0) -> 0 | AG19: =SUM('2025Sep1-2025Sep30CustomUnified'!$AE19:$AF19) -> 125.99 | AH19: =IF('2025Sep1-2025Sep30CustomUnified'!$C19="order",'2025Sep1-2025Sep30CustomUnified'!$G19,0) -> 1 | AI19: =IF('2025Sep1-2025Sep30CustomUnified'!$C19="refund",-'2025Sep1-2025Sep30CustomUnified'!$G19,0) -> 0 | AJ19: =SUM('2025Sep1-2025Sep30CustomUnified'!$AH19:$AI19) -> 1 | AK19: ='2025Sep1-2025Sep30CustomUnified'!$Z19 -> -17.95 | AL19: ='2025Sep1-2025Sep30CustomUnified'!$AA19+'2025Sep1-2025Sep30CustomUnified'!$W19+'2025Sep1-2025Sep30CustomUnified'!$U19+'2025Sep1-2025Sep30CustomUnified'!$S19+'2025Sep1-2025Sep30CustomUnified'!$Q19 -> -32.25 | AM19: =SUM('2025Sep1-2025Sep30CustomUnified'!$AB19:$AC19) -> 0 | AN19: =SUM('2025Sep1-2025Sep30CustomUnified'!$AK19:$AM19) -> -50.2 | AO19: ='2025Sep1-2025Sep30CustomUnified'!$AG19+'2025Sep1-2025Sep30CustomUnified'!$AN19 -> 75.79
A20: Sep 4, 2025 1:11:04 AM PDT | B20: 24342675541 | C20: Order | D20: 114-9144832-1165035 | E20: RH-ET042MB(D)-FBA | F20: Stupa Solid Wood End Table - 22" Tall Round Side Table for Living Room or Bedroom, Handcrafted Accent Table in Distressed Black Finish, Easy Assembly, | G20: 1 | H20: amazon.com | I20: Standard Orders | J20: Amazon | K20: HANFORD | L20: CA | M20: 93230 | N20: MarketplaceFacilitator | O20: 129.99 | P20: 10.72 | Q20: 0 | R20: 0 | S20: 0 | T20: 0 | U20: 0 | V20: 0 | W20: 0 | X20: 0 | Y20: -10.72 | Z20: -19.5 | AA20: -16.45 | AB20: 0 | AC20: 0 | AD20: 94.04 | AE20: =IF('2025Sep1-2025Sep30CustomUnified'!$C20="order",'2025Sep1-2025Sep30CustomUnified'!$O20,0) -> 129.99 | AF20: =IF('2025Sep1-2025Sep30CustomUnified'!$C20="refund",'2025Sep1-2025Sep30CustomUnified'!$O20,0) -> 0 | AG20: =SUM('2025Sep1-2025Sep30CustomUnified'!$AE20:$AF20) -> 129.99 | AH20: =IF('2025Sep1-2025Sep30CustomUnified'!$C20="order",'2025Sep1-2025Sep30CustomUnified'!$G20,0) -> 1 | AI20: =IF('2025Sep1-2025Sep30CustomUnified'!$C20="refund",-'2025Sep1-2025Sep30CustomUnified'!$G20,0) -> 0 | AJ20: =SUM('2025Sep1-2025Sep30CustomUnified'!$AH20:$AI20) -> 1 | AK20: ='2025Sep1-2025Sep30CustomUnified'!$Z20 -> -19.5 | AL20: ='2025Sep1-2025Sep30CustomUnified'!$AA20+'2025Sep1-2025Sep30CustomUnified'!$W20+'2025Sep1-2025Sep30CustomUnified'!$U20+'2025Sep1-2025Sep30CustomUnified'!$S20+'2025Sep1-2025Sep30CustomUnified'!$Q20 -> -16.45 | AM20: =SUM('2025Sep1-2025Sep30CustomUnified'!$AB20:$AC20) -> 0 | AN20: =SUM('2025Sep1-2025Sep30CustomUnified'!$AK20:$AM20) -> -35.95 | AO20: ='2025Sep1-2025Sep30CustomUnified'!$AG20+'2025Sep1-2025Sep30CustomUnified'!$AN20 -> 94.04
A21: Sep 4, 2025 2:51:47 AM PDT | B21: 24342675541 | C21: Order | D21: 111-7196463-5953811 | E21: RH-DR002MTMW-FBA | F21: Ma'gro Drink Table - Solid Mango Wood Fluted Base with Real White Marble Top | Farmhouse Accent Side Table for Boho Decor, Bedside, Entryway, Plant St | G21: 1 | H21: amazon.com | I21: Standard Orders | J21: Amazon | K21: MARTINEZ | L21: CA | M21: 94553 | N21: MarketplaceFacilitator | O21: 125.99 | P21: 11.67 | Q21: 0 | R21: 0 | S21: 0 | T21: 0 | U21: 0 | V21: 0 | W21: -6.3 | X21: 0 | Y21: -11.67 | Z21: -17.95 | AA21: -25.95 | AB21: 0 | AC21: 0 | AD21: 75.79 | AE21: =IF('2025Sep1-2025Sep30CustomUnified'!$C21="order",'2025Sep1-2025Sep30CustomUnified'!$O21,0) -> 125.99 | AF21: =IF('2025Sep1-2025Sep30CustomUnified'!$C21="refund",'2025Sep1-2025Sep30CustomUnified'!$O21,0) -> 0 | AG21: =SUM('2025Sep1-2025Sep30CustomUnified'!$AE21:$AF21) -> 125.99 | AH21: =IF('2025Sep1-2025Sep30CustomUnified'!$C21="order",'2025Sep1-2025Sep30CustomUnified'!$G21,0) -> 1 | AI21: =IF('2025Sep1-2025Sep30CustomUnified'!$C21="refund",-'2025Sep1-2025Sep30CustomUnified'!$G21,0) -> 0 | AJ21: =SUM('2025Sep1-2025Sep30CustomUnified'!$AH21:$AI21) -> 1 | AK21: ='2025Sep1-2025Sep30CustomUnified'!$Z21 -> -17.95 | AL21: ='2025Sep1-2025Sep30CustomUnified'!$AA21+'2025Sep1-2025Sep30CustomUnified'!$W21+'2025Sep1-2025Sep30CustomUnified'!$U21+'2025Sep1-2025Sep30CustomUnified'!$S21+'2025Sep1-2025Sep30CustomUnified'!$Q21 -> -32.25 | AM21: =SUM('2025Sep1-2025Sep30CustomUnified'!$AB21:$AC21) -> 0 | AN21: =SUM('2025Sep1-2025Sep30CustomUnified'!$AK21:$AM21) -> -50.2 | AO21: ='2025Sep1-2025Sep30CustomUnified'!$AG21+'2025Sep1-2025Sep30CustomUnified'!$AN21 -> 75.79
A22: Sep 4, 2025 3:08:39 AM PDT | B22: 24342675541 | C22: Order | D22: 111-5607869-4598601 | E22: RH-ET006-FBM | F22: Relso Athena Marble Side Table with Stylish Round White Marble Top | Black Ribbed Base End Table Marble Offers Stability | Compact Design Small Accent | G22: 1 | H22: amazon.com | I22: Standard Orders | J22: Seller | K22: NEWARK | L22: NJ | M22: 07102 | N22: MarketplaceFacilitator | O22: 299.99 | P22: 17.89 | Q22: 0 | R22: 0 | S22: 0 | T22: 0 | U22: 0 | V22: 0 | W22: -30 | X22: 0 | Y22: -17.89 | Z22: -37 | AA22: 0 | AB22: 0 | AC22: 0 | AD22: 232.99 | AE22: =IF('2025Sep1-2025Sep30CustomUnified'!$C22="order",'2025Sep1-2025Sep30CustomUnified'!$O22,0) -> 299.99 | AF22: =IF('2025Sep1-2025Sep30CustomUnified'!$C22="refund",'2025Sep1-2025Sep30CustomUnified'!$O22,0) -> 0 | AG22: =SUM('2025Sep1-2025Sep30CustomUnified'!$AE22:$AF22) -> 299.99 | AH22: =IF('2025Sep1-2025Sep30CustomUnified'!$C22="order",'2025Sep1-2025Sep30CustomUnified'!$G22,0) -> 1 | AI22: =IF('2025Sep1-2025Sep30CustomUnified'!$C22="refund",-'2025Sep1-2025Sep30CustomUnified'!$G22,0) -> 0 | AJ22: =SUM('2025Sep1-2025Sep30CustomUnified'!$AH22:$AI22) -> 1 | AK22: ='2025Sep1-2025Sep30CustomUnified'!$Z22 -> -37 | AL22: ='2025Sep1-2025Sep30CustomUnified'!$AA22+'2025Sep1-2025Sep30CustomUnified'!$W22+'2025Sep1-2025Sep30CustomUnified'!$U22+'2025Sep1-2025Sep30CustomUnified'!$S22+'2025Sep1-2025Sep30CustomUnified'!$Q22 -> -30 | AM22: =SUM('2025Sep1-2025Sep30CustomUnified'!$AB22:$AC22) -> 0 | AN22: =SUM('2025Sep1-2025Sep30CustomUnified'!$AK22:$AM22) -> -67 | AO22: ='2025Sep1-2025Sep30CustomUnified'!$AG22+'2025Sep1-2025Sep30CustomUnified'!$AN22 -> 232.99
A23: Sep 4, 2025 3:13:25 AM PDT | B23: 24342675541 | C23: Order | D23: 114-5516033-7457821 | E23: RH-DR002MTMW-FBA | F23: Ma'gro Drink Table - Solid Mango Wood Fluted Base with Real White Marble Top | Farmhouse Accent Side Table for Boho Decor, Bedside, Entryway, Plant St | G23: 1 | H23: amazon.com | I23: Standard Orders | J23: Amazon | K23: Norman | L23: OK | M23: 73072 | N23: MarketplaceFacilitator | O23: 125.99 | P23: 11.02 | Q23: 0 | R23: 0 | S23: 0 | T23: 0 | U23: 0 | V23: 0 | W23: 0 | X23: 0 | Y23: -11.02 | Z23: -18.9 | AA23: -25.95 | AB23: 0 | AC23: 0 | AD23: 81.14 | AE23: =IF('2025Sep1-2025Sep30CustomUnified'!$C23="order",'2025Sep1-2025Sep30CustomUnified'!$O23,0) -> 125.99 | AF23: =IF('2025Sep1-2025Sep30CustomUnified'!$C23="refund",'2025Sep1-2025Sep30CustomUnified'!$O23,0) -> 0 | AG23: =SUM('2025Sep1-2025Sep30CustomUnified'!$AE23:$AF23) -> 125.99 | AH23: =IF('2025Sep1-2025Sep30CustomUnified'!$C23="order",'2025Sep1-2025Sep30CustomUnified'!$G23,0) -> 1 | AI23: =IF('2025Sep1-2025Sep30CustomUnified'!$C23="refund",-'2025Sep1-2025Sep30CustomUnified'!$G23,0) -> 0 | AJ23: =SUM('2025Sep1-2025Sep30CustomUnified'!$AH23:$AI23) -> 1 | AK23: ='2025Sep1-2025Sep30CustomUnified'!$Z23 -> -18.9 | AL23: ='2025Sep1-2025Sep30CustomUnified'!$AA23+'2025Sep1-2025Sep30CustomUnified'!$W23+'2025Sep1-2025Sep30CustomUnified'!$U23+'2025Sep1-2025Sep30CustomUnified'!$S23+'2025Sep1-2025Sep30CustomUnified'!$Q23 -> -25.95 | AM23: =SUM('2025Sep1-2025Sep30CustomUnified'!$AB23:$AC23) -> 0 | AN23: =SUM('2025Sep1-2025Sep30CustomUnified'!$AK23:$AM23) -> -44.85 | AO23: ='2025Sep1-2025Sep30CustomUnified'!$AG23+'2025Sep1-2025Sep30CustomUnified'!$AN23 -> 81.14
A24: Sep 4, 2025 4:52:48 AM PDT | B24: 24342675541 | C24: Order | D24: 111-8470975-6821037 | E24: RH-ET003-N-FBA | F24: Relso Gaia Round End Table for Living Room and Farmhouse | Solid Mango Wood for Rustic Elegance | Ideal for Side Tables, Nightstands & More | Wood Sid | G24: 1 | H24: amazon.com | I24: Standard Orders | J24: Amazon | K24: PLYMOUTH | L24: MN | M24: 55446 | N24: MarketplaceFacilitator | O24: 219.99 | P24: 17.82 | Q24: 0 | R24: 0 | S24: 0 | T24: 0 | U24: 0 | V24: 0 | W24: -11 | X24: 0 | Y24: -17.82 | Z24: -30.9 | AA24: -21.39 | AB24: 0 | AC24: 0 | AD24: 156.7 | AE24: =IF('2025Sep1-2025Sep30CustomUnified'!$C24="order",'2025Sep1-2025Sep30CustomUnified'!$O24,0) -> 219.99 | AF24: =IF('2025Sep1-2025Sep30CustomUnified'!$C24="refund",'2025Sep1-2025Sep30CustomUnified'!$O24,0) -> 0 | AG24: =SUM('2025Sep1-2025Sep30CustomUnified'!$AE24:$AF24) -> 219.99 | AH24: =IF('2025Sep1-2025Sep30CustomUnified'!$C24="order",'2025Sep1-2025Sep30CustomUnified'!$G24,0) -> 1 | AI24: =IF('2025Sep1-2025Sep30CustomUnified'!$C24="refund",-'2025Sep1-2025Sep30CustomUnified'!$G24,0) -> 0 | AJ24: =SUM('2025Sep1-2025Sep30CustomUnified'!$AH24:$AI24) -> 1 | AK24: ='2025Sep1-2025Sep30CustomUnified'!$Z24 -> -30.9 | AL24: ='2025Sep1-2025Sep30CustomUnified'!$AA24+'2025Sep1-2025Sep30CustomUnified'!$W24+'2025Sep1-2025Sep30CustomUnified'!$U24+'2025Sep1-2025Sep30CustomUnified'!$S24+'2025Sep1-2025Sep30CustomUnified'!$Q24 -> -32.39 | AM24: =SUM('2025Sep1-2025Sep30CustomUnified'!$AB24:$AC24) -> 0 | AN24: =SUM('2025Sep1-2025Sep30CustomUnified'!$AK24:$AM24) -> -63.29 | AO24: ='2025Sep1-2025Sep30CustomUnified'!$AG24+'2025Sep1-2025Sep30CustomUnified'!$AN24 -> 156.7
A25: Sep 4, 2025 10:39:47 AM PDT | B25: 24342675541 | C25: Order | D25: 113-3183692-7519425 | E25: RH-ET042MW-FBA | F25: Relso Stupa Solid Wood End Table - 22" Tall Round Side Table for Living Room or Bedroom, Handcrafted Accent Table in Walnut Finish, Easy Assembly, Mod | G25: 1 | H25: amazon.com | I25: Standard Orders | J25: Amazon | K25: BOSSIER CITY | L25: LA | M25: 71111 | N25: MarketplaceFacilitator | O25: 110.49 | P25: 9.71 | Q25: 0 | R25: 0 | S25: 0 | T25: 0 | U25: 0 | V25: 0 | W25: -5.52 | X25: 0 | Y25: -9.71 | Z25: -15.75 | AA25: -16.45 | AB25: 0 | AC25: 0 | AD25: 72.77 | AE25: =IF('2025Sep1-2025Sep30CustomUnified'!$C25="order",'2025Sep1-2025Sep30CustomUnified'!$O25,0) -> 110.49 | AF25: =IF('2025Sep1-2025Sep30CustomUnified'!$C25="refund",'2025Sep1-2025Sep30CustomUnified'!$O25,0) -> 0 | AG25: =SUM('2025Sep1-2025Sep30CustomUnified'!$AE25:$AF25) -> 110.49 | AH25: =IF('2025Sep1-2025Sep30CustomUnified'!$C25="order",'2025Sep1-2025Sep30CustomUnified'!$G25,0) -> 1 | AI25: =IF('2025Sep1-2025Sep30CustomUnified'!$C25="refund",-'2025Sep1-2025Sep30CustomUnified'!$G25,0) -> 0 | AJ25: =SUM('2025Sep1-2025Sep30CustomUnified'!$AH25:$AI25) -> 1 | AK25: ='2025Sep1-2025Sep30CustomUnified'!$Z25 -> -15.75 | AL25: ='2025Sep1-2025Sep30CustomUnified'!$AA25+'2025Sep1-2025Sep30CustomUnified'!$W25+'2025Sep1-2025Sep30CustomUnified'!$U25+'2025Sep1-2025Sep30CustomUnified'!$S25+'2025Sep1-2025Sep30CustomUnified'!$Q25 -> -21.97 | AM25: =SUM('2025Sep1-2025Sep30CustomUnified'!$AB25:$AC25) -> 0 | AN25: =SUM('2025Sep1-2025Sep30CustomUnified'!$AK25:$AM25) -> -37.72 | AO25: ='2025Sep1-2025Sep30CustomUnified'!$AG25+'2025Sep1-2025Sep30CustomUnified'!$AN25 -> 72.77
A26: Sep 5, 2025 8:29:34 PM PDT | B26: 24450080321 | C26: Order | D26: 114-3514505-3681039 | E26: RH-ET042MW-FBA | F26: Relso Stupa Solid Wood End Table - 22" Tall Round Side Table for Living Room or Bedroom, Handcrafted Accent Table in Walnut Finish, Easy Assembly, Mod | G26: 1 | H26: amazon.com | I26: Standard Orders | J26: Amazon | K26: NORTH EAST | L26: MD | M26: 21901 | N26: MarketplaceFacilitator | O26: 110.49 | P26: 6.3 | Q26: 0 | R26: 0 | S26: 0 | T26: 0 | U26: 0 | V26: 0 | W26: -5.52 | X26: 0 | Y26: -6.3 | Z26: -15.75 | AA26: -16.45 | AB26: 0 | AC26: 0 | AD26: 72.77 | AE26: =IF('2025Sep1-2025Sep30CustomUnified'!$C26="order",'2025Sep1-2025Sep30CustomUnified'!$O26,0) -> 110.49 | AF26: =IF('2025Sep1-2025Sep30CustomUnified'!$C26="refund",'2025Sep1-2025Sep30CustomUnified'!$O26,0) -> 0 | AG26: =SUM('2025Sep1-2025Sep30CustomUnified'!$AE26:$AF26) -> 110.49 | AH26: =IF('2025Sep1-2025Sep30CustomUnified'!$C26="order",'2025Sep1-2025Sep30CustomUnified'!$G26,0) -> 1 | AI26: =IF('2025Sep1-2025Sep30CustomUnified'!$C26="refund",-'2025Sep1-2025Sep30CustomUnified'!$G26,0) -> 0 | AJ26: =SUM('2025Sep1-2025Sep30CustomUnified'!$AH26:$AI26) -> 1 | AK26: ='2025Sep1-2025Sep30CustomUnified'!$Z26 -> -15.75 | AL26: ='2025Sep1-2025Sep30CustomUnified'!$AA26+'2025Sep1-2025Sep30CustomUnified'!$W26+'2025Sep1-2025Sep30CustomUnified'!$U26+'2025Sep1-2025Sep30CustomUnified'!$S26+'2025Sep1-2025Sep30CustomUnified'!$Q26 -> -21.97 | AM26: =SUM('2025Sep1-2025Sep30CustomUnified'!$AB26:$AC26) -> 0 | AN26: =SUM('2025Sep1-2025Sep30CustomUnified'!$AK26:$AM26) -> -37.72 | AO26: ='2025Sep1-2025Sep30CustomUnified'!$AG26+'2025Sep1-2025Sep30CustomUnified'!$AN26 -> 72.77
A27: Sep 5, 2025 11:46:19 PM PDT | B27: 24450080321 | C27: Order | D27: 113-4797825-8422632 | E27: RH-DR005MW-FBA | F27: Relso Stambha Solid Wood Drink Table - 24" Tall Round Accent Side Table for Living Room or Bedroom, Narrow End Table or Indoor Plant Stand, Walnut Fin | G27: 1 | H27: amazon.com | I27: Standard Orders | J27: Amazon | K27: MENASHA | L27: WI | M27: 54952 | N27: MarketplaceFacilitator | O27: 0 | P27: 0 | Q27: 0 | R27: 0 | S27: 0 | T27: 0 | U27: 0 | V27: 0 | W27: 0 | X27: 0 | Y27: 0 | Z27: 0 | AA27: 0 | AB27: 0 | AC27: 0 | AD27: 0 | AE27: =IF('2025Sep1-2025Sep30CustomUnified'!$C27="order",'2025Sep1-2025Sep30CustomUnified'!$O27,0) -> 0 | AF27: =IF('2025Sep1-2025Sep30CustomUnified'!$C27="refund",'2025Sep1-2025Sep30CustomUnified'!$O27,0) -> 0 | AG27: =SUM('2025Sep1-2025Sep30CustomUnified'!$AE27:$AF27) -> 0 | AH27: =IF('2025Sep1-2025Sep30CustomUnified'!$C27="order",'2025Sep1-2025Sep30CustomUnified'!$G27,0) -> 1 | AI27: =IF('2025Sep1-2025Sep30CustomUnified'!$C27="refund",-'2025Sep1-2025Sep30CustomUnified'!$G27,0) -> 0 | AJ27: =SUM('2025Sep1-2025Sep30CustomUnified'!$AH27:$AI27) -> 1 | AK27: ='2025Sep1-2025Sep30CustomUnified'!$Z27 -> 0 | AL27: ='2025Sep1-2025Sep30CustomUnified'!$AA27+'2025Sep1-2025Sep30CustomUnified'!$W27+'2025Sep1-2025Sep30CustomUnified'!$U27+'2025Sep1-2025Sep30CustomUnified'!$S27+'2025Sep1-2025Sep30CustomUnified'!$Q27 -> 0 | AM27: =SUM('2025Sep1-2025Sep30CustomUnified'!$AB27:$AC27) -> 0 | AN27: =SUM('2025Sep1-2025Sep30CustomUnified'!$AK27:$AM27) -> 0 | AO27: ='2025Sep1-2025Sep30CustomUnified'!$AG27+'2025Sep1-2025Sep30CustomUnified'!$AN27 -> 0
A28: Sep 6, 2025 2:32:35 AM PDT | B28: 24450080321 | C28: Order | D28: 114-5087639-6957025 | E28: RH-DR002MTMW-FBA | F28: Ma'gro Drink Table - Solid Mango Wood Fluted Base with Real White Marble Top | Farmhouse Accent Side Table for Boho Decor, Bedside, Entryway, Plant St | G28: 1 | H28: amazon.com | I28: Standard Orders | J28: Amazon | K28: BROOKLYN | L28: NY | M28: 11213 | N28: MarketplaceFacilitator | O28: 125.99 | P28: 11.18 | Q28: 0 | R28: 0 | S28: 0 | T28: 0 | U28: 0 | V28: 0 | W28: 0 | X28: 0 | Y28: -11.18 | Z28: -18.9 | AA28: -25.95 | AB28: 0 | AC28: 0 | AD28: 81.14 | AE28: =IF('2025Sep1-2025Sep30CustomUnified'!$C28="order",'2025Sep1-2025Sep30CustomUnified'!$O28,0) -> 125.99 | AF28: =IF('2025Sep1-2025Sep30CustomUnified'!$C28="refund",'2025Sep1-2025Sep30CustomUnified'!$O28,0) -> 0 | AG28: =SUM('2025Sep1-2025Sep30CustomUnified'!$AE28:$AF28) -> 125.99 | AH28: =IF('2025Sep1-2025Sep30CustomUnified'!$C28="order",'2025Sep1-2025Sep30CustomUnified'!$G28,0) -> 1 | AI28: =IF('2025Sep1-2025Sep30CustomUnified'!$C28="refund",-'2025Sep1-2025Sep30CustomUnified'!$G28,0) -> 0 | AJ28: =SUM('2025Sep1-2025Sep30CustomUnified'!$AH28:$AI28) -> 1 | AK28: ='2025Sep1-2025Sep30CustomUnified'!$Z28 -> -18.9 | AL28: ='2025Sep1-2025Sep30CustomUnified'!$AA28+'2025Sep1-2025Sep30CustomUnified'!$W28+'2025Sep1-2025Sep30CustomUnified'!$U28+'2025Sep1-2025Sep30CustomUnified'!$S28+'2025Sep1-2025Sep30CustomUnified'!$Q28 -> -25.95 | AM28: =SUM('2025Sep1-2025Sep30CustomUnified'!$AB28:$AC28) -> 0 | AN28: =SUM('2025Sep1-2025Sep30CustomUnified'!$AK28:$AM28) -> -44.85 | AO28: ='2025Sep1-2025Sep30CustomUnified'!$AG28+'2025Sep1-2025Sep30CustomUnified'!$AN28 -> 81.14
A29: Sep 6, 2025 7:01:57 AM PDT | B29: 24450080321 | C29: Order | D29: 113-3003677-5688227 | E29: RH-DR001MW-FBA | F29: Enteka Solid Mango Wood Drink Table - 24" Tall Accent Side Table with Walnut Finish | Handcrafted, No Assembly Required | Perfect for Modern Living Ro | G29: 1 | H29: amazon.com | I29: Standard Orders | J29: Amazon | K29: AUSTIN | L29: TX | M29: 78738 | N29: MarketplaceFacilitator | O29: 113.39 | P29: 9.35 | Q29: 0 | R29: 0 | S29: 0 | T29: 0 | U29: 0 | V29: 0 | W29: 0 | X29: 0 | Y29: -9.35 | Z29: -17.01 | AA29: -24.43 | AB29: 0 | AC29: 0 | AD29: 71.95 | AE29: =IF('2025Sep1-2025Sep30CustomUnified'!$C29="order",'2025Sep1-2025Sep30CustomUnified'!$O29,0) -> 113.39 | AF29: =IF('2025Sep1-2025Sep30CustomUnified'!$C29="refund",'2025Sep1-2025Sep30CustomUnified'!$O29,0) -> 0 | AG29: =SUM('2025Sep1-2025Sep30CustomUnified'!$AE29:$AF29) -> 113.39 | AH29: =IF('2025Sep1-2025Sep30CustomUnified'!$C29="order",'2025Sep1-2025Sep30CustomUnified'!$G29,0) -> 1 | AI29: =IF('2025Sep1-2025Sep30CustomUnified'!$C29="refund",-'2025Sep1-2025Sep30CustomUnified'!$G29,0) -> 0 | AJ29: =SUM('2025Sep1-2025Sep30CustomUnified'!$AH29:$AI29) -> 1 | AK29: ='2025Sep1-2025Sep30CustomUnified'!$Z29 -> -17.01 | AL29: ='2025Sep1-2025Sep30CustomUnified'!$AA29+'2025Sep1-2025Sep30CustomUnified'!$W29+'2025Sep1-2025Sep30CustomUnified'!$U29+'2025Sep1-2025Sep30CustomUnified'!$S29+'2025Sep1-2025Sep30CustomUnified'!$Q29 -> -24.43 | AM29: =SUM('2025Sep1-2025Sep30CustomUnified'!$AB29:$AC29) -> 0 | AN29: =SUM('2025Sep1-2025Sep30CustomUnified'!$AK29:$AM29) -> -41.44 | AO29: ='2025Sep1-2025Sep30CustomUnified'!$AG29+'2025Sep1-2025Sep30CustomUnified'!$AN29 -> 71.95
A30: Sep 6, 2025 2:22:50 PM PDT | B30: 24450080321 | C30: Refund | D30: 111-0008355-4040228 | E30: RH-ET003-N-FBA | F30: Relso Gaia Round End Table for Living Room and Farmhouse | Solid Mango Wood for Rustic Elegance | Ideal for Side Tables, Nightstands & More | Wood Sid | G30: 1 | H30: amazon.com | I30: Standard Orders | J30: Amazon | K30: LOS ANGELES | L30: CA | M30: 90036 | N30: MarketplaceFacilitator | O30: -219.89 | P30: -21.44 | Q30: 0 | R30: 0 | S30: 0 | T30: 0 | U30: 0 | V30: 0 | W30: 0 | X30: 0 | Y30: 21.44 | Z30: 26.99 | AA30: 0 | AB30: 0 | AC30: 0 | AD30: -192.9 | AE30: =IF('2025Sep1-2025Sep30CustomUnified'!$C30="order",'2025Sep1-2025Sep30CustomUnified'!$O30,0) -> 0 | AF30: =IF('2025Sep1-2025Sep30CustomUnified'!$C30="refund",'2025Sep1-2025Sep30CustomUnified'!$O30,0) -> -219.89 | AG30: =SUM('2025Sep1-2025Sep30CustomUnified'!$AE30:$AF30) -> -219.89 | AH30: =IF('2025Sep1-2025Sep30CustomUnified'!$C30="order",'2025Sep1-2025Sep30CustomUnified'!$G30,0) -> 0 | AI30: =IF('2025Sep1-2025Sep30CustomUnified'!$C30="refund",-'2025Sep1-2025Sep30CustomUnified'!$G30,0) -> -1 | AJ30: =SUM('2025Sep1-2025Sep30CustomUnified'!$AH30:$AI30) -> -1 | AK30: ='2025Sep1-2025Sep30CustomUnified'!$Z30 -> 26.99 | AL30: ='2025Sep1-2025Sep30CustomUnified'!$AA30+'2025Sep1-2025Sep30CustomUnified'!$W30+'2025Sep1-2025Sep30CustomUnified'!$U30+'2025Sep1-2025Sep30CustomUnified'!$S30+'2025Sep1-2025Sep30CustomUnified'!$Q30 -> 0 | AM30: =SUM('2025Sep1-2025Sep30CustomUnified'!$AB30:$AC30) -> 0 | AN30: =SUM('2025Sep1-2025Sep30CustomUnified'!$AK30:$AM30) -> 26.99 | AO30: ='2025Sep1-2025Sep30CustomUnified'!$AG30+'2025Sep1-2025Sep30CustomUnified'!$AN30 -> -192.9
A31: Sep 7, 2025 1:14:12 AM PDT | B31: 24450080321 | C31: Refund | D31: 114-3052582-0653001 | E31: RH-ET003-N-FBA | F31: Relso Gaia Round End Table for Living Room and Farmhouse | Solid Mango Wood for Rustic Elegance | Ideal for Side Tables, Nightstands & More | Wood Sid | G31: 1 | H31: amazon.com | I31: Standard Orders | J31: Amazon | K31: NEW YORK | L31: NY | M31: 10003 | N31: MarketplaceFacilitator | O31: -219.99 | P31: -18.55 | Q31: 0 | R31: 0 | S31: 0 | T31: 0 | U31: 0 | V31: 0 | W31: 11 | X31: 0 | Y31: 18.55 | Z31: 25.9 | AA31: 0 | AB31: 0 | AC31: 0 | AD31: -183.09 | AE31: =IF('2025Sep1-2025Sep30CustomUnified'!$C31="order",'2025Sep1-2025Sep30CustomUnified'!$O31,0) -> 0 | AF31: =IF('2025Sep1-2025Sep30CustomUnified'!$C31="refund",'2025Sep1-2025Sep30CustomUnified'!$O31,0) -> -219.99 | AG31: =SUM('2025Sep1-2025Sep30CustomUnified'!$AE31:$AF31) -> -219.99 | AH31: =IF('2025Sep1-2025Sep30CustomUnified'!$C31="order",'2025Sep1-2025Sep30CustomUnified'!$G31,0) -> 0 | AI31: =IF('2025Sep1-2025Sep30CustomUnified'!$C31="refund",-'2025Sep1-2025Sep30CustomUnified'!$G31,0) -> -1 | AJ31: =SUM('2025Sep1-2025Sep30CustomUnified'!$AH31:$AI31) -> -1 | AK31: ='2025Sep1-2025Sep30CustomUnified'!$Z31 -> 25.9 | AL31: ='2025Sep1-2025Sep30CustomUnified'!$AA31+'2025Sep1-2025Sep30CustomUnified'!$W31+'2025Sep1-2025Sep30CustomUnified'!$U31+'2025Sep1-2025Sep30CustomUnified'!$S31+'2025Sep1-2025Sep30CustomUnified'!$Q31 -> 11 | AM31: =SUM('2025Sep1-2025Sep30CustomUnified'!$AB31:$AC31) -> 0 | AN31: =SUM('2025Sep1-2025Sep30CustomUnified'!$AK31:$AM31) -> 36.9 | AO31: ='2025Sep1-2025Sep30CustomUnified'!$AG31+'2025Sep1-2025Sep30CustomUnified'!$AN31 -> -183.09
A32: Sep 7, 2025 2:28:33 AM PDT | B32: 24450080321 | C32: Order | D32: 114-5669983-4873035 | E32: RH-ET041MN-FBA | F32: Bambos End Table | Sold Mango Wood Bedside Table, Natural Finish Side Table for Living Room, Bedroom, Entryway | Handcrafted Nightstand, Easy Assembly | G32: 1 | H32: amazon.com | I32: Standard Orders | J32: Amazon | K32: SAN DIEGO | L32: CA | M32: 92131 | N32: MarketplaceFacilitator | O32: 179.99 | P32: 13.25 | Q32: 0 | R32: 0 | S32: 0 | T32: 0 | U32: 0 | V32: 0 | W32: -9 | X32: 0 | Y32: -13.25 | Z32: -25.65 | AA32: -21.77 | AB32: 0 | AC32: 0 | AD32: 123.57 | AE32: =IF('2025Sep1-2025Sep30CustomUnified'!$C32="order",'2025Sep1-2025Sep30CustomUnified'!$O32,0) -> 179.99 | AF32: =IF('2025Sep1-2025Sep30CustomUnified'!$C32="refund",'2025Sep1-2025Sep30CustomUnified'!$O32,0) -> 0 | AG32: =SUM('2025Sep1-2025Sep30CustomUnified'!$AE32:$AF32) -> 179.99 | AH32: =IF('2025Sep1-2025Sep30CustomUnified'!$C32="order",'2025Sep1-2025Sep30CustomUnified'!$G32,0) -> 1 | AI32: =IF('2025Sep1-2025Sep30CustomUnified'!$C32="refund",-'2025Sep1-2025Sep30CustomUnified'!$G32,0) -> 0 | AJ32: =SUM('2025Sep1-2025Sep30CustomUnified'!$AH32:$AI32) -> 1 | AK32: ='2025Sep1-2025Sep30CustomUnified'!$Z32 -> -25.65 | AL32: ='2025Sep1-2025Sep30CustomUnified'!$AA32+'2025Sep1-2025Sep30CustomUnified'!$W32+'2025Sep1-2025Sep30CustomUnified'!$U32+'2025Sep1-2025Sep30CustomUnified'!$S32+'2025Sep1-2025Sep30CustomUnified'!$Q32 -> -30.77 | AM32: =SUM('2025Sep1-2025Sep30CustomUnified'!$AB32:$AC32) -> 0 | AN32: =SUM('2025Sep1-2025Sep30CustomUnified'!$AK32:$AM32) -> -56.42 | AO32: ='2025Sep1-2025Sep30CustomUnified'!$AG32+'2025Sep1-2025Sep30CustomUnified'!$AN32 -> 123.57
A33: Sep 7, 2025 5:37:52 AM PDT | B33: 24450080321 | C33: Order | D33: 111-1583116-9677067 | E33: RH-ET042MW-FBA | F33: Relso Stupa Solid Wood End Table - 22" Tall Round Side Table for Living Room or Bedroom, Handcrafted Accent Table in Walnut Finish, Easy Assembly, Mod | G33: 1 | H33: amazon.com | I33: Standard Orders | J33: Amazon | K33: OAK PARK | L33: CA | M33: 91377 | N33: MarketplaceFacilitator | O33: 129.99 | P33: 8.95 | Q33: 0 | R33: 0 | S33: 0 | T33: 0 | U33: 0 | V33: 0 | W33: -6.5 | X33: 0 | Y33: -8.95 | Z33: -18.52 | AA33: -16.45 | AB33: 0 | AC33: 0 | AD33: 88.52 | AE33: =IF('2025Sep1-2025Sep30CustomUnified'!$C33="order",'2025Sep1-2025Sep30CustomUnified'!$O33,0) -> 129.99 | AF33: =IF('2025Sep1-2025Sep30CustomUnified'!$C33="refund",'2025Sep1-2025Sep30CustomUnified'!$O33,0) -> 0 | AG33: =SUM('2025Sep1-2025Sep30CustomUnified'!$AE33:$AF33) -> 129.99 | AH33: =IF('2025Sep1-2025Sep30CustomUnified'!$C33="order",'2025Sep1-2025Sep30CustomUnified'!$G33,0) -> 1 | AI33: =IF('2025Sep1-2025Sep30CustomUnified'!$C33="refund",-'2025Sep1-2025Sep30CustomUnified'!$G33,0) -> 0 | AJ33: =SUM('2025Sep1-2025Sep30CustomUnified'!$AH33:$AI33) -> 1 | AK33: ='2025Sep1-2025Sep30CustomUnified'!$Z33 -> -18.52 | AL33: ='2025Sep1-2025Sep30CustomUnified'!$AA33+'2025Sep1-2025Sep30CustomUnified'!$W33+'2025Sep1-2025Sep30CustomUnified'!$U33+'2025Sep1-2025Sep30CustomUnified'!$S33+'2025Sep1-2025Sep30CustomUnified'!$Q33 -> -22.95 | AM33: =SUM('2025Sep1-2025Sep30CustomUnified'!$AB33:$AC33) -> 0 | AN33: =SUM('2025Sep1-2025Sep30CustomUnified'!$AK33:$AM33) -> -41.47 | AO33: ='2025Sep1-2025Sep30CustomUnified'!$AG33+'2025Sep1-2025Sep30CustomUnified'!$AN33 -> 88.52
A34: Sep 7, 2025 6:14:58 AM PDT | B34: 24450080321 | C34: Order | D34: 114-3052582-0653001 | E34: RH-ET003-N-FBA | F34: Relso Gaia Round End Table for Living Room and Farmhouse | Solid Mango Wood for Rustic Elegance | Ideal for Side Tables, Nightstands & More | Wood Sid | G34: 1 | H34: amazon.com | I34: Standard Orders | J34: Amazon | K34: NEW YORK | L34: NY | M34: 10003 | N34: MarketplaceFacilitator | O34: 219.99 | P34: 18.55 | Q34: 0 | R34: 0 | S34: 0 | T34: 0 | U34: 0 | V34: 0 | W34: -11 | X34: 0 | Y34: -18.55 | Z34: -30.9 | AA34: -21.39 | AB34: 0 | AC34: 0 | AD34: 156.7 | AE34: =IF('2025Sep1-2025Sep30CustomUnified'!$C34="order",'2025Sep1-2025Sep30CustomUnified'!$O34,0) -> 219.99 | AF34: =IF('2025Sep1-2025Sep30CustomUnified'!$C34="refund",'2025Sep1-2025Sep30CustomUnified'!$O34,0) -> 0 | AG34: =SUM('2025Sep1-2025Sep30CustomUnified'!$AE34:$AF34) -> 219.99 | AH34: =IF('2025Sep1-2025Sep30CustomUnified'!$C34="order",'2025Sep1-2025Sep30CustomUnified'!$G34,0) -> 1 | AI34: =IF('2025Sep1-2025Sep30CustomUnified'!$C34="refund",-'2025Sep1-2025Sep30CustomUnified'!$G34,0) -> 0 | AJ34: =SUM('2025Sep1-2025Sep30CustomUnified'!$AH34:$AI34) -> 1 | AK34: ='2025Sep1-2025Sep30CustomUnified'!$Z34 -> -30.9 | AL34: ='2025Sep1-2025Sep30CustomUnified'!$AA34+'2025Sep1-2025Sep30CustomUnified'!$W34+'2025Sep1-2025Sep30CustomUnified'!$U34+'2025Sep1-2025Sep30CustomUnified'!$S34+'2025Sep1-2025Sep30CustomUnified'!$Q34 -> -32.39 | AM34: =SUM('2025Sep1-2025Sep30CustomUnified'!$AB34:$AC34) -> 0 | AN34: =SUM('2025Sep1-2025Sep30CustomUnified'!$AK34:$AM34) -> -63.29 | AO34: ='2025Sep1-2025Sep30CustomUnified'!$AG34+'2025Sep1-2025Sep30CustomUnified'!$AN34 -> 156.7
... A36: Sep 8, 2025 7:35:36 AM PDT | B36: 24450080321 | C36: Order | D36: 114-7101013-4048203 | E36: RH-DR005MW-FBA | F36: Relso Stambha Solid Wood Drink Table - 24" Tall Round Accent Side Table for Living Room or Bedroom, Narrow End Table or Indoor Plant Stand, Walnut Fin | G36: 1 | H36: amazon.com | I36: Standard Orders | J36: Amazon | K36: UNIONTOWN | L36: PA | M36: 15401 | N36: MarketplaceFacilitator | O36: 94.99 | P36: 5.7 | Q36: 0 | R36: 0 | S36: 0 | T36: 0 | U36: 0 | V36: 0 | W36: 0 | X36: 0 | Y36: -5.7 | Z36: -14.25 | AA36: -13.03 | AB36: 0 | AC36: 0 | AD36: 67.71 | AE36: =IF('2025Sep1-2025Sep30CustomUnified'!$C36="order",'2025Sep1-2025Sep30CustomUnified'!$O36,0) -> 94.99 | AF36: =IF('2025Sep1-2025Sep30CustomUnified'!$C36="refund",'2025Sep1-2025Sep30CustomUnified'!$O36,0) -> 0 | AG36: =SUM('2025Sep1-2025Sep30CustomUnified'!$AE36:$AF36) -> 94.99 | AH36: =IF('2025Sep1-2025Sep30CustomUnified'!$C36="order",'2025Sep1-2025Sep30CustomUnified'!$G36,0) -> 1 | AI36: =IF('2025Sep1-2025Sep30CustomUnified'!$C36="refund",-'2025Sep1-2025Sep30CustomUnified'!$G36,0) -> 0 | AJ36: =SUM('2025Sep1-2025Sep30CustomUnified'!$AH36:$AI36) -> 1 | AK36: ='2025Sep1-2025Sep30CustomUnified'!$Z36 -> -14.25 | AL36: ='2025Sep1-2025Sep30CustomUnified'!$AA36+'2025Sep1-2025Sep30CustomUnified'!$W36+'2025Sep1-2025Sep30CustomUnified'!$U36+'2025Sep1-2025Sep30CustomUnified'!$S36+'2025Sep1-2025Sep30CustomUnified'!$Q36 -> -13.03 | AM36: =SUM('2025Sep1-2025Sep30CustomUnified'!$AB36:$AC36) -> 0 | AN36: =SUM('2025Sep1-2025Sep30CustomUnified'!$AK36:$AM36) -> -27.28 | AO36: ='2025Sep1-2025Sep30CustomUnified'!$AG36+'2025Sep1-2025Sep30CustomUnified'!$AN36 -> 67.71
A37: Sep 8, 2025 8:27:11 AM PDT | B37: 24450080321 | C37: Order | D37: 112-6513769-1499442 | E37: RH-ET042MW-FBA | F37: Relso Stupa Solid Wood End Table - 22" Tall Round Side Table for Living Room or Bedroom, Handcrafted Accent Table in Walnut Finish, Easy Assembly, Mod | G37: 1 | H37: amazon.com | I37: Standard Orders | J37: Amazon | K37: NORTH BRUNSWICK | L37: NJ | M37: 08902 | N37: MarketplaceFacilitator | O37: 110.49 | P37: 6.95 | Q37: 0 | R37: 0 | S37: 0 | T37: 0 | U37: 0 | V37: 0 | W37: -5.52 | X37: 0 | Y37: -6.95 | Z37: -15.75 | AA37: -16.45 | AB37: 0 | AC37: 0 | AD37: 72.77 | AE37: =IF('2025Sep1-2025Sep30CustomUnified'!$C37="order",'2025Sep1-2025Sep30CustomUnified'!$O37,0) -> 110.49 | AF37: =IF('2025Sep1-2025Sep30CustomUnified'!$C37="refund",'2025Sep1-2025Sep30CustomUnified'!$O37,0) -> 0 | AG37: =SUM('2025Sep1-2025Sep30CustomUnified'!$AE37:$AF37) -> 110.49 | AH37: =IF('2025Sep1-2025Sep30CustomUnified'!$C37="order",'2025Sep1-2025Sep30CustomUnified'!$G37,0) -> 1 | AI37: =IF('2025Sep1-2025Sep30CustomUnified'!$C37="refund",-'2025Sep1-2025Sep30CustomUnified'!$G37,0) -> 0 | AJ37: =SUM('2025Sep1-2025Sep30CustomUnified'!$AH37:$AI37) -> 1 | AK37: ='2025Sep1-2025Sep30CustomUnified'!$Z37 -> -15.75 | AL37: ='2025Sep1-2025Sep30CustomUnified'!$AA37+'2025Sep1-2025Sep30CustomUnified'!$W37+'2025Sep1-2025Sep30CustomUnified'!$U37+'2025Sep1-2025Sep30CustomUnified'!$S37+'2025Sep1-2025Sep30CustomUnified'!$Q37 -> -21.97 | AM37: =SUM('2025Sep1-2025Sep30CustomUnified'!$AB37:$AC37) -> 0 | AN37: =SUM('2025Sep1-2025Sep30CustomUnified'!$AK37:$AM37) -> -37.72 | AO37: ='2025Sep1-2025Sep30CustomUnified'!$AG37+'2025Sep1-2025Sep30CustomUnified'!$AN37 -> 72.77
A38: Sep 8, 2025 8:32:10 AM PDT | B38: 24450080321 | C38: Order | D38: 111-4008897-3173847 | E38: RH-ET042MW-FBA | F38: Relso Stupa Solid Wood End Table - 22" Tall Round Side Table for Living Room or Bedroom, Handcrafted Accent Table in Walnut Finish, Easy Assembly, Mod | G38: 1 | H38: amazon.com | I38: Standard Orders | J38: Amazon | K38: BETHLEHEM | L38: PA | M38: 18015 | N38: MarketplaceFacilitator | O38: 129.99 | P38: 7.8 | Q38: 0 | R38: 0 | S38: 0 | T38: 0 | U38: 0 | V38: 0 | W38: 0 | X38: 0 | Y38: -15.6 | Z38: -39 | AA38: -16.45 | AB38: 0 | AC38: 0 | AD38: 66.74 | AE38: =IF('2025Sep1-2025Sep30CustomUnified'!$C38="order",'2025Sep1-2025Sep30CustomUnified'!$O38,0) -> 129.99 | AF38: =IF('2025Sep1-2025Sep30CustomUnified'!$C38="refund",'2025Sep1-2025Sep30CustomUnified'!$O38,0) -> 0 | AG38: =SUM('2025Sep1-2025Sep30CustomUnified'!$AE38:$AF38) -> 129.99 | AH38: =IF('2025Sep1-2025Sep30CustomUnified'!$C38="order",'2025Sep1-2025Sep30CustomUnified'!$G38,0) -> 1 | AI38: =IF('2025Sep1-2025Sep30CustomUnified'!$C38="refund",-'2025Sep1-2025Sep30CustomUnified'!$G38,0) -> 0 | AJ38: =SUM('2025Sep1-2025Sep30CustomUnified'!$AH38:$AI38) -> 1 | AK38: ='2025Sep1-2025Sep30CustomUnified'!$Z38 -> -39 | AL38: ='2025Sep1-2025Sep30CustomUnified'!$AA38+'2025Sep1-2025Sep30CustomUnified'!$W38+'2025Sep1-2025Sep30CustomUnified'!$U38+'2025Sep1-2025Sep30CustomUnified'!$S38+'2025Sep1-2025Sep30CustomUnified'!$Q38 -> -16.45 | AM38: =SUM('2025Sep1-2025Sep30CustomUnified'!$AB38:$AC38) -> 0 | AN38: =SUM('2025Sep1-2025Sep30CustomUnified'!$AK38:$AM38) -> -55.45 | AO38: ='2025Sep1-2025Sep30CustomUnified'!$AG38+'2025Sep1-2025Sep30CustomUnified'!$AN38 -> 74.54
